Workbook

Sheet HD0. Trang chủ
A1: ITTs SOP TEMP
A2: Sheet tổng quan vận hành. Số liệu tự cập nhật.
A4: PRE-SALES (Phase 1-4)
A5: Tổng lead | C5: Lead mới chưa LH | E5: Đã đăng ký | G5: Doanh thu đã thu
A6: =COUNTA('DL02. Khách tiềm năng'!A4:A500) -> 20 | C6: =COUNTIF('DL02. Khách tiềm năng'!P4:P500,"new*") -> 2 | E6: =COUNTIF('DL06. Đăng ký'!F4:F500,"confirmed*") -> 14 | G6: =SUM('DL07. Thanh toán'!H4:H500) -> 218000000
A7: Tất cả lead | C7: =HYPERLINK("#'CH2. Tham số & Quy tắc'!A"&MATCH("slaLRT_minutes",'CH2. Tham số & Quy tắc'!$A:$A,0),"SLA gọi "&slaLRT_minutes&" phút") -> SLA gọi 15 phút | E7: Đăng ký đã xác nhận | G7: Tiền thực nhận
A8: VẬN HÀNH HỌC (Phase 5-10)
A9: HV đang học | C9: HV nguy cơ | E9: Lớp đang chạy | G9: Khiếu nại chưa xử lý
A10: =COUNTIF('DL09. Học viên'!O4:O500,"active*") -> 11 | C10: =COUNTIF('DL09. Học viên'!R4:R500,"at_risk*")+COUNTIF('DL09. Học viên'!R4:R500,"off_track*")+COUNTIF('DL09. Học viên'!S4:S500,"at_risk*")+COUNTIF('DL09. Học viên'!S4:S500,"off_track*") -> 4 | E10: =COUNTIF('DL10. Lớp học'!K4:K500,"in_progress*") -> 4 | G10: =COUNTIF('DL17. Khiếu nại'!J4:J500,"new*")+COUNTIF('DL17. Khiếu nại'!J4:J500,"assigned*")+COUNTIF('DL17. Khiếu nại'!J4:J500,"in_progress*")+COUNTIF('DL17. Khiếu nại'!J4:J500,"escalated*") -> 4
A11: HV đang học | C11: 2 trục, cần can thiệp | E11: Lớp đang chạy | G11: Khiếu nại đang mở
A12: VIỆC CẦN LÀM HÔM NAY
A13: Task sheet | B13: Nội dung | C13: Số lượng | D13: Mở
A14: VH5. Lead cần liên hệ lại | B14: Lead cần liên hệ | C14: =COUNTIF('DL02. Khách tiềm năng'!Q4:Q500,"<="&TODAY()+1) -> 3 | D14: =HYPERLINK("#'VH5. Việc - Chăm khách'!A1","Mở") -> Mở
A15: VH6. HV nguy cơ | B15: HV cần can thiệp | C15: =COUNTIF('DL09. Học viên'!R4:R500,"at_risk*")+COUNTIF('DL09. Học viên'!R4:R500,"off_track*") -> 2 | D15: =HYPERLINK("#'VH6. Việc - Học viên nguy cơ'!A1","Mở") -> Mở
A16: VH7. Test chờ chấm | B16: Test chưa có kết quả | C16: =COUNTIF('DL03. Đặt lịch test'!J4:J500,"pending*") -> 1 | D16: =HYPERLINK("#'VH7. Việc - Test chờ chấm'!A1","Mở") -> Mở
A17: VH8. Học phí đến hạn | B17: Học phí chờ thu | C17: =COUNTIF('DL06. Đăng ký'!P4:P500,"partial*")+COUNTIF('DL06. Đăng ký'!P4:P500,"unpaid*") -> 4 | D17: =HYPERLINK("#'VH8. Việc - Thu học phí'!A1","Mở") -> Mở
A18: VH9. Lớp sắp khai giảng | B18: =HYPERLINK("#'CH2. Tham số & Quy tắc'!A"&MATCH("thresholdClassStart_days",'CH2. Tham số & Quy tắc'!$A:$A,0),"Lớp khai giảng trong "&thresholdClassStart_days&" ngày") -> Lớp khai giảng trong 14 ngày | C18: =COUNTIFS('DL10. Lớp học'!F4:F500,">="&TODAY(),'DL10. Lớp học'!F4:F500,"<="&TODAY()+thresholdClassStart_days) -> 2 | D18: =HYPERLINK("#'VH9. Việc - Lớp sắp khai giảng'!A1","Mở") -> Mở
A19: VH10. Khiếu nại chưa xử lý | B19: Khiếu nại đang mở | C19: =COUNTIF('DL17. Khiếu nại'!J4:J500,"<>resolved*")-COUNTBLANK('DL17. Khiếu nại'!J4:J500) -> 4 | D19: =HYPERLINK("#'VH10. Việc - Khiếu nại'!A1","Mở") -> Mở
A21: ĐIỀU HƯỚNG NHANH
A22: Cấu hình | B22: =HYPERLINK("#'CH2. Tham số & Quy tắc'!A1","Tham số hệ thống") -> Tham số hệ thống | C22: =HYPERLINK("#'CH1. Danh mục lựa chọn'!A1","Enum") -> Enum | D22: =HYPERLINK("#'CH3. Phân quyền'!A1","Phân quyền") -> Phân quyền | E22: =HYPERLINK("#'CH6. Ngưỡng KPI'!A1","Ngưỡng KPI") -> Ngưỡng KPI | F22: =HYPERLINK("#'HD3. Sổ trigger & tự động'!A1","Tra cứu thông điệp") -> Tra cứu thông điệp
A23: Nhập liệu | B23: =HYPERLINK("#'DL02. Khách tiềm năng'!A1","Lead") -> Lead | C23: =HYPERLINK("#'DL06. Đăng ký'!A1","Đăng ký") -> Đăng ký | D23: =HYPERLINK("#'DL09. Học viên'!A1","Học viên") -> Học viên | E23: =HYPERLINK("#'DL10. Lớp học'!A1","Lớp") -> Lớp
A24: Báo cáo | B24: =HYPERLINK("#'BC2. Chỉ số KPI'!A1","Chỉ số KPI") -> Chỉ số KPI | C24: =HYPERLINK("#'BC4. Báo cáo tháng'!A1","Tháng") -> Tháng | D24: =HYPERLINK("#'BC1. Học viên nguy cơ'!A1","HV nguy cơ") -> HV nguy cơ | E24: =HYPERLINK("#'BC9. Bảng Quản lý'!A1","Bảng Quản lý") -> Bảng Quản lý
A25: Tra cứu | B25: =HYPERLINK("#'VH2. Tra cứu Học viên'!A1","1 HV") -> 1 HV | C25: =HYPERLINK("#'VH4. Tra cứu Khách tiềm năng'!A1","1 Lead") -> 1 Lead | D25: =HYPERLINK("#'VH1. Tra cứu Lớp'!A1","1 Lớp") -> 1 Lớp
A27: =HYPERLINK("#'VH0. Tìm kiếm'!A1","TÌM KIẾM NHANH (theo tên / SĐT) - bấm vào đây") -> TÌM KIẾM NHANH (theo tên / SĐT) - bấm vào đây

Sheet HD1. Hướng dẫn sử dụng
A1: HƯỚNG DẪN SỬ DỤNG - ITTs SOP TEMP
A2: Hệ thống vận hành trung tâm trên Google Sheets: 52 sheet, 5 nhóm, số hóa trọn quy trình 10 giai đoạn. Trang này là cửa ngõ - đọc 5 phút là dùng được.
A4: 1. BẢN ĐỒ HỆ THỐNG - 5 NHÓM SHEET
B5: Nhóm | C5: Vai trò | D5: Ai dùng | E5: Khi nào | F5: Mở
B6: HD - Hướng dẫn (xám) | C6: Đọc để hiểu và tra cứu cách hệ thống chạy | D6: Mọi người | E6: Khi mới vào / khi thắc mắc | F6: =HYPERLINK("#'HD0. Trang chủ'!A1","HD0") -> HD0
B7: CH - Cấu hình (đỏ) | C7: Mọi danh mục, ngưỡng, thông điệp - sửa 1 chỗ, cả file đổi theo | D7: IT / Quản lý | E7: Khi đổi quy định | F7: =HYPERLINK("#'CH2. Tham số & Quy tắc'!A1","CH2") -> CH2
B8: DL - Dữ liệu (xanh dương) | C8: Nhập và xem chi tiết từng bản ghi (18 sheet + lịch WOW) | D8: Theo vai trò | E8: Khi nhập liệu / dò chi tiết | F8: =HYPERLINK("#'DL02. Khách tiềm năng'!A1","DL02") -> DL02
B9: VH - Vận hành (xanh lá) | C9: Danh sách việc đã lọc sẵn + tra cứu nhanh | D9: Nhân viên | E9: Hằng ngày | F9: =HYPERLINK("#'VH5. Việc - Chăm khách'!A1","VH5") -> VH5
B10: BC - Báo cáo (cam) | C10: Dashboard: KPI, phễu, việc cần duyệt, nguy cơ | D10: Quản lý | E10: Hằng ngày / hằng tuần | F10: =HYPERLINK("#'BC2. Chỉ số KPI'!A1","BC2") -> BC2
A13: 2. CÁCH ĐỌC MỘT SHEET DỮ LIỆU (DL)
B14: Vị trí | C14: Ý nghĩa
B15: Dòng 1 | C15: Tên cột kỹ thuật (tiếng Anh) - dùng cho công thức, KHÔNG sửa.
B16: Dòng 2 | C16: Tên tiếng Việt - giải thích ý nghĩa của biến.
B17: Dòng 3 | C17: Gợi ý nhập nhanh cho cột (nếu có).
B18: Dòng 4 trở đi | C18: Dữ liệu. Mỗi dòng 1 bản ghi, cột A là mã định danh.
B19: Ô chứa mã (HV001, ENR-...) | C19: Có liên kết về dữ liệu gốc.
B20: Cột "next_action" | C20: Câu nhắc tự sinh kèm màu ưu tiên. Tra "vì sao hiện câu này" ở HD3.
A22: 3. CẨM NANG THEO VAI TRÒ - mở đúng sheet của mình
B23: Vai trò | C23: Mở mỗi ngày | D23: Nhập liệu ở | E23: Xem báo cáo | F23: Lối tắt
B24: NV Tư vấn | C24: VH5 (khách cần chăm) | D24: DL02 - DL04, DL06 | E24: BC5, BC3 | F24: =HYPERLINK("#'VH5. Việc - Chăm khách'!A1","VH5") -> VH5
B25: NV Học vụ | C25: VH6, VH9, VH10 | D25: DL08, DL09, DL15 - DL17 | E25: BC8, BC1 | F25: =HYPERLINK("#'VH6. Việc - Học viên nguy cơ'!A1","VH6") -> VH6
B26: Giảng viên | C26: DL11 (buổi của mình) | D26: DL11 - DL13 | E26: BC7 | F26: =HYPERLINK("#'BC7. Bảng Giảng viên'!A1","BC7") -> BC7
B27: NV WOW | C27: VH7 (test chờ chấm) | D27: DL03, DL14 | E27: BC6 | F27: =HYPERLINK("#'VH7. Việc - Test chờ chấm'!A1","VH7") -> VH7
B28: Kế toán | C28: VH8 (thu học phí) | D28: DL07 (+DL06 nhắc nợ) | E28: BC9 (tài chính) | F28: =HYPERLINK("#'VH8. Việc - Thu học phí'!A1","VH8") -> VH8
B29: Quản lý | C29: BC9 (cần duyệt), BC1 | D29: duyệt tại DL06 | E29: BC2, BC4, VH11 | F29: =HYPERLINK("#'BC9. Bảng Quản lý'!A1","BC9") -> BC9
A31: 4. HIỂU FILE QUA VÍ DỤ THẬT - theo chân Trần Minh Anh (HV001)
B32: Xem demo các trang nối nhau bằng mã ID. Quy trình liền mạch cho 1 học viên
B33: Bước | C33: Mở sheet | D33: Tìm mã | E33: Bạn sẽ thấy
B34: 1 | C34: =HYPERLINK("#'DL02. Khách tiềm năng'!A1","DL02. Khách tiềm năng") -> DL02. Khách tiềm năng | D34: L-2026-00006 | E34: Điểm khởi đầu: Trần Minh Anh để lại thông tin, mục tiêu xây nền.
B35: 2 | C35: =HYPERLINK("#'DL03. Đặt lịch test'!A1","DL03. Đặt lịch test") -> DL03. Đặt lịch test | D35: TB-2026-003 | E35: Làm test đầu vào: overall 4.0, đã chấm, đã tư vấn.
B36: 3 | C36: =HYPERLINK("#'DL04. Tư vấn'!A1","DL04. Tư vấn") -> DL04. Tư vấn | D36: CS-2026-002 | E36: Tư vấn theo kết quả test, chốt khóa Foundation kèm cọc.
B37: 4 | C37: =HYPERLINK("#'DL06. Đăng ký'!A1","DL06. Đăng ký") -> DL06. Đăng ký | D37: ENR-2026-001 | E37: Đăng ký khóa. final_fee, paid_amount tự tính.
B38: 5 | C38: =HYPERLINK("#'DL07. Thanh toán'!A1","DL07. Thanh toán") -> DL07. Thanh toán | D38: PAY-2026-001 | E38: Đóng đủ 12.000.000đ một lần, net_received tự trừ phí.
B39: 6 | C39: =HYPERLINK("#'DL09. Học viên'!A1","DL09. Học viên") -> DL09. Học viên | D39: HV001 | E39: Hồ sơ chính thức. Cờ nguy cơ 2 trục đều ổn.
B40: 7 | C40: =HYPERLINK("#'DL08. Xếp lớp & Nhập học'!A1","DL08. Xếp lớp & Nhập học") -> DL08. Xếp lớp & Nhập học | D40: OB-001 | E40: Xếp vào lớp LOP-FOUND-PLA-01, onboarding hoàn tất.
B41: 8 | C41: =HYPERLINK("#'DL10. Lớp học'!A1","DL10. Lớp học") -> DL10. Lớp học | D41: LOP-FOUND-PLA-01 | E41: Lớp Foundation: GV, sĩ số tự đếm từ onboarding.
A44: 5. DANH MỤC ĐẦY ĐỦ 52 SHEET (bấm tên để mở)
B45: NHÓM HƯỚNG DẪN (tab xám)
B46: =HYPERLINK("#'HD0. Trang chủ'!A1","HD0. Trang chủ") -> HD0. Trang chủ | C46: Trang chủ - đếm việc hôm nay + điều hướng nhanh
B47: =HYPERLINK("#'HD1. Hướng dẫn sử dụng'!A1","HD1. Hướng dẫn sử dụng") -> HD1. Hướng dẫn sử dụng | C47: Nhìn tổng quát chức năng các trang
B48: =HYPERLINK("#'HD2. Quy trình nghiệp vụ'!A1","HD2. Quy trình nghiệp vụ") -> HD2. Quy trình nghiệp vụ | C48: Quy trình nghiệp vụ 10 giai đoạn chi tiết
B49: =HYPERLINK("#'HD3. Sổ trigger & tự động'!A1","HD3. Sổ trigger & tự động") -> HD3. Sổ trigger & tự động | C49: Sổ trigger & tự động hóa - tra mọi thứ hệ thống tự làm
B50: NHÓM CẤU HÌNH (tab đỏ)
B51: =HYPERLINK("#'CH1. Danh mục lựa chọn'!A1","CH1. Danh mục lựa chọn") -> CH1. Danh mục lựa chọn | C51: Danh mục giá trị cho mọi ô chọn (dropdown)
B52: =HYPERLINK("#'CH2. Tham số & Quy tắc'!A1","CH2. Tham số & Quy tắc") -> CH2. Tham số & Quy tắc | C52: Tham số SLA / ngưỡng / hoàn tiền - SỬA CON SỐ Ở ĐÂY
B53: =HYPERLINK("#'CH3. Phân quyền'!A1","CH3. Phân quyền") -> CH3. Phân quyền | C53: Phân quyền theo hành động
B54: =HYPERLINK("#'CH4. Thông điệp nhắc việc'!A1","CH4. Thông điệp nhắc việc") -> CH4. Thông điệp nhắc việc | C54: Thông điệp nhắc việc - SỬA CÂU CHỮ Ở ĐÂY
B55: =HYPERLINK("#'CH5. Thuật ngữ'!A1","CH5. Thuật ngữ") -> CH5. Thuật ngữ | C55: Thuật ngữ, viết tắt
B56: =HYPERLINK("#'CH6. Ngưỡng KPI'!A1","CH6. Ngưỡng KPI") -> CH6. Ngưỡng KPI | C56: Ngưỡng 48 chỉ số KPI - SỬA KPI Ở ĐÂY
B57: NHÓM DỮ LIỆU (tab xanh dương)
B58: =HYPERLINK("#'DL01. Nhân viên'!A1","DL01. Nhân viên") -> DL01. Nhân viên | C58: Nhân viên
B59: =HYPERLINK("#'DL02. Khách tiềm năng'!A1","DL02. Khách tiềm năng") -> DL02. Khách tiềm năng | C59: Khách tiềm năng (lead)
B60: =HYPERLINK("#'DL02b. Lịch sử liên hệ'!A1","DL02b. Lịch sử liên hệ") -> DL02b. Lịch sử liên hệ | C60: Lịch sử liên hệ từng lead
B61: =HYPERLINK("#'DL03. Đặt lịch test'!A1","DL03. Đặt lịch test") -> DL03. Đặt lịch test | C61: Đặt lịch test đầu vào
B62: =HYPERLINK("#'DL04. Tư vấn'!A1","DL04. Tư vấn") -> DL04. Tư vấn | C62: Tư vấn & chốt
B63: =HYPERLINK("#'DL05. Khóa học'!A1","DL05. Khóa học") -> DL05. Khóa học | C63: Danh mục khóa học
B64: =HYPERLINK("#'DL06. Đăng ký'!A1","DL06. Đăng ký") -> DL06. Đăng ký | C64: Đăng ký học
B65: =HYPERLINK("#'DL07. Thanh toán'!A1","DL07. Thanh toán") -> DL07. Thanh toán | C65: Thanh toán
B66: =HYPERLINK("#'DL08. Xếp lớp & Nhập học'!A1","DL08. Xếp lớp & Nhập học") -> DL08. Xếp lớp & Nhập học | C66: Xếp lớp & nhập học (onboarding)
B67: =HYPERLINK("#'DL09. Học viên'!A1","DL09. Học viên") -> DL09. Học viên | C67: Hồ sơ học viên + cờ nguy cơ
B68: =HYPERLINK("#'DL10. Lớp học'!A1","DL10. Lớp học") -> DL10. Lớp học | C68: Lớp học
B69: =HYPERLINK("#'DL11. Buổi học'!A1","DL11. Buổi học") -> DL11. Buổi học | C69: Buổi học
B70: =HYPERLINK("#'DL12. Điểm danh'!A1","DL12. Điểm danh") -> DL12. Điểm danh | C70: Điểm danh
B71: =HYPERLINK("#'DL13. Bài tập'!A1","DL13. Bài tập") -> DL13. Bài tập | C71: Bài tập
B72: =HYPERLINK("#'DL14. Buổi WOW 1-1'!A1","DL14. Buổi WOW 1-1") -> DL14. Buổi WOW 1-1 | C72: Buổi WOW 1-1
B73: =HYPERLINK("#'DL15. Khảo sát'!A1","DL15. Khảo sát") -> DL15. Khảo sát | C73: Khảo sát định kỳ
B74: =HYPERLINK("#'DL16. Phản hồi'!A1","DL16. Phản hồi") -> DL16. Phản hồi | C74: Phản hồi (feedback)
B75: =HYPERLINK("#'DL17. Khiếu nại'!A1","DL17. Khiếu nại") -> DL17. Khiếu nại | C75: Khiếu nại
B76: =HYPERLINK("#'DL18. Kết thúc khóa'!A1","DL18. Kết thúc khóa") -> DL18. Kết thúc khóa | C76: Kết thúc khóa & tái ghi danh
B77: =HYPERLINK("#'DL19. Lịch làm việc WOW'!A1","DL19. Lịch làm việc WOW") -> DL19. Lịch làm việc WOW | C77: Lịch trực WOW theo tháng
B78: NHÓM VẬN HÀNH (tab xanh lá)
B79: =HYPERLINK("#'VH0. Tìm kiếm'!A1","VH0. Tìm kiếm") -> VH0. Tìm kiếm | C79: Tìm kiếm toàn hệ thống
B80: =HYPERLINK("#'VH1. Tra cứu Lớp'!A1","VH1. Tra cứu Lớp") -> VH1. Tra cứu Lớp | C80: Tra cứu Lớp (kèm danh sách HV của lớp)
B81: =HYPERLINK("#'VH2. Tra cứu Học viên'!A1","VH2. Tra cứu Học viên") -> VH2. Tra cứu Học viên | C81: Tra cứu Học viên - hồ sơ 360 độ
B82: =HYPERLINK("#'VH3. Tra cứu Giảng viên'!A1","VH3. Tra cứu Giảng viên") -> VH3. Tra cứu Giảng viên | C82: Tra cứu Giảng viên
B83: =HYPERLINK("#'VH3b. Tra cứu NV WOW'!A1","VH3b. Tra cứu NV WOW") -> VH3b. Tra cứu NV WOW | C83: Tra cứu NV WOW
B84: =HYPERLINK("#'VH4. Tra cứu Khách tiềm năng'!A1","VH4. Tra cứu Khách tiềm năng") -> VH4. Tra cứu Khách tiềm năng | C84: Tra cứu Khách tiềm năng
B85: =HYPERLINK("#'VH5. Việc - Chăm khách'!A1","VH5. Việc - Chăm khách") -> VH5. Việc - Chăm khách | C85: Việc: khách cần chăm hôm nay
B86: =HYPERLINK("#'VH6. Việc - Học viên nguy cơ'!A1","VH6. Việc - Học viên nguy cơ") -> VH6. Việc - Học viên nguy cơ | C86: Việc: học viên nguy cơ
B87: =HYPERLINK("#'VH7. Việc - Test chờ chấm'!A1","VH7. Việc - Test chờ chấm") -> VH7. Việc - Test chờ chấm | C87: Việc: test chờ chấm
B88: =HYPERLINK("#'VH8. Việc - Thu học phí'!A1","VH8. Việc - Thu học phí") -> VH8. Việc - Thu học phí | C88: Việc: thu học phí
B89: =HYPERLINK("#'VH9. Việc - Lớp sắp khai giảng'!A1","VH9. Việc - Lớp sắp khai giảng") -> VH9. Việc - Lớp sắp khai giảng | C89: Việc: lớp sắp khai giảng
B90: =HYPERLINK("#'VH10. Việc - Khiếu nại'!A1","VH10. Việc - Khiếu nại") -> VH10. Việc - Khiếu nại | C90: Việc: khiếu nại đang mở
B91: =HYPERLINK("#'VH11. Khối lượng việc theo NV'!A1","VH11. Khối lượng việc theo NV") -> VH11. Khối lượng việc theo NV | C91: Khối lượng việc theo nhân viên
B92: NHÓM BÁO CÁO (tab cam)
B93: =HYPERLINK("#'BC1. Học viên nguy cơ'!A1","BC1. Học viên nguy cơ") -> BC1. Học viên nguy cơ | C93: Học viên nguy cơ
B94: =HYPERLINK("#'BC2. Chỉ số KPI'!A1","BC2. Chỉ số KPI") -> BC2. Chỉ số KPI | C94: 48 chỉ số KPI
B95: =HYPERLINK("#'BC3. Phễu khách tiềm năng'!A1","BC3. Phễu khách tiềm năng") -> BC3. Phễu khách tiềm năng | C95: Phễu khách tiềm năng
B96: =HYPERLINK("#'BC4. Báo cáo tháng'!A1","BC4. Báo cáo tháng") -> BC4. Báo cáo tháng | C96: Báo cáo tháng (có so sánh tháng trước)
B97: =HYPERLINK("#'BC5. Bảng NV Tư vấn'!A1","BC5. Bảng NV Tư vấn") -> BC5. Bảng NV Tư vấn | C97: Bảng việc NV Tư vấn
B98: =HYPERLINK("#'BC6. Bảng NV WOW'!A1","BC6. Bảng NV WOW") -> BC6. Bảng NV WOW | C98: Bảng việc NV WOW
B99: =HYPERLINK("#'BC7. Bảng Giảng viên'!A1","BC7. Bảng Giảng viên") -> BC7. Bảng Giảng viên | C99: Bảng Giảng viên (lọc theo GV)
B100: =HYPERLINK("#'BC8. Bảng Học vụ'!A1","BC8. Bảng Học vụ") -> BC8. Bảng Học vụ | C100: Bảng Học vụ
B101: =HYPERLINK("#'BC9. Bảng Quản lý'!A1","BC9. Bảng Quản lý") -> BC9. Bảng Quản lý | C101: Bảng Quản lý (duyệt, KN cao, hoàn tiền)
A103: Tài liệu sâu hơn: HD2 (quy trình 10 giai đoạn) - HD3 (sổ trigger) - 2 file Word hướng dẫn vận hành & kỹ thuật.

Sheet HD2. Quy trình nghiệp vụ
A1: QUY TRÌNH HƯỚNG DẪN TỪNG BƯỚC (SOP TEMP)
A2: File này mô tả toàn bộ quy trình vận hành ITTs theo SOP, chia theo 10 Phase. Mỗi sheet data có cột "next_action" tự gợi ý việc cần làm tiếp.
A3: Cách dùng hằng ngày: mỗi sáng mở dashboard vai trò của mình (nhóm BC màu cam) và các sheet "Việc cần làm" (nhóm VH màu xanh lá) để biết hôm nay phải xử lý gì.
A4: CÁCH ĐỌC BẢNG: Mỗi bảng bên dưới là 1 Phase trong quy trình. Đọc theo từng HÀNG, từ trái sang phải: (1) "Trạng thái hiện tại" của lead/học viên - (2) "Điều kiện" để biết rơi vào trường hợp nào - (3) "Hành động cần làm" - (4) "Người làm" - (5) "SLA" là thời hạn phải xong - (6) "Kết quả / Trạng thái mới": giá trị tiếng Anh (vd contacted, confirmed) chính là giá trị cần nhập vào cột trạng thái ở sheet data tương ứng; sau khi nhập, lead/HV chuyển sang hàng có trạng thái đó để làm bước tiếp theo. Mọi bước cũng được hệ thống tự nhắc ở cột "next_action" trong các sheet VH (Việc cần làm).
A5: LUỒNG TỔNG QUAN - 10 PHASE
A6: Lead vào -> P1 Tiếp nhận -> P2 Test -> P3 Tư vấn+Báo giá -> P4 Thanh toán -> P5 Xếp lớp -> P6 Vận hành buổi -> P7 BT+WOW -> P8 Khảo sát -> P9 Feedback/KN -> P10 Kết thúc khóa
A8: PHASE 1-3: TƯ VẤN - LEAD ENROLL
A9: Trạng thái hiện tại | B9: Điều kiện | C9: Hành động cần làm | D9: Người làm | E9: SLA | F9: Kết quả / Trạng thái mới
A10: lead_status = new (Chưa liên hệ) | B10: Lead vừa vào hệ thống | C10: Gọi điện thoại lần 1 | D10: NV Tư vấn | E10: =HYPERLINK("#'CH2. Tham số & Quy tắc'!A"&MATCH("slaLRT_minutes",'CH2. Tham số & Quy tắc'!$A:$A,0),slaLRT_minutes&" phút") -> 15 phút | F10: contacted (Đã liên hệ)
A11: lead_status = new (Chưa liên hệ) | B11: ="Quá "&slaLRT_minutes&"p chưa gọi" -> Quá 15p chưa gọi | C11: KHẨN: gọi NGAY + ghi nhận lý do trễ | D11: NV Tư vấn + Sale Leader | E11: NGAY | F11: contacted (Đã liên hệ)
A12: lead_status = contacted (Đã liên hệ, đang khai thác) | B12: HV chưa book test | C12: Hẹn ngày làm test đầu vào | D12: NV Tư vấn | E12: =HYPERLINK("#'CH2. Tham số & Quy tắc'!A"&MATCH("slaFollowup_grace_days",'CH2. Tham số & Quy tắc'!$A:$A,0),slaFollowup_grace_days&" ngày") -> 3 ngày | F12: booking_status = booked (đã làm test)
A13: lead_status = contacted (Đã liên hệ, đang khai thác) | B13: ="HV từ chối test sau "&thresholdContacted_attempts&" lần liên hệ" -> HV từ chối test sau 5 lần liên hệ | C13: Đổi lead_status = rejected (Từ chối) | D13: NV Tư vấn | E13: - | F13: lead_status = rejected (Từ chối)
A14: test_status = pending (Chưa có kết quả) | B14: test_result_overall còn trống | C14: NV WOW chấm test + ghi nhận xét | D14: NV WOW Coach | E14: =HYPERLINK("#'CH2. Tham số & Quy tắc'!A"&MATCH("slaGLA_hours",'CH2. Tham số & Quy tắc'!$A:$A,0),slaGLA_hours&" giờ") -> 24 giờ | F14: (điền test_result + academic_note)
A15: test_status = graded (Đã chấm xong) | B15: Đã có test_result | C15: Tư vấn lộ trình + gói khóa phù hợp | D15: NV Tư vấn | E15: =HYPERLINK("#'CH2. Tham số & Quy tắc'!A"&MATCH("slaCVT_hours",'CH2. Tham số & Quy tắc'!$A:$A,0),slaCVT_hours&" giờ") -> 24 giờ | F15: consulted (Đã tư vấn lộ trình)
A16: consultation_status = consulted (Đã tư vấn xong) | B16: quoted_amount còn trống | C16: Gửi báo giá chính thức (email/Zalo) | D16: NV Tư vấn | E16: =HYPERLINK("#'CH2. Tham số & Quy tắc'!A"&MATCH("slaQuote_days",'CH2. Tham số & Quy tắc'!$A:$A,0),slaQuote_days&" ngày") -> 1 ngày | F16: conversion_status = interested (đã báo giá, quan tâm)
A17: consultation_status = consulted (Đã tư vấn xong) | B17: ="Có chiết khấu ≥ "&TEXT(thresholdDiscount_approval,"#,##0")&"đ" -> Có chiết khấu ≥ 1,000,000đ | C17: Xin Trưởng phòng TV hoặc CEO duyệt | D17: NV Tư vấn QL | E17: =HYPERLINK("#'CH2. Tham số & Quy tắc'!A"&MATCH("slaApproval_days",'CH2. Tham số & Quy tắc'!$A:$A,0),slaApproval_days&" ngày") -> 1 ngày | F17: (điền discount_approved_by)
A18: conversion_status = interested (Quan tâm, chưa chốt) | B18: Chưa enroll | C18: Follow-up chốt deal. Nếu sau 3 lần FL không phản hồi thì đổi lead_status = unreachable | D18: NV Tư vấn | E18: =HYPERLINK("#'CH2. Tham số & Quy tắc'!A"&MATCH("thresholdContacted_days",'CH2. Tham số & Quy tắc'!$A:$A,0),thresholdContacted_days&" ngày") -> 7 ngày | F18: enrollment_status = confirmed (Đã xác nhận) / lead_status = rejected (Từ chối)
A19: enrollment_status = confirmed (Đã xác nhận) + payment_status = paid (Đã thanh toán đủ) | B19: Đã đóng tiền | C19: Chuyển sheet "DL07. Thanh toán" + báo Học vụ | D19: NV Tư vấn | E19: NGAY | F19: -> Chuyển sang Phase 4 (xem bảng phía dưới)
A20: lead_status = unreachable (Hết cách liên lạc) | B20: - | C20: Ghi rõ lost_reason để học bài | D20: NV Tư vấn | E20: - | F20: (đóng case)
A22: PHASE 4: THANH TOÁN
A23: Trạng thái | B23: Điều kiện | C23: Hành động | D23: Người làm | E23: SLA | F23: Kết quả / Trạng thái mới
A24: payment_status = unpaid (Chưa thanh toán) | B24: Báo giá xong, chờ chuyển khoản | C24: Gửi link/STK + theo dõi | D24: NV TV | E24: - | F24: completed (Hoàn tất) / partial (Đóng từng đợt)
A25: payment_status = paid (Đã thanh toán đủ) | B25: Đã thu đủ | C25: Lập hóa đơn + xác nhận với HV | D25: Kế toán | E25: =HYPERLINK("#'CH2. Tham số & Quy tắc'!A"&MATCH("slaPaymentConfirm_days",'CH2. Tham số & Quy tắc'!$A:$A,0),slaPaymentConfirm_days&" ngày") -> 1 ngày | F25: -> Chuyển sang Phase 5 (xem bảng phía dưới)
A26: payment_status = partial (Đã thanh toán 1 phần) | B26: Chưa đóng đợt tiếp | C26: FL nhắc HV đợt 2 theo lịch | D26: Kế toán | E26: Theo lịch đợt | F26: completed (Hoàn tất)
A27: payment_status = refunded (Đã hoàn tiền) | B27: HV yêu cầu hoàn | C27: Xác minh + duyệt + lập biên bản | D27: Kế toán + QL | E27: =HYPERLINK("#'CH2. Tham số & Quy tắc'!A"&MATCH("slaRefundProcess_days",'CH2. Tham số & Quy tắc'!$A:$A,0),slaRefundProcess_days&" ngày") -> 5 ngày | F27: (close)
A29: PHASE 5: XẾP LỚP (Học vụ)
A30: Tình huống | B30: Điều kiện | C30: Hành động | D30: Người làm | E30: SLA | F30: Kết quả / Trạng thái mới
A31: placement_status = not_assigned (Chưa xếp lớp) | B31: Chưa có class_id | C31: Tạo bản ghi xếp lớp (sheet DL08) + gán class_id phù hợp band & lịch của HV | D31: Học vụ | E31: =HYPERLINK("#'DL08. Xếp lớp & Nhập học'!A"&MATCH("slaPLR48_hours",'CH2. Tham số & Quy tắc'!$A:$A,0),slaPLR48_hours&" giờ") -> 48 giờ | F31: Có class_id
A32: placement_status = not_assigned (Chưa xếp lớp) + không còn lớp phù hợp (cùng band đều full hoặc lệch lịch) | B32: Lớp cùng band đã full hoặc lịch không khớp | C32: Báo NV TV + đề xuất mở lớp mới hoặc waitlist | D32: Học vụ TP | E32: =HYPERLINK("#'CH2. Tham số & Quy tắc'!A"&MATCH("slaPLR48_hours",'CH2. Tham số & Quy tắc'!$A:$A,0),slaPLR48_hours&" giờ") -> 48 giờ | F32: waitlist / mở lớp
A33: class: current_enrollment = class_capacity (lớp đã đủ sĩ số) | B33: current_enrollment = class_capacity | C33: Khóa enroll thêm hoặc xin duyệt vượt sĩ số | D33: Học vụ TP | E33: NGAY | F33: -
A35: PHASE 6: VẬN HÀNH BUỔI HỌC
A36: Trạng thái buổi | B36: Điều kiện | C36: Hành động | D36: Người làm | E36: SLA | F36: Kết quả / Trạng thái mới
A37: session_status = scheduled (Đã lên lịch) | B37: Buổi sắp diễn ra | C37: Chuẩn bị giáo án + tài liệu | D37: Giảng viên | E37: Trước buổi | F37: in_progress (Đang thực hiện)
A38: session_status = in_progress (Đang diễn ra) | B38: GV đã bấm "Bắt đầu" | C38: Dạy + cập nhật điểm danh sau giờ | D38: Giảng viên | E38: Realtime | F38: completed (Hoàn tất)
A39: session_status = completed (Đã hoàn thành) + teacher_note_completed_at còn trống | B39: has_teacher_note = FALSE | C39: Viết teacher_note 6 phần | D39: Giảng viên | E39: =HYPERLINK("#'CH2. Tham số & Quy tắc'!A"&MATCH("slaTeacherNote_hours",'CH2. Tham số & Quy tắc'!$A:$A,0),slaTeacherNote_hours&" giờ") -> 48 giờ | F39: Ghi: has_teacher_note = TRUE
A40: session_status = completed (Đã hoàn thành) + teacher_note_completed_at đã có | B40: has_teacher_note = TRUE | C40: Học vụ duyệt note + chia sẻ HV | D40: Học vụ | E40: =HYPERLINK("#'CH2. Tham số & Quy tắc'!A"&MATCH("slaNoteReview_hours",'CH2. Tham số & Quy tắc'!$A:$A,0),slaNoteReview_hours&" giờ") -> 24 giờ | F40: Hoàn tất
A41: session_status = cancelled (Đã hủy) | B41: Buổi bị hủy đột xuất | C41: Báo HV + lên lịch bù | D41: Học vụ | E41: NGAY | F41: session_status = scheduled (lịch bù mới)
A43: PHASE 6: ĐIỂM DANH
A44: Tình huống | B44: Điều kiện | C44: Hành động | D44: Người làm | E44: SLA | F44: Kết quả / Trạng thái mới
A45: class_start_actual đã ghi nhận (GV bấm "Bắt đầu" buổi) | B45: GV bấm "Bắt đầu" (class_start_actual ghi nhận) | C45: Mở app điểm danh | D45: GV | E45: - | F45: -
A46: attendance_status = on_time (Đúng giờ) | B46: - | C46: Điểm danh on_time | D46: GV | E46: - | F46: Ghi: attendance = on_time
A47: attendance_status = late (Trễ) | B47: - | C47: Điểm danh late + ghi giờ | D47: GV | E47: - | F47: Ghi: attendance = late
A48: attendance_status = no_show (Vắng) + absence_type = excused (Có phép) | B48: HV báo trước có lý do | C48: Điểm danh absent + absence_type = excused | D48: GV | E48: - | F48: Ghi: attendance = absent
A49: attendance_status = no_show (Vắng) + absence_type = unexcused (Không phép) | B49: - | C49: absence_type = unexcused tính vào at_risk | D49: GV Học vụ | E49: - | F49: cập nhật at_risk_level
A50: in_class_performance = weak (Yếu) 3 buổi liên tiếp | B50: - | C50: Cập nhật at_risk = high + book WOW academic_support | D50: Học vụ | E50: =HYPERLINK("#'CH2. Tham số & Quy tắc'!A"&MATCH("slaRiskFlagUpdate_hours",'CH2. Tham số & Quy tắc'!$A:$A,0),slaRiskFlagUpdate_hours&" giờ") -> 48 giờ | F50: Ghi: at_risk = high
A52: PHASE 7: BÀI TẬP
A53: Trạng thái | B53: Điều kiện | C53: Hành động | D53: Người làm | E53: SLA | F53: Kết quả / Trạng thái mới
A54: homework_status = assigned (Đã giao) | B54: HV chưa nộp, chưa quá hạn | C54: Theo dõi, có thể nhắc | D54: GV | E54: Đến hạn nộp | F54: homework_status = submitted_on_time (Đã nộp) / missing (Chưa nộp)
A55: homework_status = assigned (Đã giao) + quá homework_due_date | B55: Quá hạn 1+ ngày | C55: Đánh dấu missing tính at_risk | D55: GV | E55: NGAY | F55: missing (Chưa nộp)
A56: homework_status = submitted_on_time (Nộp đúng/trước hạn) + graded_at còn trống | B56: ="Chấm trong "&slaHomeworkGrading_hours&"h" -> Chấm trong 48h | C56: Chấm + cho điểm + nhận xét | D56: GV | E56: =HYPERLINK("#'CH2. Tham số & Quy tắc'!A"&MATCH("slaHomeworkGrading_hours",'CH2. Tham số & Quy tắc'!$A:$A,0),slaHomeworkGrading_hours&" giờ") -> 48 giờ | F56: graded (Đã chấm)
A57: homework_status = submitted_on_time (Nộp đúng/trước hạn) + graded_at còn trống, quá hạn chấm | B57: ="Quá "&slaHomeworkGrading_hours&"h chưa chấm" -> Quá 48h chưa chấm | C57: Chấm GẤP - tính vào KPI GCR7 | D57: GV | E57: NGAY | F57: graded (Đã chấm)
A58: homework_score đã có (đã chấm) + điểm thấp hoặc in_class_performance = weak (Yếu) | B58: Điểm thấp hoặc kỹ năng Weak | C58: Ghi vào teacher_note + đề xuất WOW | D58: GV | E58: Cùng note | F58: WOW booked
A60: PHASE 7: WOW SESSIONS
A61: Trạng thái | B61: Điều kiện | C61: Hành động | D61: Người làm | E61: SLA | F61: Kết quả / Trạng thái mới
A62: wow_booked_by = academic_hv (Học vụ) | B62: HV có cờ at_risk/off_track ở DL09 | C62: Hệ thống tự tạo WOW academic_support | D62: Hệ thống (tương lai) / Học vụ thủ công | E62: NGAY | F62: booked (Đã đặt)
A63: wow_booked_by = teacher (Giảng viên) | B63: GV ghi đề xuất trong teacher_note | C63: Học vụ tạo WOW advanced_practice | D63: Học vụ | E63: =HYPERLINK("#'CH2. Tham số & Quy tắc'!A"&MATCH("slaWowBooking_hours",'CH2. Tham số & Quy tắc'!$A:$A,0),slaWowBooking_hours&" giờ") -> 24 giờ | F63: booked (Đã đặt)
A64: wow_booked_by = student (Học viên) | B64: HV tự book qua app | C64: Trừ quota confirm | D64: HV (app) Học vụ | E64: =HYPERLINK("#'CH2. Tham số & Quy tắc'!A"&MATCH("slaWowBooking_hours",'CH2. Tham số & Quy tắc'!$A:$A,0),slaWowBooking_hours&" giờ") -> 24 giờ | F64: confirmed (Đã xác nhận)
A65: wow_booked_by = sales (NV Tư vấn) | B65: NV TV book trước midterm | C65: Học vụ confirm với HV | D65: NV TV Học vụ | E65: =HYPERLINK("#'CH2. Tham số & Quy tắc'!A"&MATCH("slaWowBooking_hours",'CH2. Tham số & Quy tắc'!$A:$A,0),slaWowBooking_hours&" giờ") -> 24 giờ | F65: confirmed (Đã xác nhận)
A66: wow_status = booked (Đã đặt) | B66: Chưa confirm | C66: Học vụ liên hệ HV xác nhận lịch | D66: Học vụ | E66: =HYPERLINK("#'CH2. Tham số & Quy tắc'!A"&MATCH("slaWowBooking_hours",'CH2. Tham số & Quy tắc'!$A:$A,0),slaWowBooking_hours&" giờ") -> 24 giờ | F66: confirmed (Đã xác nhận)
A67: wow_status = confirmed (Đã xác nhận) | B67: Sắp diễn ra | C67: NV WOW chuẩn bị nội dung trọng tâm | D67: NV WOW | E67: Trước buổi | F67: completed (Hoàn tất)
A68: wow_status = completed (Đã hoàn thành) + wow_content_note còn trống | B68: wow_content_note còn trống | C68: ="Viết content_note (SLA "&slaWowOutcomeRead_hours&"h)" -> Viết content_note (SLA 24h) | D68: NV WOW | E68: =HYPERLINK("#'CH2. Tham số & Quy tắc'!A"&MATCH("slaWowOutcomeRead_hours",'CH2. Tham số & Quy tắc'!$A:$A,0),slaWowOutcomeRead_hours&" giờ") -> 24 giờ | F68: có content_note
A69: wow_status = completed (Đã hoàn thành) + có content_note, wow_outcome còn trống | B69: Có content_note, chưa đánh giá | C69: Đánh giá outcome: improved / no_change / needs_more | D69: NV WOW | E69: Cùng note | F69: có outcome
A70: wow_status = no_show (HV không đến) | B70: - | C70: Trừ quota + ghi no_show_reason + thông báo HV | D70: NV WOW + Học vụ | E70: NGAY | F70: close
A72: PHASE 8: KHẢO SÁT
A73: Tuần | B73: Điều kiện | C73: Hành động | D73: Người làm | E73: SLA | F73: Kết quả / Trạng thái mới
A74: survey_type = week_1 (Tuần 1) | B74: HV đã học buổi 1 | C74: Gửi form khảo sát ấn tượng ban đầu | D74: Học vụ | E74: Sau buổi 1 | F74: Ghi: survey_type = week_1
A75: survey_type = week_4 (Tuần 4) | B75: HV đã học 4 tuần | C75: Gửi form đánh giá tiến bộ giữa khóa | D75: Học vụ | E75: =HYPERLINK("#'CH2. Tham số & Quy tắc'!A"&MATCH("slaSurveyCollect_days",'CH2. Tham số & Quy tắc'!$A:$A,0),slaSurveyCollect_days&" ngày") -> 7 ngày | F75: Ghi: survey_type = week_4
A76: survey_type = week_8 (Tuần 8) | B76: HV đã học 8 tuần | C76: Gửi form (cho khóa dài) | D76: Học vụ | E76: =HYPERLINK("#'CH2. Tham số & Quy tắc'!A"&MATCH("slaSurveyCollect_days",'CH2. Tham số & Quy tắc'!$A:$A,0),slaSurveyCollect_days&" ngày") -> 7 ngày | F76: Ghi: survey_type = week_8
A77: survey_type = end_of_course (Cuối khóa) | B77: HV sắp KT | C77: Gửi form đánh giá tổng kết + xin testimonial | D77: Học vụ | E77: Sau buổi cuối | F77: Ghi: survey_type = end_of_course
A78: nps_score >= 9 (Promoter) | B78: HV rất hài lòng | C78: Đề xuất xin testimonial chính thức + ref | D78: Học vụ MKT | E78: =HYPERLINK("#'CH2. Tham số & Quy tắc'!A"&MATCH("slaTestimonialAsk_days",'CH2. Tham số & Quy tắc'!$A:$A,0),slaTestimonialAsk_days&" ngày") -> 7 ngày | F78: Ghi: is_testimonial = TRUE
A79: nps_score <= 6 (Detractor) | B79: HV không hài lòng | C79: Học vụ gọi điện tìm hiểu sâu | D79: Học vụ | E79: =HYPERLINK("#'CH2. Tham số & Quy tắc'!A"&MATCH("slaSurveyReport_hours",'CH2. Tham số & Quy tắc'!$A:$A,0),slaSurveyReport_hours&" giờ") -> 48 giờ | F79: có thể tạo Feedback
A81: PHASE 8-9: FEEDBACK & KHIẾU NẠI
A82: Trạng thái | B82: Điều kiện | C82: Hành động | D82: Người làm | E82: SLA | F82: Kết quả / Trạng thái mới
A83: feedback_status = new (Mới nhận) / complaint_status = new (Mới tiếp nhận) | B83: Chưa phân loại | C83: Phân loại type + category + priority | D83: Học vụ | E83: =HYPERLINK("#'CH2. Tham số & Quy tắc'!A"&MATCH("slaFB_classify_hours",'CH2. Tham số & Quy tắc'!$A:$A,0),slaFB_classify_hours&" giờ") -> 24 giờ | F83: complaint_status = assigned (Đã phân loại & phân công)
A84: complaint_status = assigned (Đã phân công) + complaint_severity = high (Cao) | B84: complaint_severity = high | C84: Liên hệ HV NGAY + thông báo các bên liên quan | D84: Học vụ QL | E84: =HYPERLINK("#'CH2. Tham số & Quy tắc'!A"&MATCH("slaKN_high_hours",'CH2. Tham số & Quy tắc'!$A:$A,0),slaKN_high_hours&" giờ") -> 4 giờ | F84: in_progress (Đang thực hiện)
A85: complaint_status = assigned (Đã phân công) + complaint_severity = medium (Trung bình) | B85: complaint_severity = medium | C85: Lên kế hoạch xử lý | D85: Học vụ | E85: =HYPERLINK("#'CH2. Tham số & Quy tắc'!A"&MATCH("slaKN_medium_hours",'CH2. Tham số & Quy tắc'!$A:$A,0),slaKN_medium_hours&" giờ") -> 48 giờ | F85: in_progress (Đang thực hiện)
A86: feedback_type = positive (Tích cực) | B86: type = positive | C86: Chuyển feedback đến đối tượng (GV/NV) | D86: Học vụ | E86: =HYPERLINK("#'CH2. Tham số & Quy tắc'!A"&MATCH("slaTestimonialAsk_days",'CH2. Tham số & Quy tắc'!$A:$A,0),slaTestimonialAsk_days&" ngày") -> 7 ngày | F86: complaint_status = resolved (Đã giải quyết)
A87: feedback_type = positive (Tích cực) + is_testimonial = TRUE (đặc biệt tốt) | B87: type = positive + đặc biệt tốt | C87: Xin testimonial chính thức | D87: Học vụ MKT | E87: =HYPERLINK("#'CH2. Tham số & Quy tắc'!A"&MATCH("slaTestimonialAsk_days",'CH2. Tham số & Quy tắc'!$A:$A,0),slaTestimonialAsk_days&" ngày") -> 7 ngày | F87: Ghi: is_testimonial = TRUE
A88: complaint_status = in_progress (Đang xử lý) | B88: Đang xử lý | C88: Cập nhật action_note + đặt next_follow_up | D88: Học vụ | E88: - | F88: complaint_status = in_progress (chờ theo dõi lại)
A89: complaint_status = in_progress (Đang xử lý) + đến hẹn theo dõi lại | B89: Đến ngày FL | C89: Liên hệ HV xác nhận tình hình | D89: Học vụ | E89: Đúng ngày | F89: in_progress (Đang thực hiện) / resolved (Đã giải quyết)
A90: ="complaint_severity = high (Cao) + quá "&slaKN_high_hours&" giờ chưa liên hệ HV" -> complaint_severity = high (Cao) + quá 4 giờ chưa liên hệ HV | B90: - | C90: Tự động escalate Quản lý | D90: Hệ thống QL | E90: NGAY | F90: escalated (Đã chuyển cấp trên)
A91: complaint_status = resolved (Đã xử lý xong) | B91: HV xác nhận hài lòng | C91: Đóng case | D91: Học vụ | E91: =HYPERLINK("#'CH2. Tham số & Quy tắc'!A"&MATCH("slaComplaintClose_days",'CH2. Tham số & Quy tắc'!$A:$A,0),slaComplaintClose_days&" ngày") -> 7 ngày | F91: complaint_status = resolved (Đã giải quyết)
A93: PHASE 10: KẾT THÚC KHÓA + TÁI ĐĂNG KÝ
A94: Tình huống | B94: Điều kiện | C94: Hành động | D94: Người làm | E94: SLA | F94: Kết quả / Trạng thái mới
A95: ="class_end_date còn ≤ "&thresholdPreEnd_days&" ngày (HV sắp kết thúc khóa)" -> class_end_date còn ≤ 30 ngày (HV sắp kết thúc khóa) | B95: ="class_end_date (DL10) còn "&thresholdPreEnd_days&" ngày" -> class_end_date (DL10) còn 30 ngày | C95: NV TV liên hệ giới thiệu khóa tiếp theo | D95: NV TV | E95: =HYPERLINK("#'CH2. Tham số & Quy tắc'!A"&MATCH("thresholdPreEnd_days",'CH2. Tham số & Quy tắc'!$A:$A,0),"Trước "&thresholdPreEnd_days&" ngày") -> Trước 30 ngày | F95: Có deal mới
A96: student_status = completed (Hoàn thành khóa) | B96: Đã hoàn thành buổi cuối | C96: Gửi survey end_of_course + cert hoàn thành | D96: Học vụ | E96: =HYPERLINK("#'CH2. Tham số & Quy tắc'!A"&MATCH("slaFinalTest_days",'CH2. Tham số & Quy tắc'!$A:$A,0),slaFinalTest_days&" ngày") -> 3 ngày | F96: Ghi: student_status = finished
A97: achievement_status = achieved (Đạt mục tiêu) | B97: final_test_score ≥ target_band | C97: Xin testimonial + giới thiệu (referral) | D97: Học vụ + NV TV | E97: =HYPERLINK("#'CH2. Tham số & Quy tắc'!A"&MATCH("slaReenrollSchedule_days",'CH2. Tham số & Quy tắc'!$A:$A,0),slaReenrollSchedule_days&" ngày") -> 14 ngày | F97: achievement_note
A98: achievement_status = not_achieved (Không cải thiện đáng kể) | B98: final_test_score < target_band | C98: Phân tích + đề xuất khóa tiếp tục với CK | D98: NV TV | E98: =HYPERLINK("#'CH2. Tham số & Quy tắc'!A"&MATCH("slaReenroll_contact_days",'CH2. Tham số & Quy tắc'!$A:$A,0),slaReenroll_contact_days&" ngày") -> 3 ngày | F98: enroll khóa mới
A99: ="re_enrollment_status = not_contacted (Chưa LH) + quá "&thresholdReenrollLost_days&" ngày sau kết thúc chưa đăng ký lại" -> re_enrollment_status = not_contacted (Chưa LH) + quá 90 ngày sau kết thúc chưa đăng ký lại | B99: =thresholdReenrollLost_days&" ngày sau KT chưa enroll lại" -> 90 ngày sau KT chưa enroll lại | C99: Đưa vào kênh nurture lâu dài | D99: MKT | E99: =HYPERLINK("#'CH2. Tham số & Quy tắc'!A"&MATCH("thresholdReenrollLost_days",'CH2. Tham số & Quy tắc'!$A:$A,0),thresholdReenrollLost_days&" ngày") -> 90 ngày | F99: lead_long_term

Sheet HD3. Sổ trigger & tự động
A1: HD3 - SỔ TRIGGER & TỰ ĐỘNG HÓA (mọi thứ hệ thống tự làm, tra cứu tại đây)
A2: 5 phần: (1) Nhắc việc & gợi ý chuyển trạng thái - điều kiện nào ra câu nào; (2) Dấu giờ tự động - đổi trạng thái là hệ thống tự điền giờ; (3) Quy tắc màu; (4) Cột tự tính - cột nào không nhập tay; (5) Bảng báo cáo tự lọc. Cột "Mở ô" bấm để nhảy thẳng tới công thức thật đang chạy.
A4: Loại | B4: Tình huống | C4: KHI NÀO / CÁCH TÍNH | D4: Mã | E4: Nội dung hiển thị | F4: Người phụ trách | G4: Chỉnh NGƯỠNG tại | H4: Chỉnh CÂU tại | I4: Mở ô (xem thử)
A5: PHẦN 1 - NHẮC VIỆC (next_action) & GỢI Ý CHUYỂN TRẠNG THÁI (auto_trigger_hint)
A6: DL02. Khách tiềm năng
A7: next_action | B7: Lead giao quá hạn chưa gọi | C7: lead_status chưa đóng, đã có assigned_to (NV phụ trách) nhưng first_call_time (giờ liên hệ đầu) còn trống, và kể từ lead_created_time (giờ tạo lead) đã quá slaLeadReassign_hours | D7: NA046 | E7: {=IFERROR(INDEX('CH4. Thông điệp nhắc việc'!$G:$G,MATCH($D7,'CH4. Thông điệp nhắc việc'!$A:$A,0)),"")} -> Lead đã giao cho NV nhưng quá 4 giờ (cấu hình slaLeadReassign_hours) chưa gọi. Việc cần làm: gọi gấp hoặc giao lại cho NV khác. | F7: {=IFERROR(INDEX('CH4. Thông điệp nhắc việc'!$E:$E,MATCH($D7,'CH4. Thông điệp nhắc việc'!$A:$A,0)),"-")} -> NV Tư vấn | G7: =HYPERLINK("#'CH2. Tham số & Quy tắc'!B"&MATCH("slaLeadReassign_hours",'CH2. Tham số & Quy tắc'!$A:$A,0),"CH2: slaLeadReassign_hours") -> CH2: slaLeadReassign_hours | H7: =HYPERLINK("#'CH4. Thông điệp nhắc việc'!C"&MATCH("NA046",'CH4. Thông điệp nhắc việc'!$A:$A,0),"CH4: NA046") -> CH4: NA046 | I7: =HYPERLINK("#'DL02. Khách tiềm năng'!T4","Mở ô") -> Mở ô
A8: next_action | B8: Gọi đủ số lần, không phản hồi | C8: contact_count (số lần liên hệ) ≥ thresholdContacted_attempts và lead_status là no_response/considering | D8: NA047 | E8: {=IFERROR(INDEX('CH4. Thông điệp nhắc việc'!$G:$G,MATCH($D8,'CH4. Thông điệp nhắc việc'!$A:$A,0)),"")} -> Đã liên hệ đủ 5 lần (cấu hình thresholdContacted_attempts) mà khách không phản hồi. Việc cần làm: cân nhắc chuyển lead sang trạng thái không liên lạc được. | F8: {=IFERROR(INDEX('CH4. Thông điệp nhắc việc'!$E:$E,MATCH($D8,'CH4. Thông điệp nhắc việc'!$A:$A,0)),"-")} -> NV Tư vấn | G8: =HYPERLINK("#'CH2. Tham số & Quy tắc'!B"&MATCH("thresholdContacted_attempts",'CH2. Tham số & Quy tắc'!$A:$A,0),"CH2: thresholdContacted_attempts") -> CH2: thresholdContacted_attempts | H8: =HYPERLINK("#'CH4. Thông điệp nhắc việc'!C"&MATCH("NA047",'CH4. Thông điệp nhắc việc'!$A:$A,0),"CH4: NA047") -> CH4: NA047 | I8: =HYPERLINK("#'DL02. Khách tiềm năng'!T4","Mở ô") -> Mở ô
A9: next_action | B9: Đã liên hệ, quá ngày chưa chốt | C9: lead_status = contacted và kể từ last_contact_time (liên hệ gần nhất) đã quá thresholdContacted_days | D9: NA048 | E9: {=IFERROR(INDEX('CH4. Thông điệp nhắc việc'!$G:$G,MATCH($D9,'CH4. Thông điệp nhắc việc'!$A:$A,0)),"")} -> Đã liên hệ nhưng quá 7 ngày (cấu hình thresholdContacted_days) chưa chốt. Việc cần làm: đẩy mạnh tư vấn để chốt. | F9: {=IFERROR(INDEX('CH4. Thông điệp nhắc việc'!$E:$E,MATCH($D9,'CH4. Thông điệp nhắc việc'!$A:$A,0)),"-")} -> NV Tư vấn | G9: =HYPERLINK("#'CH2. Tham số & Quy tắc'!B"&MATCH("thresholdContacted_days",'CH2. Tham số & Quy tắc'!$A:$A,0),"CH2: thresholdContacted_days") -> CH2: thresholdContacted_days | H9: =HYPERLINK("#'CH4. Thông điệp nhắc việc'!C"&MATCH("NA048",'CH4. Thông điệp nhắc việc'!$A:$A,0),"CH4: NA048") -> CH4: NA048 | I9: =HYPERLINK("#'DL02. Khách tiềm năng'!T4","Mở ô") -> Mở ô
A10: next_action | B10: Lead mới quá hạn phản hồi | C10: lead_status = new và kể từ lead_created_time đã quá slaLRT_minutes phút | D10: NA049 | E10: {=IFERROR(INDEX('CH4. Thông điệp nhắc việc'!$G:$G,MATCH($D10,'CH4. Thông điệp nhắc việc'!$A:$A,0)),"")} -> Lead mới đã quá 15 phút (cấu hình slaLRT_minutes) chưa được liên hệ. Việc cần làm: GỌI NGAY để không mất lead. | F10: {=IFERROR(INDEX('CH4. Thông điệp nhắc việc'!$E:$E,MATCH($D10,'CH4. Thông điệp nhắc việc'!$A:$A,0)),"-")} -> NV Tư vấn | G10: =HYPERLINK("#'CH2. Tham số & Quy tắc'!B"&MATCH("slaLRT_minutes",'CH2. Tham số & Quy tắc'!$A:$A,0),"CH2: slaLRT_minutes") -> CH2: slaLRT_minutes | H10: =HYPERLINK("#'CH4. Thông điệp nhắc việc'!C"&MATCH("NA049",'CH4. Thông điệp nhắc việc'!$A:$A,0),"CH4: NA049") -> CH4: NA049 | I10: =HYPERLINK("#'DL02. Khách tiềm năng'!T4","Mở ô") -> Mở ô
A11: next_action | B11: Lead mới còn trong hạn | C11: lead_status = new và còn trong hạn slaLRT_minutes phút kể từ lead_created_time | D11: NA050 | E11: {=IFERROR(INDEX('CH4. Thông điệp nhắc việc'!$G:$G,MATCH($D11,'CH4. Thông điệp nhắc việc'!$A:$A,0)),"")} -> Lead mới, còn trong hạn phản hồi 15 phút (cấu hình slaLRT_minutes). Việc cần làm: liên hệ khách càng sớm càng tốt. | F11: {=IFERROR(INDEX('CH4. Thông điệp nhắc việc'!$E:$E,MATCH($D11,'CH4. Thông điệp nhắc việc'!$A:$A,0)),"-")} -> NV Tư vấn | G11: =HYPERLINK("#'CH2. Tham số & Quy tắc'!B"&MATCH("slaLRT_minutes",'CH2. Tham số & Quy tắc'!$A:$A,0),"CH2: slaLRT_minutes") -> CH2: slaLRT_minutes | H11: =HYPERLINK("#'CH4. Thông điệp nhắc việc'!C"&MATCH("NA050",'CH4. Thông điệp nhắc việc'!$A:$A,0),"CH4: NA050") -> CH4: NA050 | I11: =HYPERLINK("#'DL02. Khách tiềm năng'!T4","Mở ô") -> Mở ô
A12: next_action | B12: Tới/quá hẹn theo dõi | C12: lead_status = contacted/considering/no_response và next_followup_time (lịch liên hệ tiếp) ≤ hôm nay | D12: NA051 | E12: {=IFERROR(INDEX('CH4. Thông điệp nhắc việc'!$G:$G,MATCH($D12,'CH4. Thông điệp nhắc việc'!$A:$A,0)),"")} -> Đã tới hoặc quá hẹn theo dõi lead. Việc cần làm: liên hệ lại ngay. | F12: {=IFERROR(INDEX('CH4. Thông điệp nhắc việc'!$E:$E,MATCH($D12,'CH4. Thông điệp nhắc việc'!$A:$A,0)),"-")} -> NV Tư vấn | G12: - | H12: =HYPERLINK("#'CH4. Thông điệp nhắc việc'!C"&MATCH("NA051",'CH4. Thông điệp nhắc việc'!$A:$A,0),"CH4: NA051") -> CH4: NA051 | I12: =HYPERLINK("#'DL02. Khách tiềm năng'!T4","Mở ô") -> Mở ô
A13: next_action | B13: Sắp tới hẹn theo dõi | C13: next_followup_time (lịch liên hệ tiếp) ≤ hôm nay + 1 (trong 24 giờ) | D13: NA052 | E13: {=IFERROR(INDEX('CH4. Thông điệp nhắc việc'!$G:$G,MATCH($D13,'CH4. Thông điệp nhắc việc'!$A:$A,0)),"")} -> Sắp tới hẹn theo dõi lead (trong vòng 24 giờ). Việc cần làm: chuẩn bị liên hệ khách. | F13: {=IFERROR(INDEX('CH4. Thông điệp nhắc việc'!$E:$E,MATCH($D13,'CH4. Thông điệp nhắc việc'!$A:$A,0)),"-")} -> NV Tư vấn | G13: - | H13: =HYPERLINK("#'CH4. Thông điệp nhắc việc'!C"&MATCH("NA052",'CH4. Thông điệp nhắc việc'!$A:$A,0),"CH4: NA052") -> CH4: NA052 | I13: =HYPERLINK("#'DL02. Khách tiềm năng'!T4","Mở ô") -> Mở ô
A14: next_action | B14: Lead đã đóng | C14: lead_status = rejected (từ chối) hoặc unreachable (không liên lạc được) | D14: NA053 | E14: {=IFERROR(INDEX('CH4. Thông điệp nhắc việc'!$G:$G,MATCH($D14,'CH4. Thông điệp nhắc việc'!$A:$A,0)),"")} -> Lead đã đóng (từ chối hoặc không liên lạc được). Không cần làm gì thêm. | F14: {=IFERROR(INDEX('CH4. Thông điệp nhắc việc'!$E:$E,MATCH($D14,'CH4. Thông điệp nhắc việc'!$A:$A,0)),"-")} -> - | G14: - | H14: =HYPERLINK("#'CH4. Thông điệp nhắc việc'!C"&MATCH("NA053",'CH4. Thông điệp nhắc việc'!$A:$A,0),"CH4: NA053") -> CH4: NA053 | I14: =HYPERLINK("#'DL02. Khách tiềm năng'!T4","Mở ô") -> Mở ô
A15: DL03. Đặt lịch test
A16: next_action | B16: Có bài test, quá hạn chấm | C16: test_attendance_status (kết quả điểm danh) = on_time/late + test_status (trạng thái chấm bài) = pending, và kể từ test_attendance_time (giờ vào test thực tế) đã quá slaGLA_hours | D16: NA054 | E16: {=IFERROR(INDEX('CH4. Thông điệp nhắc việc'!$G:$G,MATCH($D16,'CH4. Thông điệp nhắc việc'!$A:$A,0)),"")} -> Khách đã làm test nhưng quá 24 giờ (cấu hình slaGLA_hours) chưa chấm bài. Việc cần làm: chấm bài test ngay. | F16: {=IFERROR(INDEX('CH4. Thông điệp nhắc việc'!$E:$E,MATCH($D16,'CH4. Thông điệp nhắc việc'!$A:$A,0)),"-")} -> Người chấm test | G16: =HYPERLINK("#'CH2. Tham số & Quy tắc'!B"&MATCH("slaGLA_hours",'CH2. Tham số & Quy tắc'!$A:$A,0),"CH2: slaGLA_hours") -> CH2: slaGLA_hours | H16: =HYPERLINK("#'CH4. Thông điệp nhắc việc'!C"&MATCH("NA054",'CH4. Thông điệp nhắc việc'!$A:$A,0),"CH4: NA054") -> CH4: NA054 | I16: =HYPERLINK("#'DL03. Đặt lịch test'!U4","Mở ô") -> Mở ô
A17: next_action | B17: Có bài test, còn trong hạn chấm | C17: test_attendance_status = on_time/late + test_status = pending, còn trong hạn slaGLA_hours kể từ test_attendance_time | D17: NA055 | E17: {=IFERROR(INDEX('CH4. Thông điệp nhắc việc'!$G:$G,MATCH($D17,'CH4. Thông điệp nhắc việc'!$A:$A,0)),"")} -> Bài test chờ chấm, còn trong hạn 24 giờ (cấu hình slaGLA_hours). Việc cần làm: chấm bài sớm để kịp tư vấn. | F17: {=IFERROR(INDEX('CH4. Thông điệp nhắc việc'!$E:$E,MATCH($D17,'CH4. Thông điệp nhắc việc'!$A:$A,0)),"-")} -> Người chấm test | G17: =HYPERLINK("#'CH2. Tham số & Quy tắc'!B"&MATCH("slaGLA_hours",'CH2. Tham số & Quy tắc'!$A:$A,0),"CH2: slaGLA_hours") -> CH2: slaGLA_hours | H17: =HYPERLINK("#'CH4. Thông điệp nhắc việc'!C"&MATCH("NA055",'CH4. Thông điệp nhắc việc'!$A:$A,0),"CH4: NA055") -> CH4: NA055 | I17: =HYPERLINK("#'DL03. Đặt lịch test'!U4","Mở ô") -> Mở ô
A18: next_action | B18: Đã chấm, chưa chuyển trạng thái | C18: test_status = graded (đã chấm xong) và post_test_status (trạng thái sau test) còn trống | D18: NA056 | E18: {=IFERROR(INDEX('CH4. Thông điệp nhắc việc'!$G:$G,MATCH($D18,'CH4. Thông điệp nhắc việc'!$A:$A,0)),"")} -> Đã chấm xong bài test. Việc cần làm: chuyển trạng thái sau test sang chờ tư vấn (awaiting). | F18: {=IFERROR(INDEX('CH4. Thông điệp nhắc việc'!$E:$E,MATCH($D18,'CH4. Thông điệp nhắc việc'!$A:$A,0)),"-")} -> NV Tư vấn | G18: - | H18: =HYPERLINK("#'CH4. Thông điệp nhắc việc'!C"&MATCH("NA056",'CH4. Thông điệp nhắc việc'!$A:$A,0),"CH4: NA056") -> CH4: NA056 | I18: =HYPERLINK("#'DL03. Đặt lịch test'!U4","Mở ô") -> Mở ô
A19: next_action | B19: Quá hạn tư vấn sau test | C19: post_test_status = awaiting (chờ tư vấn) và kể từ result_time (thời gian trả kết quả) đã quá slaCVT_hours | D19: NA001 | E19: {=IFERROR(INDEX('CH4. Thông điệp nhắc việc'!$G:$G,MATCH($D19,'CH4. Thông điệp nhắc việc'!$A:$A,0)),"")} -> Khách đã có kết quả test nhưng quá 24 giờ (cấu hình slaCVT_hours) chưa được tư vấn. Việc cần làm: tư vấn ngay để chốt khi khách còn quan tâm. | F19: {=IFERROR(INDEX('CH4. Thông điệp nhắc việc'!$E:$E,MATCH($D19,'CH4. Thông điệp nhắc việc'!$A:$A,0)),"-")} -> NV Tư vấn | G19: =HYPERLINK("#'CH2. Tham số & Quy tắc'!B"&MATCH("slaCVT_hours",'CH2. Tham số & Quy tắc'!$A:$A,0),"CH2: slaCVT_hours") -> CH2: slaCVT_hours | H19: =HYPERLINK("#'CH4. Thông điệp nhắc việc'!C"&MATCH("NA001",'CH4. Thông điệp nhắc việc'!$A:$A,0),"CH4: NA001") -> CH4: NA001 | I19: =HYPERLINK("#'DL03. Đặt lịch test'!U4","Mở ô") -> Mở ô
A20: next_action | B20: Đã tư vấn xong | C20: post_test_status = consulted (đã tư vấn) | D20: NA002 | E20: {=IFERROR(INDEX('CH4. Thông điệp nhắc việc'!$G:$G,MATCH($D20,'CH4. Thông điệp nhắc việc'!$A:$A,0)),"")} -> Đã tư vấn xong cho khách. Không cần làm gì thêm ở bước này. | F20: {=IFERROR(INDEX('CH4. Thông điệp nhắc việc'!$E:$E,MATCH($D20,'CH4. Thông điệp nhắc việc'!$A:$A,0)),"-")} -> NV Tư vấn | G20: - | H20: =HYPERLINK("#'CH4. Thông điệp nhắc việc'!C"&MATCH("NA002",'CH4. Thông điệp nhắc việc'!$A:$A,0),"CH4: NA002") -> CH4: NA002 | I20: =HYPERLINK("#'DL03. Đặt lịch test'!U4","Mở ô") -> Mở ô
A21: auto_trigger_hint | B21: Chấm xong, cần chuyển trạng thái | C21: test_status = graded (đã chấm xong) và post_test_status (trạng thái sau test) còn trống | D21: NA085 | E21: {=IFERROR(INDEX('CH4. Thông điệp nhắc việc'!$G:$G,MATCH($D21,'CH4. Thông điệp nhắc việc'!$A:$A,0)),"")} -> Cập nhật post_test_status = awaiting_consultation (chờ tư vấn) | F21: {=IFERROR(INDEX('CH4. Thông điệp nhắc việc'!$E:$E,MATCH($D21,'CH4. Thông điệp nhắc việc'!$A:$A,0)),"-")} -> Học vụ / hệ thống | G21: - | H21: =HYPERLINK("#'CH4. Thông điệp nhắc việc'!C"&MATCH("NA085",'CH4. Thông điệp nhắc việc'!$A:$A,0),"CH4: NA085") -> CH4: NA085 | I21: =HYPERLINK("#'DL03. Đặt lịch test'!T4","Mở ô") -> Mở ô
A22: auto_trigger_hint | B22: Chờ tư vấn, cần tạo bản ghi TV | C22: test_status = graded và post_test_status = awaiting (chờ tư vấn) | D22: NA086 | E22: {=IFERROR(INDEX('CH4. Thông điệp nhắc việc'!$G:$G,MATCH($D22,'CH4. Thông điệp nhắc việc'!$A:$A,0)),"")} -> Tạo Tư vấn mới (CS-...) cho lead này ở sheet DL04 | F22: {=IFERROR(INDEX('CH4. Thông điệp nhắc việc'!$E:$E,MATCH($D22,'CH4. Thông điệp nhắc việc'!$A:$A,0)),"-")} -> NV Tư vấn | G22: - | H22: =HYPERLINK("#'CH4. Thông điệp nhắc việc'!C"&MATCH("NA086",'CH4. Thông điệp nhắc việc'!$A:$A,0),"CH4: NA086") -> CH4: NA086 | I22: =HYPERLINK("#'DL03. Đặt lịch test'!T4","Mở ô") -> Mở ô
A23: DL04. Tư vấn
A24: next_action | B24: Quan tâm, quá hạn chưa chốt | C24: conversion_status (kết quả tư vấn) = interested và kể từ conversion_time (thời gian cập nhật kết quả) đã quá slaFollowup_grace_days | D24: NA003 | E24: {=IFERROR(INDEX('CH4. Thông điệp nhắc việc'!$G:$G,MATCH($D24,'CH4. Thông điệp nhắc việc'!$A:$A,0)),"")} -> Khách quan tâm nhưng đã quá 3 ngày (cấu hình slaFollowup_grace_days) chưa chốt. Việc cần làm: liên hệ chốt ngay khi khách còn quan tâm. | F24: {=IFERROR(INDEX('CH4. Thông điệp nhắc việc'!$E:$E,MATCH($D24,'CH4. Thông điệp nhắc việc'!$A:$A,0)),"-")} -> NV Tư vấn | G24: =HYPERLINK("#'CH2. Tham số & Quy tắc'!B"&MATCH("slaFollowup_grace_days",'CH2. Tham số & Quy tắc'!$A:$A,0),"CH2: slaFollowup_grace_days") -> CH2: slaFollowup_grace_days | H24: =HYPERLINK("#'CH4. Thông điệp nhắc việc'!C"&MATCH("NA003",'CH4. Thông điệp nhắc việc'!$A:$A,0),"CH4: NA003") -> CH4: NA003 | I24: =HYPERLINK("#'DL04. Tư vấn'!N4","Mở ô") -> Mở ô
A25: next_action | B25: Đồng ý + đặt cọc | C25: conversion_status = confirmed_with_deposit | D25: NA057 | E25: {=IFERROR(INDEX('CH4. Thông điệp nhắc việc'!$G:$G,MATCH($D25,'CH4. Thông điệp nhắc việc'!$A:$A,0)),"")} -> Khách đã đồng ý và đặt cọc. Việc cần làm: tạo đăng ký và thu cọc (chuyển sang sheet DL06 Đăng ký). | F25: {=IFERROR(INDEX('CH4. Thông điệp nhắc việc'!$E:$E,MATCH($D25,'CH4. Thông điệp nhắc việc'!$A:$A,0)),"-")} -> NV Tư vấn | G25: - | H25: =HYPERLINK("#'CH4. Thông điệp nhắc việc'!C"&MATCH("NA057",'CH4. Thông điệp nhắc việc'!$A:$A,0),"CH4: NA057") -> CH4: NA057 | I25: =HYPERLINK("#'DL04. Tư vấn'!N4","Mở ô") -> Mở ô
A26: next_action | B26: Khách bỏ | C26: conversion_status = dropped | D26: NA058 | E26: {=IFERROR(INDEX('CH4. Thông điệp nhắc việc'!$G:$G,MATCH($D26,'CH4. Thông điệp nhắc việc'!$A:$A,0)),"")} -> Khách đã bỏ, không tiếp tục. Không cần làm gì thêm. | F26: {=IFERROR(INDEX('CH4. Thông điệp nhắc việc'!$E:$E,MATCH($D26,'CH4. Thông điệp nhắc việc'!$A:$A,0)),"-")} -> - | G26: - | H26: =HYPERLINK("#'CH4. Thông điệp nhắc việc'!C"&MATCH("NA058",'CH4. Thông điệp nhắc việc'!$A:$A,0),"CH4: NA058") -> CH4: NA058 | I26: =HYPERLINK("#'DL04. Tư vấn'!N4","Mở ô") -> Mở ô
A27: next_action | B27: Chưa quyết định | C27: conversion_status = undecided | D27: NA004 | E27: {=IFERROR(INDEX('CH4. Thông điệp nhắc việc'!$G:$G,MATCH($D27,'CH4. Thông điệp nhắc việc'!$A:$A,0)),"")} -> Khách chưa quyết định, vẫn trong thời gian theo dõi cho phép. Việc cần làm: tiếp tục theo dõi và chăm sóc. | F27: {=IFERROR(INDEX('CH4. Thông điệp nhắc việc'!$E:$E,MATCH($D27,'CH4. Thông điệp nhắc việc'!$A:$A,0)),"-")} -> NV Tư vấn | G27: - | H27: =HYPERLINK("#'CH4. Thông điệp nhắc việc'!C"&MATCH("NA004",'CH4. Thông điệp nhắc việc'!$A:$A,0),"CH4: NA004") -> CH4: NA004 | I27: =HYPERLINK("#'DL04. Tư vấn'!N4","Mở ô") -> Mở ô
A28: DL06. Đăng ký
A29: next_action | B29: Đăng ký đã hủy | C29: enrollment_status (trạng thái đăng ký) = cancelled | D29: NA059 | E29: {=IFERROR(INDEX('CH4. Thông điệp nhắc việc'!$G:$G,MATCH($D29,'CH4. Thông điệp nhắc việc'!$A:$A,0)),"")} -> Đăng ký đã hủy. Chính sách hoàn tiền (cấu hình): hoàn 100% nếu hủy trong 7 ngày, hoàn một phần nếu trong 14 ngày, hoàn mức thấp nếu trong 30 ngày, quá thì không hoàn. Việc cần làm: kiểm tra ngày hủy và xử lý hoàn tiền. | F29: {=IFERROR(INDEX('CH4. Thông điệp nhắc việc'!$E:$E,MATCH($D29,'CH4. Thông điệp nhắc việc'!$A:$A,0)),"-")} -> Kế toán / Học vụ | G29: =HYPERLINK("#'CH2. Tham số & Quy tắc'!B"&MATCH("refundFull_days",'CH2. Tham số & Quy tắc'!$A:$A,0),"CH2: refundFull_days +2") -> CH2: refundFull_days +2 | H29: =HYPERLINK("#'CH4. Thông điệp nhắc việc'!C"&MATCH("NA059",'CH4. Thông điệp nhắc việc'!$A:$A,0),"CH4: NA059") -> CH4: NA059 | I29: =HYPERLINK("#'DL06. Đăng ký'!T4","Mở ô") -> Mở ô
A30: next_action | B30: Chờ quá hạn (nên hủy) | C30: enrollment_status = pending và kể từ enrollment_time (thời gian xác nhận) đã quá slaENR_cancel_hours | D30: NA060 | E30: {=IFERROR(INDEX('CH4. Thông điệp nhắc việc'!$G:$G,MATCH($D30,'CH4. Thông điệp nhắc việc'!$A:$A,0)),"")} -> Đăng ký để ở trạng thái chờ quá 72 giờ (cấu hình slaENR_cancel_hours). Việc cần làm: cân nhắc hủy đăng ký ngay để dọn dữ liệu ảo. | F30: {=IFERROR(INDEX('CH4. Thông điệp nhắc việc'!$E:$E,MATCH($D30,'CH4. Thông điệp nhắc việc'!$A:$A,0)),"-")} -> NV Tư vấn / Học vụ | G30: =HYPERLINK("#'CH2. Tham số & Quy tắc'!B"&MATCH("slaENR_cancel_hours",'CH2. Tham số & Quy tắc'!$A:$A,0),"CH2: slaENR_cancel_hours") -> CH2: slaENR_cancel_hours | H30: =HYPERLINK("#'CH4. Thông điệp nhắc việc'!C"&MATCH("NA060",'CH4. Thông điệp nhắc việc'!$A:$A,0),"CH4: NA060") -> CH4: NA060 | I30: =HYPERLINK("#'DL06. Đăng ký'!T4","Mở ô") -> Mở ô
A31: next_action | B31: Giảm giá vượt mức | C31: discount_amount (tiền chiết khấu) > thresholdDiscount_approval và discount_approved_by (người duyệt) còn trống | D31: NA061 | E31: {=IFERROR(INDEX('CH4. Thông điệp nhắc việc'!$G:$G,MATCH($D31,'CH4. Thông điệp nhắc việc'!$A:$A,0)),"")} -> Khoản giảm giá vượt mức cho phép 1,000,000đ (cấu hình thresholdDiscount_approval). Việc cần làm: trình cấp trên duyệt trước khi áp dụng. | F31: {=IFERROR(INDEX('CH4. Thông điệp nhắc việc'!$E:$E,MATCH($D31,'CH4. Thông điệp nhắc việc'!$A:$A,0)),"-")} -> Quản lý | G31: =HYPERLINK("#'CH2. Tham số & Quy tắc'!B"&MATCH("thresholdDiscount_approval",'CH2. Tham số & Quy tắc'!$A:$A,0),"CH2: thresholdDiscount_approval") -> CH2: thresholdDiscount_approval | H31: =HYPERLINK("#'CH4. Thông điệp nhắc việc'!C"&MATCH("NA061",'CH4. Thông điệp nhắc việc'!$A:$A,0),"CH4: NA061") -> CH4: NA061 | I31: =HYPERLINK("#'DL06. Đăng ký'!T4","Mở ô") -> Mở ô
A32: next_action | B32: Chờ quá hạn xác nhận | C32: enrollment_status = pending và kể từ enrollment_time đã quá slaENR_pending_hours | D32: NA005 | E32: {=IFERROR(INDEX('CH4. Thông điệp nhắc việc'!$G:$G,MATCH($D32,'CH4. Thông điệp nhắc việc'!$A:$A,0)),"")} -> Đăng ký ở trạng thái chờ đã quá 24 giờ (cấu hình slaENR_pending_hours). Việc cần làm: xác nhận hoặc hủy đăng ký ngay. | F32: {=IFERROR(INDEX('CH4. Thông điệp nhắc việc'!$E:$E,MATCH($D32,'CH4. Thông điệp nhắc việc'!$A:$A,0)),"-")} -> NV Tư vấn / Học vụ | G32: =HYPERLINK("#'CH2. Tham số & Quy tắc'!B"&MATCH("slaENR_pending_hours",'CH2. Tham số & Quy tắc'!$A:$A,0),"CH2: slaENR_pending_hours") -> CH2: slaENR_pending_hours | H32: =HYPERLINK("#'CH4. Thông điệp nhắc việc'!C"&MATCH("NA005",'CH4. Thông điệp nhắc việc'!$A:$A,0),"CH4: NA005") -> CH4: NA005 | I32: =HYPERLINK("#'DL06. Đăng ký'!T4","Mở ô") -> Mở ô
A33: next_action | B33: Xác nhận nhưng chưa thu tiền | C33: enrollment_status = confirmed và payment_status (trạng thái thanh toán) = unpaid | D33: NA006 | E33: {=IFERROR(INDEX('CH4. Thông điệp nhắc việc'!$G:$G,MATCH($D33,'CH4. Thông điệp nhắc việc'!$A:$A,0)),"")} -> Đăng ký đã xác nhận nhưng chưa thu được tiền. Việc cần làm: thu học phí ngay. | F33: {=IFERROR(INDEX('CH4. Thông điệp nhắc việc'!$E:$E,MATCH($D33,'CH4. Thông điệp nhắc việc'!$A:$A,0)),"-")} -> NV Tư vấn | G33: - | H33: =HYPERLINK("#'CH4. Thông điệp nhắc việc'!C"&MATCH("NA006",'CH4. Thông điệp nhắc việc'!$A:$A,0),"CH4: NA006") -> CH4: NA006 | I33: =HYPERLINK("#'DL06. Đăng ký'!T4","Mở ô") -> Mở ô
A34: next_action | B34: Còn nợ học phí và quá hạn | C34: payment_status = partial + remaining_amount (còn lại) > 0, và kể từ enrollment_time đã quá slaPayment_grace_days | D34: NA007 | E34: {=IFERROR(INDEX('CH4. Thông điệp nhắc việc'!$G:$G,MATCH($D34,'CH4. Thông điệp nhắc việc'!$A:$A,0)),"")} -> Còn khoản học phí chưa đóng và đã quá hạn 14 ngày (cấu hình slaPayment_grace_days). Việc cần làm: nhắc HV đóng phần còn lại ngay. | F34: {=IFERROR(INDEX('CH4. Thông điệp nhắc việc'!$E:$E,MATCH($D34,'CH4. Thông điệp nhắc việc'!$A:$A,0)),"-")} -> NV Tư vấn | G34: =HYPERLINK("#'CH2. Tham số & Quy tắc'!B"&MATCH("slaPayment_grace_days",'CH2. Tham số & Quy tắc'!$A:$A,0),"CH2: slaPayment_grace_days") -> CH2: slaPayment_grace_days | H34: =HYPERLINK("#'CH4. Thông điệp nhắc việc'!C"&MATCH("NA007",'CH4. Thông điệp nhắc việc'!$A:$A,0),"CH4: NA007") -> CH4: NA007 | I34: =HYPERLINK("#'DL06. Đăng ký'!T4","Mở ô") -> Mở ô
A35: next_action | B35: Xác nhận + đóng đủ | C35: enrollment_status = confirmed và payment_status = paid | D35: NA009 | E35: {=IFERROR(INDEX('CH4. Thông điệp nhắc việc'!$G:$G,MATCH($D35,'CH4. Thông điệp nhắc việc'!$A:$A,0)),"")} -> Đăng ký đã xác nhận và HV đã đóng đủ tiền. Không cần làm gì thêm. | F35: {=IFERROR(INDEX('CH4. Thông điệp nhắc việc'!$E:$E,MATCH($D35,'CH4. Thông điệp nhắc việc'!$A:$A,0)),"-")} -> - | G35: - | H35: =HYPERLINK("#'CH4. Thông điệp nhắc việc'!C"&MATCH("NA009",'CH4. Thông điệp nhắc việc'!$A:$A,0),"CH4: NA009") -> CH4: NA009 | I35: =HYPERLINK("#'DL06. Đăng ký'!T4","Mở ô") -> Mở ô
A36: auto_trigger_hint | B36: Đủ cọc, còn ở trạng thái chờ | C36: paid_amount (đã thanh toán) ≥ thresholdDeposit_minimum và enrollment_status = pending | D36: NA087 | E36: {=IFERROR(INDEX('CH4. Thông điệp nhắc việc'!$G:$G,MATCH($D36,'CH4. Thông điệp nhắc việc'!$A:$A,0)),"")} -> Đã đủ cọc tối thiểu 5,000,000đ - chuyển enrollment_status = confirmed và tạo Onboarding (DL08) | F36: {=IFERROR(INDEX('CH4. Thông điệp nhắc việc'!$E:$E,MATCH($D36,'CH4. Thông điệp nhắc việc'!$A:$A,0)),"-")} -> Kế toán / Học vụ | G36: =HYPERLINK("#'CH2. Tham số & Quy tắc'!B"&MATCH("thresholdDeposit_minimum",'CH2. Tham số & Quy tắc'!$A:$A,0),"CH2: thresholdDeposit_minimum") -> CH2: thresholdDeposit_minimum | H36: =HYPERLINK("#'CH4. Thông điệp nhắc việc'!C"&MATCH("NA087",'CH4. Thông điệp nhắc việc'!$A:$A,0),"CH4: NA087") -> CH4: NA087 | I36: =HYPERLINK("#'DL06. Đăng ký'!S4","Mở ô") -> Mở ô
A37: auto_trigger_hint | B37: Đã thanh toán đủ | C37: payment_status = paid (không phải partial/unpaid) | D37: NA088 | E37: {=IFERROR(INDEX('CH4. Thông điệp nhắc việc'!$G:$G,MATCH($D37,'CH4. Thông điệp nhắc việc'!$A:$A,0)),"")} -> Đã thanh toán đủ - chuyển sang Onboarding (DL08) nếu chưa | F37: {=IFERROR(INDEX('CH4. Thông điệp nhắc việc'!$E:$E,MATCH($D37,'CH4. Thông điệp nhắc việc'!$A:$A,0)),"-")} -> Kế toán / Học vụ | G37: - | H37: =HYPERLINK("#'CH4. Thông điệp nhắc việc'!C"&MATCH("NA088",'CH4. Thông điệp nhắc việc'!$A:$A,0),"CH4: NA088") -> CH4: NA088 | I37: =HYPERLINK("#'DL06. Đăng ký'!S4","Mở ô") -> Mở ô
A38: DL08. Xếp lớp & Nhập học
A39: next_action | B39: Quá hạn gửi thông tin Zalo | C39: placement_status (trạng thái xếp lớp) = assigned + class_confirmation_status (xác nhận lớp của HV) = pending, và kể từ assigned_at (thời gian xếp lớp) đã quá slaClassInfoZalo_hours | D39: NA062 | E39: {=IFERROR(INDEX('CH4. Thông điệp nhắc việc'!$G:$G,MATCH($D39,'CH4. Thông điệp nhắc việc'!$A:$A,0)),"")} -> Đã xếp lớp nhưng quá 24 giờ (cấu hình slaClassInfoZalo_hours) chưa gửi thông tin lớp. Việc cần làm: gửi thông tin lớp qua Zalo cho HV ngay. | F39: {=IFERROR(INDEX('CH4. Thông điệp nhắc việc'!$E:$E,MATCH($D39,'CH4. Thông điệp nhắc việc'!$A:$A,0)),"-")} -> Học vụ | G39: =HYPERLINK("#'CH2. Tham số & Quy tắc'!B"&MATCH("slaClassInfoZalo_hours",'CH2. Tham số & Quy tắc'!$A:$A,0),"CH2: slaClassInfoZalo_hours") -> CH2: slaClassInfoZalo_hours | H39: =HYPERLINK("#'CH4. Thông điệp nhắc việc'!C"&MATCH("NA062",'CH4. Thông điệp nhắc việc'!$A:$A,0),"CH4: NA062") -> CH4: NA062 | I39: =HYPERLINK("#'DL08. Xếp lớp & Nhập học'!Q4","Mở ô") -> Mở ô
A40: next_action | B40: Quá hạn xếp lớp | C40: placement_status = not_assigned và kể từ assigned_at đã quá slaPLR48_hours | D40: NA063 | E40: {=IFERROR(INDEX('CH4. Thông điệp nhắc việc'!$G:$G,MATCH($D40,'CH4. Thông điệp nhắc việc'!$A:$A,0)),"")} -> Đăng ký đã xác nhận nhưng quá 48 giờ (cấu hình slaPLR48_hours) chưa xếp lớp. Việc cần làm: xếp lớp ngay. | F40: {=IFERROR(INDEX('CH4. Thông điệp nhắc việc'!$E:$E,MATCH($D40,'CH4. Thông điệp nhắc việc'!$A:$A,0)),"-")} -> Học vụ | G40: =HYPERLINK("#'CH2. Tham số & Quy tắc'!B"&MATCH("slaPLR48_hours",'CH2. Tham số & Quy tắc'!$A:$A,0),"CH2: slaPLR48_hours") -> CH2: slaPLR48_hours | H40: =HYPERLINK("#'CH4. Thông điệp nhắc việc'!C"&MATCH("NA063",'CH4. Thông điệp nhắc việc'!$A:$A,0),"CH4: NA063") -> CH4: NA063 | I40: =HYPERLINK("#'DL08. Xếp lớp & Nhập học'!Q4","Mở ô") -> Mở ô
A41: next_action | B41: Quá hạn nhập học (đã xếp) | C41: placement_status = assigned và kể từ assigned_at đã quá slaOBT_hours | D41: NA010 | E41: {=IFERROR(INDEX('CH4. Thông điệp nhắc việc'!$G:$G,MATCH($D41,'CH4. Thông điệp nhắc việc'!$A:$A,0)),"")} -> Đã xếp lớp nhưng quá 72 giờ (cấu hình slaOBT_hours) chưa hoàn tất nhập học. Việc cần làm: kiểm tra và đẩy nhanh nhập học ngay. | F41: {=IFERROR(INDEX('CH4. Thông điệp nhắc việc'!$E:$E,MATCH($D41,'CH4. Thông điệp nhắc việc'!$A:$A,0)),"-")} -> Học vụ | G41: =HYPERLINK("#'CH2. Tham số & Quy tắc'!B"&MATCH("slaOBT_hours",'CH2. Tham số & Quy tắc'!$A:$A,0),"CH2: slaOBT_hours") -> CH2: slaOBT_hours | H41: =HYPERLINK("#'CH4. Thông điệp nhắc việc'!C"&MATCH("NA010",'CH4. Thông điệp nhắc việc'!$A:$A,0),"CH4: NA010") -> CH4: NA010 | I41: =HYPERLINK("#'DL08. Xếp lớp & Nhập học'!Q4","Mở ô") -> Mở ô
A42: next_action | B42: Quá hạn nhập học (đang làm) | C42: onboarding_status = in_progress và kể từ assigned_at đã quá slaOBT_hours | D42: NA011 | E42: {=IFERROR(INDEX('CH4. Thông điệp nhắc việc'!$G:$G,MATCH($D42,'CH4. Thông điệp nhắc việc'!$A:$A,0)),"")} -> Nhập học đang dở và đã quá 72 giờ (cấu hình slaOBT_hours). Việc cần làm: gửi tài liệu và hoàn tất thủ tục ngay. | F42: {=IFERROR(INDEX('CH4. Thông điệp nhắc việc'!$E:$E,MATCH($D42,'CH4. Thông điệp nhắc việc'!$A:$A,0)),"-")} -> Học vụ | G42: =HYPERLINK("#'CH2. Tham số & Quy tắc'!B"&MATCH("slaOBT_hours",'CH2. Tham số & Quy tắc'!$A:$A,0),"CH2: slaOBT_hours") -> CH2: slaOBT_hours | H42: =HYPERLINK("#'CH4. Thông điệp nhắc việc'!C"&MATCH("NA011",'CH4. Thông điệp nhắc việc'!$A:$A,0),"CH4: NA011") -> CH4: NA011 | I42: =HYPERLINK("#'DL08. Xếp lớp & Nhập học'!Q4","Mở ô") -> Mở ô
A43: next_action | B43: Đã nhập học xong | C43: onboarding_status = completed | D43: NA012 | E43: {=IFERROR(INDEX('CH4. Thông điệp nhắc việc'!$G:$G,MATCH($D43,'CH4. Thông điệp nhắc việc'!$A:$A,0)),"")} -> HV đã hoàn tất nhập học. Không cần làm gì thêm. | F43: {=IFERROR(INDEX('CH4. Thông điệp nhắc việc'!$E:$E,MATCH($D43,'CH4. Thông điệp nhắc việc'!$A:$A,0)),"-")} -> Học vụ | G43: - | H43: =HYPERLINK("#'CH4. Thông điệp nhắc việc'!C"&MATCH("NA012",'CH4. Thông điệp nhắc việc'!$A:$A,0),"CH4: NA012") -> CH4: NA012 | I43: =HYPERLINK("#'DL08. Xếp lớp & Nhập học'!Q4","Mở ô") -> Mở ô
A44: next_action | B44: Còn trong hạn xử lý | C44: các trường hợp còn lại | D44: NA013 | E44: {=IFERROR(INDEX('CH4. Thông điệp nhắc việc'!$G:$G,MATCH($D44,'CH4. Thông điệp nhắc việc'!$A:$A,0)),"")} -> Đang trong thời hạn xử lý cho phép, chưa cần thúc. | F44: {=IFERROR(INDEX('CH4. Thông điệp nhắc việc'!$E:$E,MATCH($D44,'CH4. Thông điệp nhắc việc'!$A:$A,0)),"-")} -> Học vụ | G44: - | H44: =HYPERLINK("#'CH4. Thông điệp nhắc việc'!C"&MATCH("NA013",'CH4. Thông điệp nhắc việc'!$A:$A,0),"CH4: NA013") -> CH4: NA013 | I44: =HYPERLINK("#'DL08. Xếp lớp & Nhập học'!Q4","Mở ô") -> Mở ô
A45: auto_trigger_hint | B45: Xong xác nhận + onboarding | C45: placement đã xong + class_confirmation_status = confirmed (HV đã xác nhận lớp) + onboarding_status = completed | D45: NA089 | E45: {=IFERROR(INDEX('CH4. Thông điệp nhắc việc'!$G:$G,MATCH($D45,'CH4. Thông điệp nhắc việc'!$A:$A,0)),"")} -> Hoàn tất - set student.status = active (DL09) | F45: {=IFERROR(INDEX('CH4. Thông điệp nhắc việc'!$E:$E,MATCH($D45,'CH4. Thông điệp nhắc việc'!$A:$A,0)),"-")} -> Học vụ | G45: - | H45: =HYPERLINK("#'CH4. Thông điệp nhắc việc'!C"&MATCH("NA089",'CH4. Thông điệp nhắc việc'!$A:$A,0),"CH4: NA089") -> CH4: NA089 | I45: =HYPERLINK("#'DL08. Xếp lớp & Nhập học'!P4","Mở ô") -> Mở ô
A46: auto_trigger_hint | B46: Xác nhận rồi, chưa hoàn tất OB | C46: class_confirmation_status = confirmed (HV đã xác nhận lớp) nhưng onboarding_status chưa completed | D46: NA090 | E46: {=IFERROR(INDEX('CH4. Thông điệp nhắc việc'!$G:$G,MATCH($D46,'CH4. Thông điệp nhắc việc'!$A:$A,0)),"")} -> Gửi: lịch học + giáo trình + nội quy + LMS guide, rồi set onboarding_status = completed | F46: {=IFERROR(INDEX('CH4. Thông điệp nhắc việc'!$E:$E,MATCH($D46,'CH4. Thông điệp nhắc việc'!$A:$A,0)),"-")} -> Học vụ | G46: - | H46: =HYPERLINK("#'CH4. Thông điệp nhắc việc'!C"&MATCH("NA090",'CH4. Thông điệp nhắc việc'!$A:$A,0),"CH4: NA090") -> CH4: NA090 | I46: =HYPERLINK("#'DL08. Xếp lớp & Nhập học'!P4","Mở ô") -> Mở ô
A47: DL09. Học viên
A48: next_action | B48: Vắng vượt ngưỡng | C48: Đếm số buổi no_show (vắng) của HV này bên DL12 ≥ thresholdAtRisk_absences | D48: NA064 | E48: {=IFERROR(INDEX('CH4. Thông điệp nhắc việc'!$G:$G,MATCH($D48,'CH4. Thông điệp nhắc việc'!$A:$A,0)),"")} -> HV vắng không phép từ 2 buổi trở lên (cấu hình thresholdAtRisk_absences). Việc cần làm: đánh dấu nguy cơ chuyên cần, học vụ liên hệ HV ngay. | F48: {=IFERROR(INDEX('CH4. Thông điệp nhắc việc'!$E:$E,MATCH($D48,'CH4. Thông điệp nhắc việc'!$A:$A,0)),"-")} -> Học vụ | G48: =HYPERLINK("#'CH2. Tham số & Quy tắc'!B"&MATCH("thresholdAtRisk_absences",'CH2. Tham số & Quy tắc'!$A:$A,0),"CH2: thresholdAtRisk_absences") -> CH2: thresholdAtRisk_absences | H48: =HYPERLINK("#'CH4. Thông điệp nhắc việc'!C"&MATCH("NA064",'CH4. Thông điệp nhắc việc'!$A:$A,0),"CH4: NA064") -> CH4: NA064 | I48: =HYPERLINK("#'DL09. Học viên'!AD4","Mở ô") -> Mở ô
A49: next_action | B49: Thiếu bài vượt ngưỡng | C49: Đếm số bài missing (không nộp) của HV này bên DL13 ≥ thresholdAtRisk_hw_missing | D49: NA065 | E49: {=IFERROR(INDEX('CH4. Thông điệp nhắc việc'!$G:$G,MATCH($D49,'CH4. Thông điệp nhắc việc'!$A:$A,0)),"")} -> HV thiếu bài tập từ 3 lần trở lên (cấu hình thresholdAtRisk_hw_missing). Việc cần làm: đánh dấu nguy cơ học thuật, can thiệp ngay. | F49: {=IFERROR(INDEX('CH4. Thông điệp nhắc việc'!$E:$E,MATCH($D49,'CH4. Thông điệp nhắc việc'!$A:$A,0)),"-")} -> Học vụ | G49: =HYPERLINK("#'CH2. Tham số & Quy tắc'!B"&MATCH("thresholdAtRisk_hw_missing",'CH2. Tham số & Quy tắc'!$A:$A,0),"CH2: thresholdAtRisk_hw_missing") -> CH2: thresholdAtRisk_hw_missing | H49: =HYPERLINK("#'CH4. Thông điệp nhắc việc'!C"&MATCH("NA065",'CH4. Thông điệp nhắc việc'!$A:$A,0),"CH4: NA065") -> CH4: NA065 | I49: =HYPERLINK("#'DL09. Học viên'!AD4","Mở ô") -> Mở ô
A50: next_action | B50: Nguy hiểm (yếu cả 2) | C50: attendance_progress_status (tiến độ chuyên cần) = off_track VÀ academic_progress_status (tiến độ học thuật) = off_track | D50: NA014 | E50: {=IFERROR(INDEX('CH4. Thông điệp nhắc việc'!$G:$G,MATCH($D50,'CH4. Thông điệp nhắc việc'!$A:$A,0)),"")} -> HV vừa yếu chuyên cần vừa yếu học thuật (mức nguy hiểm). Việc cần làm: họp 4 bên gấp và đặt buổi WOW kèm học thuật. | F50: {=IFERROR(INDEX('CH4. Thông điệp nhắc việc'!$E:$E,MATCH($D50,'CH4. Thông điệp nhắc việc'!$A:$A,0)),"-")} -> Học vụ + Quản lý | G50: - | H50: =HYPERLINK("#'CH4. Thông điệp nhắc việc'!C"&MATCH("NA014",'CH4. Thông điệp nhắc việc'!$A:$A,0),"CH4: NA014") -> CH4: NA014 | I50: =HYPERLINK("#'DL09. Học viên'!AD4","Mở ô") -> Mở ô
A51: next_action | B51: Học thuật rớt lộ trình | C51: academic_progress_status = off_track | D51: NA015 | E51: {=IFERROR(INDEX('CH4. Thông điệp nhắc việc'!$G:$G,MATCH($D51,'CH4. Thông điệp nhắc việc'!$A:$A,0)),"")} -> Tiến độ học thuật của HV rớt khỏi lộ trình. Việc cần làm: họp 3 bên gấp (trong 24 giờ) và đặt buổi WOW. | F51: {=IFERROR(INDEX('CH4. Thông điệp nhắc việc'!$E:$E,MATCH($D51,'CH4. Thông điệp nhắc việc'!$A:$A,0)),"-")} -> Học vụ | G51: - | H51: =HYPERLINK("#'CH4. Thông điệp nhắc việc'!C"&MATCH("NA015",'CH4. Thông điệp nhắc việc'!$A:$A,0),"CH4: NA015") -> CH4: NA015 | I51: =HYPERLINK("#'DL09. Học viên'!AD4","Mở ô") -> Mở ô
A52: next_action | B52: Chuyên cần rớt lộ trình | C52: attendance_progress_status = off_track | D52: NA016 | E52: {=IFERROR(INDEX('CH4. Thông điệp nhắc việc'!$G:$G,MATCH($D52,'CH4. Thông điệp nhắc việc'!$A:$A,0)),"")} -> Chuyên cần của HV sa sút nặng. Việc cần làm: họp 3 bên gấp (trong 24 giờ). | F52: {=IFERROR(INDEX('CH4. Thông điệp nhắc việc'!$E:$E,MATCH($D52,'CH4. Thông điệp nhắc việc'!$A:$A,0)),"-")} -> Học vụ | G52: - | H52: =HYPERLINK("#'CH4. Thông điệp nhắc việc'!C"&MATCH("NA016",'CH4. Thông điệp nhắc việc'!$A:$A,0),"CH4: NA016") -> CH4: NA016 | I52: =HYPERLINK("#'DL09. Học viên'!AD4","Mở ô") -> Mở ô
A53: next_action | B53: Học thuật có nguy cơ | C53: academic_progress_status = at_risk | D53: NA066 | E53: {=IFERROR(INDEX('CH4. Thông điệp nhắc việc'!$G:$G,MATCH($D53,'CH4. Thông điệp nhắc việc'!$A:$A,0)),"")} -> Học thuật của HV có dấu hiệu rủi ro (at-risk). Việc cần làm: học vụ đặt buổi WOW kèm học thuật (academic_support, theo SOP P7). | F53: {=IFERROR(INDEX('CH4. Thông điệp nhắc việc'!$E:$E,MATCH($D53,'CH4. Thông điệp nhắc việc'!$A:$A,0)),"-")} -> Học vụ | G53: - | H53: =HYPERLINK("#'CH4. Thông điệp nhắc việc'!C"&MATCH("NA066",'CH4. Thông điệp nhắc việc'!$A:$A,0),"CH4: NA066") -> CH4: NA066 | I53: =HYPERLINK("#'DL09. Học viên'!AD4","Mở ô") -> Mở ô
A54: next_action | B54: Chuyên cần có nguy cơ | C54: attendance_progress_status = at_risk | D54: NA017 | E54: {=IFERROR(INDEX('CH4. Thông điệp nhắc việc'!$G:$G,MATCH($D54,'CH4. Thông điệp nhắc việc'!$A:$A,0)),"")} -> Chuyên cần có dấu hiệu rủi ro. Việc cần làm: can thiệp, liên hệ HV trong 24-48 giờ. | F54: {=IFERROR(INDEX('CH4. Thông điệp nhắc việc'!$E:$E,MATCH($D54,'CH4. Thông điệp nhắc việc'!$A:$A,0)),"-")} -> Học vụ | G54: - | H54: =HYPERLINK("#'CH4. Thông điệp nhắc việc'!C"&MATCH("NA017",'CH4. Thông điệp nhắc việc'!$A:$A,0),"CH4: NA017") -> CH4: NA017 | I54: =HYPERLINK("#'DL09. Học viên'!AD4","Mở ô") -> Mở ô
A55: next_action | B55: Không hoạt động quá lâu | C55: kể từ last_learning_activity_time (lần hoạt động cuối) đã quá slaActivity_inactive_days | D55: NA067 | E55: {=IFERROR(INDEX('CH4. Thông điệp nhắc việc'!$G:$G,MATCH($D55,'CH4. Thông điệp nhắc việc'!$A:$A,0)),"")} -> HV không có hoạt động học quá 7 ngày (cấu hình slaActivity_inactive_days). Việc cần làm: liên hệ kiểm tra tình hình HV ngay. | F55: {=IFERROR(INDEX('CH4. Thông điệp nhắc việc'!$E:$E,MATCH($D55,'CH4. Thông điệp nhắc việc'!$A:$A,0)),"-")} -> Học vụ | G55: =HYPERLINK("#'CH2. Tham số & Quy tắc'!B"&MATCH("slaActivity_inactive_days",'CH2. Tham số & Quy tắc'!$A:$A,0),"CH2: slaActivity_inactive_days") -> CH2: slaActivity_inactive_days | H55: =HYPERLINK("#'CH4. Thông điệp nhắc việc'!C"&MATCH("NA067",'CH4. Thông điệp nhắc việc'!$A:$A,0),"CH4: NA067") -> CH4: NA067 | I55: =HYPERLINK("#'DL09. Học viên'!AD4","Mở ô") -> Mở ô
A56: next_action | B56: Đang học ổn định | C56: các trường hợp còn lại | D56: NA018 | E56: {=IFERROR(INDEX('CH4. Thông điệp nhắc việc'!$G:$G,MATCH($D56,'CH4. Thông điệp nhắc việc'!$A:$A,0)),"")} -> HV đang học đều và ổn định. Không cần làm gì thêm. | F56: {=IFERROR(INDEX('CH4. Thông điệp nhắc việc'!$E:$E,MATCH($D56,'CH4. Thông điệp nhắc việc'!$A:$A,0)),"-")} -> - | G56: - | H56: =HYPERLINK("#'CH4. Thông điệp nhắc việc'!C"&MATCH("NA018",'CH4. Thông điệp nhắc việc'!$A:$A,0),"CH4: NA018") -> CH4: NA018 | I56: =HYPERLINK("#'DL09. Học viên'!AD4","Mở ô") -> Mở ô
A57: DL11. Buổi học
A58: next_action | B58: Quá giờ vào lớp chưa bắt đầu | C58: session_status (trạng thái) = scheduled và kể từ class_start_scheduled (giờ bắt đầu theo lịch) đã quá slaTeacherAttendance_minutes phút mà buổi chưa mở | D58: NA068 | E58: {=IFERROR(INDEX('CH4. Thông điệp nhắc việc'!$G:$G,MATCH($D58,'CH4. Thông điệp nhắc việc'!$A:$A,0)),"")} -> Đã quá 30 phút sau giờ vào lớp (cấu hình slaTeacherAttendance_minutes) mà buổi chưa bắt đầu. Việc cần làm: kiểm tra giáo viên và điểm danh ngay. | F58: {=IFERROR(INDEX('CH4. Thông điệp nhắc việc'!$E:$E,MATCH($D58,'CH4. Thông điệp nhắc việc'!$A:$A,0)),"-")} -> Học vụ / GV | G58: =HYPERLINK("#'CH2. Tham số & Quy tắc'!B"&MATCH("slaTeacherAttendance_minutes",'CH2. Tham số & Quy tắc'!$A:$A,0),"CH2: slaTeacherAttendance_minutes") -> CH2: slaTeacherAttendance_minutes | H58: =HYPERLINK("#'CH4. Thông điệp nhắc việc'!C"&MATCH("NA068",'CH4. Thông điệp nhắc việc'!$A:$A,0),"CH4: NA068") -> CH4: NA068 | I58: =HYPERLINK("#'DL11. Buổi học'!Q4","Mở ô") -> Mở ô
A59: next_action | B59: Buổi sắp tới | C59: session_status = scheduled | D59: NA019 | E59: {=IFERROR(INDEX('CH4. Thông điệp nhắc việc'!$G:$G,MATCH($D59,'CH4. Thông điệp nhắc việc'!$A:$A,0)),"")} -> Buổi học sắp tới. Việc cần làm: chuẩn bị giáo án trước buổi. | F59: {=IFERROR(INDEX('CH4. Thông điệp nhắc việc'!$E:$E,MATCH($D59,'CH4. Thông điệp nhắc việc'!$A:$A,0)),"-")} -> Giáo viên | G59: - | H59: =HYPERLINK("#'CH4. Thông điệp nhắc việc'!C"&MATCH("NA019",'CH4. Thông điệp nhắc việc'!$A:$A,0),"CH4: NA019") -> CH4: NA019 | I59: =HYPERLINK("#'DL11. Buổi học'!Q4","Mở ô") -> Mở ô
A60: next_action | B60: Buổi đang diễn ra | C60: session_status = in_progress | D60: NA020 | E60: {=IFERROR(INDEX('CH4. Thông điệp nhắc việc'!$G:$G,MATCH($D60,'CH4. Thông điệp nhắc việc'!$A:$A,0)),"")} -> Buổi đang diễn ra. Sau buổi nhớ điểm danh và ghi nhận xét (teacher_note). | F60: {=IFERROR(INDEX('CH4. Thông điệp nhắc việc'!$E:$E,MATCH($D60,'CH4. Thông điệp nhắc việc'!$A:$A,0)),"-")} -> Giáo viên | G60: - | H60: =HYPERLINK("#'CH4. Thông điệp nhắc việc'!C"&MATCH("NA020",'CH4. Thông điệp nhắc việc'!$A:$A,0),"CH4: NA020") -> CH4: NA020 | I60: =HYPERLINK("#'DL11. Buổi học'!Q4","Mở ô") -> Mở ô
A61: next_action | B61: Quá hạn ghi nhận xét | C61: session_status = completed + has_teacher_note (có note) = FALSE, và kể từ session_date (ngày buổi) đã quá slaTeacherNote_hours | D61: NA021 | E61: {=IFERROR(INDEX('CH4. Thông điệp nhắc việc'!$G:$G,MATCH($D61,'CH4. Thông điệp nhắc việc'!$A:$A,0)),"")} -> Buổi đã xong nhưng quá 48 giờ (cấu hình slaTeacherNote_hours) chưa ghi nhận xét. Việc cần làm: ghi teacher_note ngay. | F61: {=IFERROR(INDEX('CH4. Thông điệp nhắc việc'!$E:$E,MATCH($D61,'CH4. Thông điệp nhắc việc'!$A:$A,0)),"-")} -> Giáo viên | G61: =HYPERLINK("#'CH2. Tham số & Quy tắc'!B"&MATCH("slaTeacherNote_hours",'CH2. Tham số & Quy tắc'!$A:$A,0),"CH2: slaTeacherNote_hours") -> CH2: slaTeacherNote_hours | H61: =HYPERLINK("#'CH4. Thông điệp nhắc việc'!C"&MATCH("NA021",'CH4. Thông điệp nhắc việc'!$A:$A,0),"CH4: NA021") -> CH4: NA021 | I61: =HYPERLINK("#'DL11. Buổi học'!Q4","Mở ô") -> Mở ô
A62: next_action | B62: Còn hạn ghi nhận xét | C62: session_status = completed + has_teacher_note = FALSE, còn trong hạn slaTeacherNote_hours | D62: NA069 | E62: {=IFERROR(INDEX('CH4. Thông điệp nhắc việc'!$G:$G,MATCH($D62,'CH4. Thông điệp nhắc việc'!$A:$A,0)),"")} -> Buổi đã xong, cần ghi nhận xét (teacher_note) trong hạn 48 giờ (cấu hình slaTeacherNote_hours). Việc cần làm: ghi nhận xét buổi. | F62: {=IFERROR(INDEX('CH4. Thông điệp nhắc việc'!$E:$E,MATCH($D62,'CH4. Thông điệp nhắc việc'!$A:$A,0)),"-")} -> Giáo viên | G62: =HYPERLINK("#'CH2. Tham số & Quy tắc'!B"&MATCH("slaTeacherNote_hours",'CH2. Tham số & Quy tắc'!$A:$A,0),"CH2: slaTeacherNote_hours") -> CH2: slaTeacherNote_hours | H62: =HYPERLINK("#'CH4. Thông điệp nhắc việc'!C"&MATCH("NA069",'CH4. Thông điệp nhắc việc'!$A:$A,0),"CH4: NA069") -> CH4: NA069 | I62: =HYPERLINK("#'DL11. Buổi học'!Q4","Mở ô") -> Mở ô
A63: next_action | B63: Đã ghi nhận xét | C63: session_status = completed + has_teacher_note = TRUE | D63: NA022 | E63: {=IFERROR(INDEX('CH4. Thông điệp nhắc việc'!$G:$G,MATCH($D63,'CH4. Thông điệp nhắc việc'!$A:$A,0)),"")} -> Đã hoàn tất. Không cần làm gì thêm ở bước này. | F63: {=IFERROR(INDEX('CH4. Thông điệp nhắc việc'!$E:$E,MATCH($D63,'CH4. Thông điệp nhắc việc'!$A:$A,0)),"-")} -> Giáo viên | G63: - | H63: =HYPERLINK("#'CH4. Thông điệp nhắc việc'!C"&MATCH("NA022",'CH4. Thông điệp nhắc việc'!$A:$A,0),"CH4: NA022") -> CH4: NA022 | I63: =HYPERLINK("#'DL11. Buổi học'!Q4","Mở ô") -> Mở ô
A64: next_action | B64: Buổi bị hủy | C64: session_status = cancelled | D64: NA023 | E64: {=IFERROR(INDEX('CH4. Thông điệp nhắc việc'!$G:$G,MATCH($D64,'CH4. Thông điệp nhắc việc'!$A:$A,0)),"")} -> Buổi học bị hủy. Việc cần làm: lên lịch học bù. | F64: {=IFERROR(INDEX('CH4. Thông điệp nhắc việc'!$E:$E,MATCH($D64,'CH4. Thông điệp nhắc việc'!$A:$A,0)),"-")} -> Học vụ | G64: - | H64: =HYPERLINK("#'CH4. Thông điệp nhắc việc'!C"&MATCH("NA023",'CH4. Thông điệp nhắc việc'!$A:$A,0),"CH4: NA023") -> CH4: NA023 | I64: =HYPERLINK("#'DL11. Buổi học'!Q4","Mở ô") -> Mở ô
A65: next_action | B65: Buổi đã dời | C65: session_status = rescheduled | D65: NA024 | E65: {=IFERROR(INDEX('CH4. Thông điệp nhắc việc'!$G:$G,MATCH($D65,'CH4. Thông điệp nhắc việc'!$A:$A,0)),"")} -> Buổi học đã dời. Việc cần làm: cập nhật lại lịch. | F65: {=IFERROR(INDEX('CH4. Thông điệp nhắc việc'!$E:$E,MATCH($D65,'CH4. Thông điệp nhắc việc'!$A:$A,0)),"-")} -> Học vụ | G65: - | H65: =HYPERLINK("#'CH4. Thông điệp nhắc việc'!C"&MATCH("NA024",'CH4. Thông điệp nhắc việc'!$A:$A,0),"CH4: NA024") -> CH4: NA024 | I65: =HYPERLINK("#'DL11. Buổi học'!Q4","Mở ô") -> Mở ô
A66: DL12. Điểm danh
A67: next_action | B67: Vắng không phép quá hạn gọi | C67: attendance_status = no_show + absence_type = unexcused (không phép), và kể từ giờ buổi (tra từ DL11) đã quá slaAbsenceCall_hours | D67: NA070 | E67: {=IFERROR(INDEX('CH4. Thông điệp nhắc việc'!$G:$G,MATCH($D67,'CH4. Thông điệp nhắc việc'!$A:$A,0)),"")} -> HV vắng không phép đã quá 24 giờ (cấu hình slaAbsenceCall_hours). Việc cần làm: GỌI HV/phụ huynh ngay. | F67: {=IFERROR(INDEX('CH4. Thông điệp nhắc việc'!$E:$E,MATCH($D67,'CH4. Thông điệp nhắc việc'!$A:$A,0)),"-")} -> Học vụ | G67: =HYPERLINK("#'CH2. Tham số & Quy tắc'!B"&MATCH("slaAbsenceCall_hours",'CH2. Tham số & Quy tắc'!$A:$A,0),"CH2: slaAbsenceCall_hours") -> CH2: slaAbsenceCall_hours | H67: =HYPERLINK("#'CH4. Thông điệp nhắc việc'!C"&MATCH("NA070",'CH4. Thông điệp nhắc việc'!$A:$A,0),"CH4: NA070") -> CH4: NA070 | I67: =HYPERLINK("#'DL12. Điểm danh'!J4","Mở ô") -> Mở ô
A68: next_action | B68: Vắng không phép | C68: attendance_status = no_show + absence_type = unexcused | D68: NA025 | E68: {=IFERROR(INDEX('CH4. Thông điệp nhắc việc'!$G:$G,MATCH($D68,'CH4. Thông điệp nhắc việc'!$A:$A,0)),"")} -> HV vắng không phép. Việc cần làm: kiểm tra chuỗi buổi vắng và nhắc HV. | F68: {=IFERROR(INDEX('CH4. Thông điệp nhắc việc'!$E:$E,MATCH($D68,'CH4. Thông điệp nhắc việc'!$A:$A,0)),"-")} -> Giáo viên / Học vụ | G68: - | H68: =HYPERLINK("#'CH4. Thông điệp nhắc việc'!C"&MATCH("NA025",'CH4. Thông điệp nhắc việc'!$A:$A,0),"CH4: NA025") -> CH4: NA025 | I68: =HYPERLINK("#'DL12. Điểm danh'!J4","Mở ô") -> Mở ô
A69: next_action | B69: Vắng có phép | C69: attendance_status = no_show + absence_type = excused | D69: NA026 | E69: {=IFERROR(INDEX('CH4. Thông điệp nhắc việc'!$G:$G,MATCH($D69,'CH4. Thông điệp nhắc việc'!$A:$A,0)),"")} -> HV vắng có phép. Việc cần làm: đề xuất buổi WOW để học bù. | F69: {=IFERROR(INDEX('CH4. Thông điệp nhắc việc'!$E:$E,MATCH($D69,'CH4. Thông điệp nhắc việc'!$A:$A,0)),"-")} -> Học vụ | G69: - | H69: =HYPERLINK("#'CH4. Thông điệp nhắc việc'!C"&MATCH("NA026",'CH4. Thông điệp nhắc việc'!$A:$A,0),"CH4: NA026") -> CH4: NA026 | I69: =HYPERLINK("#'DL12. Điểm danh'!J4","Mở ô") -> Mở ô
A70: next_action | B70: Đi học trễ | C70: attendance_status = late | D70: NA027 | E70: {=IFERROR(INDEX('CH4. Thông điệp nhắc việc'!$G:$G,MATCH($D70,'CH4. Thông điệp nhắc việc'!$A:$A,0)),"")} -> HV đi học trễ. Việc cần làm: nhắc nhở HV đi đúng giờ. | F70: {=IFERROR(INDEX('CH4. Thông điệp nhắc việc'!$E:$E,MATCH($D70,'CH4. Thông điệp nhắc việc'!$A:$A,0)),"-")} -> Giáo viên | G70: - | H70: =HYPERLINK("#'CH4. Thông điệp nhắc việc'!C"&MATCH("NA027",'CH4. Thông điệp nhắc việc'!$A:$A,0),"CH4: NA027") -> CH4: NA027 | I70: =HYPERLINK("#'DL12. Điểm danh'!J4","Mở ô") -> Mở ô
A71: next_action | B71: Đúng giờ | C71: attendance_status = on_time | D71: NA028 | E71: {=IFERROR(INDEX('CH4. Thông điệp nhắc việc'!$G:$G,MATCH($D71,'CH4. Thông điệp nhắc việc'!$A:$A,0)),"")} -> HV đã điểm danh, đi học đúng giờ. Không cần làm gì thêm. | F71: {=IFERROR(INDEX('CH4. Thông điệp nhắc việc'!$E:$E,MATCH($D71,'CH4. Thông điệp nhắc việc'!$A:$A,0)),"-")} -> - | G71: - | H71: =HYPERLINK("#'CH4. Thông điệp nhắc việc'!C"&MATCH("NA028",'CH4. Thông điệp nhắc việc'!$A:$A,0),"CH4: NA028") -> CH4: NA028 | I71: =HYPERLINK("#'DL12. Điểm danh'!J4","Mở ô") -> Mở ô
A72: DL13. Bài tập
A73: next_action | B73: Chưa nộp bài | C73: homework_status = missing | D73: NA029 | E73: {=IFERROR(INDEX('CH4. Thông điệp nhắc việc'!$G:$G,MATCH($D73,'CH4. Thông điệp nhắc việc'!$A:$A,0)),"")} -> HV chưa nộp bài tập. Việc cần làm: kiểm tra chuỗi bài thiếu (có thể thành nguy cơ học thuật) và nhắc HV nộp. | F73: {=IFERROR(INDEX('CH4. Thông điệp nhắc việc'!$E:$E,MATCH($D73,'CH4. Thông điệp nhắc việc'!$A:$A,0)),"-")} -> Giáo viên | G73: - | H73: =HYPERLINK("#'CH4. Thông điệp nhắc việc'!C"&MATCH("NA029",'CH4. Thông điệp nhắc việc'!$A:$A,0),"CH4: NA029") -> CH4: NA029 | I73: =HYPERLINK("#'DL13. Bài tập'!T4","Mở ô") -> Mở ô
A74: next_action | B74: Đã nộp, quá hạn chấm | C74: homework_status = submitted + homework_score (điểm) còn trống, và kể từ homework_submitted_time (giờ nộp) đã quá slaHomeworkGrading_hours | D74: NA071 | E74: {=IFERROR(INDEX('CH4. Thông điệp nhắc việc'!$G:$G,MATCH($D74,'CH4. Thông điệp nhắc việc'!$A:$A,0)),"")} -> HV đã nộp bài nhưng quá 48 giờ (cấu hình slaHomeworkGrading_hours) chưa chấm. Việc cần làm: chấm bài ngay. | F74: {=IFERROR(INDEX('CH4. Thông điệp nhắc việc'!$E:$E,MATCH($D74,'CH4. Thông điệp nhắc việc'!$A:$A,0)),"-")} -> Giáo viên | G74: =HYPERLINK("#'CH2. Tham số & Quy tắc'!B"&MATCH("slaHomeworkGrading_hours",'CH2. Tham số & Quy tắc'!$A:$A,0),"CH2: slaHomeworkGrading_hours") -> CH2: slaHomeworkGrading_hours | H74: =HYPERLINK("#'CH4. Thông điệp nhắc việc'!C"&MATCH("NA071",'CH4. Thông điệp nhắc việc'!$A:$A,0),"CH4: NA071") -> CH4: NA071 | I74: =HYPERLINK("#'DL13. Bài tập'!T4","Mở ô") -> Mở ô
A75: next_action | B75: Đã nộp, còn hạn chấm | C75: homework_status = submitted + homework_score còn trống, còn trong hạn slaHomeworkGrading_hours | D75: NA072 | E75: {=IFERROR(INDEX('CH4. Thông điệp nhắc việc'!$G:$G,MATCH($D75,'CH4. Thông điệp nhắc việc'!$A:$A,0)),"")} -> HV đã nộp bài, còn trong hạn chấm 48 giờ (cấu hình slaHomeworkGrading_hours). Việc cần làm: chấm bài sớm. | F75: {=IFERROR(INDEX('CH4. Thông điệp nhắc việc'!$E:$E,MATCH($D75,'CH4. Thông điệp nhắc việc'!$A:$A,0)),"-")} -> Giáo viên | G75: =HYPERLINK("#'CH2. Tham số & Quy tắc'!B"&MATCH("slaHomeworkGrading_hours",'CH2. Tham số & Quy tắc'!$A:$A,0),"CH2: slaHomeworkGrading_hours") -> CH2: slaHomeworkGrading_hours | H75: =HYPERLINK("#'CH4. Thông điệp nhắc việc'!C"&MATCH("NA072",'CH4. Thông điệp nhắc việc'!$A:$A,0),"CH4: NA072") -> CH4: NA072 | I75: =HYPERLINK("#'DL13. Bài tập'!T4","Mở ô") -> Mở ô
A76: next_action | B76: Đã giao, chưa tới hạn nộp | C76: homework_status = assigned | D76: NA073 | E76: {=IFERROR(INDEX('CH4. Thông điệp nhắc việc'!$G:$G,MATCH($D76,'CH4. Thông điệp nhắc việc'!$A:$A,0)),"")} -> Đã giao bài, HV chưa tới hạn nộp. Chờ HV nộp bài. | F76: {=IFERROR(INDEX('CH4. Thông điệp nhắc việc'!$E:$E,MATCH($D76,'CH4. Thông điệp nhắc việc'!$A:$A,0)),"-")} -> - | G76: - | H76: =HYPERLINK("#'CH4. Thông điệp nhắc việc'!C"&MATCH("NA073",'CH4. Thông điệp nhắc việc'!$A:$A,0),"CH4: NA073") -> CH4: NA073 | I76: =HYPERLINK("#'DL13. Bài tập'!T4","Mở ô") -> Mở ô
A77: next_action | B77: Đã chấm xong | C77: homework_score (điểm) đã có | D77: NA030 | E77: {=IFERROR(INDEX('CH4. Thông điệp nhắc việc'!$G:$G,MATCH($D77,'CH4. Thông điệp nhắc việc'!$A:$A,0)),"")} -> Đã chấm bài xong cho HV. Không cần làm gì thêm. | F77: {=IFERROR(INDEX('CH4. Thông điệp nhắc việc'!$E:$E,MATCH($D77,'CH4. Thông điệp nhắc việc'!$A:$A,0)),"-")} -> Giáo viên | G77: - | H77: =HYPERLINK("#'CH4. Thông điệp nhắc việc'!C"&MATCH("NA030",'CH4. Thông điệp nhắc việc'!$A:$A,0),"CH4: NA030") -> CH4: NA030 | I77: =HYPERLINK("#'DL13. Bài tập'!T4","Mở ô") -> Mở ô
A78: DL14. Buổi WOW 1-1
A79: next_action | B79: Quá hạn trừ quota | C79: wow_status = completed + quota_deducted (trừ quota) ≠ TRUE, và kể từ wow_session_date (ngày học) đã quá slaWowQuotaCheck_hours | D79: NA074 | E79: {=IFERROR(INDEX('CH4. Thông điệp nhắc việc'!$G:$G,MATCH($D79,'CH4. Thông điệp nhắc việc'!$A:$A,0)),"")} -> Buổi WOW đã xong nhưng quá 24 giờ (cấu hình slaWowQuotaCheck_hours) chưa trừ lượt. Việc cần làm: kiểm tra và trừ quota (quota_deducted) ngay. | F79: {=IFERROR(INDEX('CH4. Thông điệp nhắc việc'!$E:$E,MATCH($D79,'CH4. Thông điệp nhắc việc'!$A:$A,0)),"-")} -> NV WOW / Học vụ | G79: =HYPERLINK("#'CH2. Tham số & Quy tắc'!B"&MATCH("slaWowQuotaCheck_hours",'CH2. Tham số & Quy tắc'!$A:$A,0),"CH2: slaWowQuotaCheck_hours") -> CH2: slaWowQuotaCheck_hours | H79: =HYPERLINK("#'CH4. Thông điệp nhắc việc'!C"&MATCH("NA074",'CH4. Thông điệp nhắc việc'!$A:$A,0),"CH4: NA074") -> CH4: NA074 | I79: =HYPERLINK("#'DL14. Buổi WOW 1-1'!S4","Mở ô") -> Mở ô
A80: next_action | B80: Vừa được đặt | C80: wow_status = booked | D80: NA031 | E80: {=IFERROR(INDEX('CH4. Thông điệp nhắc việc'!$G:$G,MATCH($D80,'CH4. Thông điệp nhắc việc'!$A:$A,0)),"")} -> Buổi WOW vừa được đặt. Việc cần làm: học vụ xác nhận lịch với HV sớm. | F80: {=IFERROR(INDEX('CH4. Thông điệp nhắc việc'!$E:$E,MATCH($D80,'CH4. Thông điệp nhắc việc'!$A:$A,0)),"-")} -> Học vụ | G80: - | H80: =HYPERLINK("#'CH4. Thông điệp nhắc việc'!C"&MATCH("NA031",'CH4. Thông điệp nhắc việc'!$A:$A,0),"CH4: NA031") -> CH4: NA031 | I80: =HYPERLINK("#'DL14. Buổi WOW 1-1'!S4","Mở ô") -> Mở ô
A81: next_action | B81: Đã xác nhận, qua giờ hẹn | C81: wow_status = confirmed + wow_session_date đã qua hiện tại | D81: NA032 | E81: {=IFERROR(INDEX('CH4. Thông điệp nhắc việc'!$G:$G,MATCH($D81,'CH4. Thông điệp nhắc việc'!$A:$A,0)),"")} -> Đã qua giờ hẹn buổi WOW. Việc cần làm: cập nhật trạng thái buổi (đã diễn ra hoặc HV vắng). | F81: {=IFERROR(INDEX('CH4. Thông điệp nhắc việc'!$E:$E,MATCH($D81,'CH4. Thông điệp nhắc việc'!$A:$A,0)),"-")} -> NV WOW | G81: - | H81: =HYPERLINK("#'CH4. Thông điệp nhắc việc'!C"&MATCH("NA032",'CH4. Thông điệp nhắc việc'!$A:$A,0),"CH4: NA032") -> CH4: NA032 | I81: =HYPERLINK("#'DL14. Buổi WOW 1-1'!S4","Mở ô") -> Mở ô
A82: next_action | B82: Đã xác nhận, sắp tới | C82: wow_status = confirmed + wow_session_date chưa tới | D82: NA033 | E82: {=IFERROR(INDEX('CH4. Thông điệp nhắc việc'!$G:$G,MATCH($D82,'CH4. Thông điệp nhắc việc'!$A:$A,0)),"")} -> Buổi WOW sắp tới. Việc cần làm: chuẩn bị nội dung buổi. | F82: {=IFERROR(INDEX('CH4. Thông điệp nhắc việc'!$E:$E,MATCH($D82,'CH4. Thông điệp nhắc việc'!$A:$A,0)),"-")} -> NV WOW | G82: - | H82: =HYPERLINK("#'CH4. Thông điệp nhắc việc'!C"&MATCH("NA033",'CH4. Thông điệp nhắc việc'!$A:$A,0),"CH4: NA033") -> CH4: NA033 | I82: =HYPERLINK("#'DL14. Buổi WOW 1-1'!S4","Mở ô") -> Mở ô
A83: next_action | B83: Quá hạn ghi kết quả | C83: wow_status = completed + wow_content_note (note sau buổi) trống, và kể từ wow_session_date đã quá slaWowOutcomeRead_hours | D83: NA075 | E83: {=IFERROR(INDEX('CH4. Thông điệp nhắc việc'!$G:$G,MATCH($D83,'CH4. Thông điệp nhắc việc'!$A:$A,0)),"")} -> Buổi WOW đã xong nhưng quá 24 giờ (cấu hình slaWowOutcomeRead_hours) chưa ghi kết quả. Việc cần làm: viết content_note ngay. | F83: {=IFERROR(INDEX('CH4. Thông điệp nhắc việc'!$E:$E,MATCH($D83,'CH4. Thông điệp nhắc việc'!$A:$A,0)),"-")} -> Học vụ | G83: =HYPERLINK("#'CH2. Tham số & Quy tắc'!B"&MATCH("slaWowOutcomeRead_hours",'CH2. Tham số & Quy tắc'!$A:$A,0),"CH2: slaWowOutcomeRead_hours") -> CH2: slaWowOutcomeRead_hours | H83: =HYPERLINK("#'CH4. Thông điệp nhắc việc'!C"&MATCH("NA075",'CH4. Thông điệp nhắc việc'!$A:$A,0),"CH4: NA075") -> CH4: NA075 | I83: =HYPERLINK("#'DL14. Buổi WOW 1-1'!S4","Mở ô") -> Mở ô
A84: next_action | B84: Còn hạn ghi kết quả | C84: wow_status = completed + wow_content_note trống, còn trong hạn slaWowOutcomeRead_hours | D84: NA076 | E84: {=IFERROR(INDEX('CH4. Thông điệp nhắc việc'!$G:$G,MATCH($D84,'CH4. Thông điệp nhắc việc'!$A:$A,0)),"")} -> Buổi WOW đã xong, cần ghi kết quả (content_note) trong hạn 24 giờ (cấu hình slaWowOutcomeRead_hours). Việc cần làm: viết content_note. | F84: {=IFERROR(INDEX('CH4. Thông điệp nhắc việc'!$E:$E,MATCH($D84,'CH4. Thông điệp nhắc việc'!$A:$A,0)),"-")} -> Học vụ | G84: =HYPERLINK("#'CH2. Tham số & Quy tắc'!B"&MATCH("slaWowOutcomeRead_hours",'CH2. Tham số & Quy tắc'!$A:$A,0),"CH2: slaWowOutcomeRead_hours") -> CH2: slaWowOutcomeRead_hours | H84: =HYPERLINK("#'CH4. Thông điệp nhắc việc'!C"&MATCH("NA076",'CH4. Thông điệp nhắc việc'!$A:$A,0),"CH4: NA076") -> CH4: NA076 | I84: =HYPERLINK("#'DL14. Buổi WOW 1-1'!S4","Mở ô") -> Mở ô
A85: next_action | B85: Chưa đánh giá kết quả | C85: wow_status = completed + wow_outcome (kết quả) trống | D85: NA034 | E85: {=IFERROR(INDEX('CH4. Thông điệp nhắc việc'!$G:$G,MATCH($D85,'CH4. Thông điệp nhắc việc'!$A:$A,0)),"")} -> Buổi WOW đã xong. Việc cần làm: đánh giá kết quả buổi (tiến bộ / không đổi / cần thêm). | F85: {=IFERROR(INDEX('CH4. Thông điệp nhắc việc'!$E:$E,MATCH($D85,'CH4. Thông điệp nhắc việc'!$A:$A,0)),"-")} -> NV WOW | G85: - | H85: =HYPERLINK("#'CH4. Thông điệp nhắc việc'!C"&MATCH("NA034",'CH4. Thông điệp nhắc việc'!$A:$A,0),"CH4: NA034") -> CH4: NA034 | I85: =HYPERLINK("#'DL14. Buổi WOW 1-1'!S4","Mở ô") -> Mở ô
A86: next_action | B86: Đã hoàn tất | C86: wow_status = completed + đã đủ note và kết quả | D86: NA022 | E86: {=IFERROR(INDEX('CH4. Thông điệp nhắc việc'!$G:$G,MATCH($D86,'CH4. Thông điệp nhắc việc'!$A:$A,0)),"")} -> Đã hoàn tất. Không cần làm gì thêm ở bước này. | F86: {=IFERROR(INDEX('CH4. Thông điệp nhắc việc'!$E:$E,MATCH($D86,'CH4. Thông điệp nhắc việc'!$A:$A,0)),"-")} -> Giáo viên | G86: - | H86: =HYPERLINK("#'CH4. Thông điệp nhắc việc'!C"&MATCH("NA022",'CH4. Thông điệp nhắc việc'!$A:$A,0),"CH4: NA022") -> CH4: NA022 | I86: =HYPERLINK("#'DL14. Buổi WOW 1-1'!S4","Mở ô") -> Mở ô
A87: next_action | B87: HV vắng buổi WOW | C87: wow_status = no_show | D87: NA035 | E87: {=IFERROR(INDEX('CH4. Thông điệp nhắc việc'!$G:$G,MATCH($D87,'CH4. Thông điệp nhắc việc'!$A:$A,0)),"")} -> HV vắng buổi WOW. Việc cần làm: trừ lượt WOW và ghi lý do. | F87: {=IFERROR(INDEX('CH4. Thông điệp nhắc việc'!$E:$E,MATCH($D87,'CH4. Thông điệp nhắc việc'!$A:$A,0)),"-")} -> NV WOW | G87: - | H87: =HYPERLINK("#'CH4. Thông điệp nhắc việc'!C"&MATCH("NA035",'CH4. Thông điệp nhắc việc'!$A:$A,0),"CH4: NA035") -> CH4: NA035 | I87: =HYPERLINK("#'DL14. Buổi WOW 1-1'!S4","Mở ô") -> Mở ô
A88: next_action | B88: Buổi WOW đã hủy | C88: wow_status = cancelled | D88: NA077 | E88: {=IFERROR(INDEX('CH4. Thông điệp nhắc việc'!$G:$G,MATCH($D88,'CH4. Thông điệp nhắc việc'!$A:$A,0)),"")} -> Buổi WOW đã hủy. Không cần làm gì thêm. | F88: {=IFERROR(INDEX('CH4. Thông điệp nhắc việc'!$E:$E,MATCH($D88,'CH4. Thông điệp nhắc việc'!$A:$A,0)),"-")} -> - | G88: - | H88: =HYPERLINK("#'CH4. Thông điệp nhắc việc'!C"&MATCH("NA077",'CH4. Thông điệp nhắc việc'!$A:$A,0),"CH4: NA077") -> CH4: NA077 | I88: =HYPERLINK("#'DL14. Buổi WOW 1-1'!S4","Mở ô") -> Mở ô
A89: DL15. Khảo sát
A90: next_action | B90: Đã nộp, quá hạn xử lý | C90: submitted_date (ngày trả lời) đã có + assigned_staff (NV xử lý) trống, và kể từ submitted_date đã quá slaSurveyReport_hours | D90: NA078 | E90: {=IFERROR(INDEX('CH4. Thông điệp nhắc việc'!$G:$G,MATCH($D90,'CH4. Thông điệp nhắc việc'!$A:$A,0)),"")} -> HV đã nộp khảo sát nhưng quá 48 giờ (cấu hình slaSurveyReport_hours) chưa xử lý. Việc cần làm: phân công đọc và báo cáo khảo sát ngay. | F90: {=IFERROR(INDEX('CH4. Thông điệp nhắc việc'!$E:$E,MATCH($D90,'CH4. Thông điệp nhắc việc'!$A:$A,0)),"-")} -> Học vụ | G90: =HYPERLINK("#'CH2. Tham số & Quy tắc'!B"&MATCH("slaSurveyReport_hours",'CH2. Tham số & Quy tắc'!$A:$A,0),"CH2: slaSurveyReport_hours") -> CH2: slaSurveyReport_hours | H90: =HYPERLINK("#'CH4. Thông điệp nhắc việc'!C"&MATCH("NA078",'CH4. Thông điệp nhắc việc'!$A:$A,0),"CH4: NA078") -> CH4: NA078 | I90: =HYPERLINK("#'DL15. Khảo sát'!R4","Mở ô") -> Mở ô
A91: next_action | B91: Đã gửi, HV chưa làm | C91: sent_date (đã gửi) có + submitted_date (trả lời) trống | D91: NA036 | E91: {=IFERROR(INDEX('CH4. Thông điệp nhắc việc'!$G:$G,MATCH($D91,'CH4. Thông điệp nhắc việc'!$A:$A,0)),"")} -> Đã gửi khảo sát nhưng HV chưa làm. Việc cần làm: nhắc HV làm khảo sát. | F91: {=IFERROR(INDEX('CH4. Thông điệp nhắc việc'!$E:$E,MATCH($D91,'CH4. Thông điệp nhắc việc'!$A:$A,0)),"-")} -> Học vụ | G91: - | H91: =HYPERLINK("#'CH4. Thông điệp nhắc việc'!C"&MATCH("NA036",'CH4. Thông điệp nhắc việc'!$A:$A,0),"CH4: NA036") -> CH4: NA036 | I91: =HYPERLINK("#'DL15. Khảo sát'!R4","Mở ô") -> Mở ô
A92: next_action | B92: Cần theo dõi thêm | C92: submitted_date có + follow_up_needed (cần follow-up) = yes | D92: NA079 | E92: {=IFERROR(INDEX('CH4. Thông điệp nhắc việc'!$G:$G,MATCH($D92,'CH4. Thông điệp nhắc việc'!$A:$A,0)),"")} -> Khảo sát cho thấy cần theo dõi thêm HV. Việc cần làm: học vụ liên hệ HV. | F92: {=IFERROR(INDEX('CH4. Thông điệp nhắc việc'!$E:$E,MATCH($D92,'CH4. Thông điệp nhắc việc'!$A:$A,0)),"-")} -> Học vụ | G92: - | H92: =HYPERLINK("#'CH4. Thông điệp nhắc việc'!C"&MATCH("NA079",'CH4. Thông điệp nhắc việc'!$A:$A,0),"CH4: NA079") -> CH4: NA079 | I92: =HYPERLINK("#'DL15. Khảo sát'!R4","Mở ô") -> Mở ô
A93: next_action | B93: Đã làm khảo sát | C93: submitted_date đã có | D93: NA037 | E93: {=IFERROR(INDEX('CH4. Thông điệp nhắc việc'!$G:$G,MATCH($D93,'CH4. Thông điệp nhắc việc'!$A:$A,0)),"")} -> HV đã làm khảo sát. Không cần làm gì thêm. | F93: {=IFERROR(INDEX('CH4. Thông điệp nhắc việc'!$E:$E,MATCH($D93,'CH4. Thông điệp nhắc việc'!$A:$A,0)),"-")} -> - | G93: - | H93: =HYPERLINK("#'CH4. Thông điệp nhắc việc'!C"&MATCH("NA037",'CH4. Thông điệp nhắc việc'!$A:$A,0),"CH4: NA037") -> CH4: NA037 | I93: =HYPERLINK("#'DL15. Khảo sát'!R4","Mở ô") -> Mở ô
A94: DL16. Phản hồi
A95: next_action | B95: Phản hồi mới quá hạn phân loại | C95: feedback_status (trạng thái xử lý) = new và kể từ feedback_time (thời gian nhận) đã quá slaFB_classify_hours | D95: NA091 | E95: {=IFERROR(INDEX('CH4. Thông điệp nhắc việc'!$G:$G,MATCH($D95,'CH4. Thông điệp nhắc việc'!$A:$A,0)),"")} -> Phản hồi mới đã quá 24 giờ (cấu hình slaFB_classify_hours) chưa phân loại. Việc cần làm: phân loại ngay. | F95: {=IFERROR(INDEX('CH4. Thông điệp nhắc việc'!$E:$E,MATCH($D95,'CH4. Thông điệp nhắc việc'!$A:$A,0)),"-")} -> Học vụ | G95: =HYPERLINK("#'CH2. Tham số & Quy tắc'!B"&MATCH("slaFB_classify_hours",'CH2. Tham số & Quy tắc'!$A:$A,0),"CH2: slaFB_classify_hours") -> CH2: slaFB_classify_hours | H95: =HYPERLINK("#'CH4. Thông điệp nhắc việc'!C"&MATCH("NA091",'CH4. Thông điệp nhắc việc'!$A:$A,0),"CH4: NA091") -> CH4: NA091 | I95: =HYPERLINK("#'DL16. Phản hồi'!R4","Mở ô") -> Mở ô
A96: next_action | B96: Phản hồi mới còn trong hạn | C96: feedback_status = new, còn trong hạn phân loại slaFB_classify_hours | D96: NA092 | E96: {=IFERROR(INDEX('CH4. Thông điệp nhắc việc'!$G:$G,MATCH($D96,'CH4. Thông điệp nhắc việc'!$A:$A,0)),"")} -> Phản hồi mới, còn trong hạn phân loại 24 giờ (cấu hình slaFB_classify_hours). Việc cần làm: phân loại sớm. | F96: {=IFERROR(INDEX('CH4. Thông điệp nhắc việc'!$E:$E,MATCH($D96,'CH4. Thông điệp nhắc việc'!$A:$A,0)),"-")} -> Học vụ | G96: =HYPERLINK("#'CH2. Tham số & Quy tắc'!B"&MATCH("slaFB_classify_hours",'CH2. Tham số & Quy tắc'!$A:$A,0),"CH2: slaFB_classify_hours") -> CH2: slaFB_classify_hours | H96: =HYPERLINK("#'CH4. Thông điệp nhắc việc'!C"&MATCH("NA092",'CH4. Thông điệp nhắc việc'!$A:$A,0),"CH4: NA092") -> CH4: NA092 | I96: =HYPERLINK("#'DL16. Phản hồi'!R4","Mở ô") -> Mở ô
A97: next_action | B97: Tiêu cực chưa xử lý xong | C97: feedback_type (loại) = negative và feedback_status chưa resolved | D97: NA093 | E97: {=IFERROR(INDEX('CH4. Thông điệp nhắc việc'!$G:$G,MATCH($D97,'CH4. Thông điệp nhắc việc'!$A:$A,0)),"")} -> Phản hồi tiêu cực chưa xử lý xong. Việc cần làm: xử lý ngay và cân nhắc tạo khiếu nại (sheet DL17). | F97: {=IFERROR(INDEX('CH4. Thông điệp nhắc việc'!$E:$E,MATCH($D97,'CH4. Thông điệp nhắc việc'!$A:$A,0)),"-")} -> Học vụ | G97: - | H97: =HYPERLINK("#'CH4. Thông điệp nhắc việc'!C"&MATCH("NA093",'CH4. Thông điệp nhắc việc'!$A:$A,0),"CH4: NA093") -> CH4: NA093 | I97: =HYPERLINK("#'DL16. Phản hồi'!R4","Mở ô") -> Mở ô
A98: next_action | B98: Đã xử lý xong phản hồi | C98: feedback_status = resolved | D98: NA094 | E98: {=IFERROR(INDEX('CH4. Thông điệp nhắc việc'!$G:$G,MATCH($D98,'CH4. Thông điệp nhắc việc'!$A:$A,0)),"")} -> Đã xử lý xong phản hồi. Không cần làm gì thêm. | F98: {=IFERROR(INDEX('CH4. Thông điệp nhắc việc'!$E:$E,MATCH($D98,'CH4. Thông điệp nhắc việc'!$A:$A,0)),"-")} -> - | G98: - | H98: =HYPERLINK("#'CH4. Thông điệp nhắc việc'!C"&MATCH("NA094",'CH4. Thông điệp nhắc việc'!$A:$A,0),"CH4: NA094") -> CH4: NA094 | I98: =HYPERLINK("#'DL16. Phản hồi'!R4","Mở ô") -> Mở ô
A99: DL17. Khiếu nại
A100: next_action | B100: Ưu tiên thấp quá hạn | C100: complaint_severity (mức độ) = low + resolution_time (thời gian xử lý xong) trống, và kể từ complaint_time (thời gian tiếp nhận) đã quá slaKN_low_hours | D100: NA080 | E100: {=IFERROR(INDEX('CH4. Thông điệp nhắc việc'!$G:$G,MATCH($D100,'CH4. Thông điệp nhắc việc'!$A:$A,0)),"")} -> Khiếu nại ưu tiên thấp đã quá 7 ngày (cấu hình slaKN_low_hours) chưa xử lý. Việc cần làm: phản hồi và xử lý cho HV ngay. | F100: {=IFERROR(INDEX('CH4. Thông điệp nhắc việc'!$E:$E,MATCH($D100,'CH4. Thông điệp nhắc việc'!$A:$A,0)),"-")} -> Học vụ | G100: =HYPERLINK("#'CH2. Tham số & Quy tắc'!B"&MATCH("slaKN_low_hours",'CH2. Tham số & Quy tắc'!$A:$A,0),"CH2: slaKN_low_hours") -> CH2: slaKN_low_hours | H100: =HYPERLINK("#'CH4. Thông điệp nhắc việc'!C"&MATCH("NA080",'CH4. Thông điệp nhắc việc'!$A:$A,0),"CH4: NA080") -> CH4: NA080 | I100: =HYPERLINK("#'DL17. Khiếu nại'!T4","Mở ô") -> Mở ô
A101: next_action | B101: Mới, quá hạn phân công | C101: complaint_status (trạng thái xử lý) = new và kể từ complaint_time đã quá slaKN_assignment_hours | D101: NA081 | E101: {=IFERROR(INDEX('CH4. Thông điệp nhắc việc'!$G:$G,MATCH($D101,'CH4. Thông điệp nhắc việc'!$A:$A,0)),"")} -> Khiếu nại mới đã quá 2 giờ (cấu hình slaKN_assignment_hours) chưa phân công người xử lý. Việc cần làm: phân công gấp. | F101: {=IFERROR(INDEX('CH4. Thông điệp nhắc việc'!$E:$E,MATCH($D101,'CH4. Thông điệp nhắc việc'!$A:$A,0)),"-")} -> Học vụ | G101: =HYPERLINK("#'CH2. Tham số & Quy tắc'!B"&MATCH("slaKN_assignment_hours",'CH2. Tham số & Quy tắc'!$A:$A,0),"CH2: slaKN_assignment_hours") -> CH2: slaKN_assignment_hours | H101: =HYPERLINK("#'CH4. Thông điệp nhắc việc'!C"&MATCH("NA081",'CH4. Thông điệp nhắc việc'!$A:$A,0),"CH4: NA081") -> CH4: NA081 | I101: =HYPERLINK("#'DL17. Khiếu nại'!T4","Mở ô") -> Mở ô
...

Sheet CH1. Danh mục lựa chọn
A1: DANH MỤC LỰA CHỌN (ENUM)
A2: Đây là kho giá trị cho các ô dropdown (chọn từ danh sách) trong toàn file. Mỗi KHỐI là một danh mục (vd: nguồn lead, trạng thái lớp). Cột trái là MÃ kỹ thuật (tiếng Anh, dùng trong công thức), cột phải là giá trị hiển thị kèm nghĩa tiếng Việt. Muốn thêm/bớt lựa chọn cho một dropdown, sửa trong khối tương ứng ở đây - dropdown ở các sheet data sẽ tự cập nhật theo.
A3: Mã (kỹ thuật) | B3: Giá trị hiển thị (dropdown)
A4: lead_source - Nguồn lead
A5: Giá trị | B5: Combined (cho dropdown)
A6: facebook_ads | B6: facebook_ads (Quảng cáo Facebook)
A7: tiktok_ads | B7: tiktok_ads (Quảng cáo TikTok)
A8: website | B8: website (Form website ITTs)
A9: landing_page | B9: landing_page (Landing page chiến dịch)
A10: zalo_oa | B10: zalo_oa (Zalo Official Account)
A11: hotline | B11: hotline (Gọi đến hotline)
A12: walk_in | B12: walk_in (Khách tự đến trực tiếp)
A13: referral | B13: referral (Giới thiệu)
A14: seeding | B14: seeding (Bài seeding nội dung)
A15: upsell | B15: upsell (Học viên cũ mua thêm)
A16: other | B16: other (Khác)
A18: lead_qualification_status - Mức đủ điều kiện
A19: Giá trị | B19: Combined (cho dropdown)
A20: qualified | B20: qualified (Đủ điều kiện)
A21: unknown | B21: unknown (Chưa rõ)
A22: unqualified | B22: unqualified (Không phù hợp)
A24: lead_status - Trạng thái lead
A25: Giá trị | B25: Combined (cho dropdown)
A26: new | B26: new (Chưa liên hệ)
A27: contacted | B27: contacted (Đã liên hệ, đang khai thác)
A28: considering | B28: considering (Đang cân nhắc)
A29: no_response | B29: no_response (Không liên lạc được)
A30: unreachable | B30: unreachable (Hết cách liên lạc)
A31: rejected | B31: rejected (Từ chối)
A32: converted | B32: converted (Đã chuyển đổi - đã thành HV)
A34: contact_channel - Kênh liên hệ
A35: Giá trị | B35: Combined
A36: facebook | B36: facebook (Facebook)
A37: zalo | B37: zalo (Zalo)
A38: phone | B38: phone (Điện thoại)
A39: email | B39: email (Email)
A40: walk_in | B40: walk_in (Đến trực tiếp)
A41: other | B41: other (Khác)
A43: contact_direction - Chiều liên hệ
A44: Giá trị | B44: Combined
A45: inbound | B45: inbound (Khách liên hệ đến)
A46: outbound | B46: outbound (NV gọi/nhắn đi)
A48: student_type - Đối tượng học
A49: Giá trị | B49: Combined (cho dropdown)
A50: school_student | B50: school_student (Học sinh)
A51: university_student | B51: university_student (Sinh viên)
A52: working_people | B52: working_people (Người đi làm)
A54: learning_goal_type - Loại mục tiêu
A55: Giá trị | B55: Combined (cho dropdown)
A56: study_abroad | B56: study_abroad (Du học)
A57: immigration | B57: immigration (Định cư)
A58: job | B58: job (Công việc)
A59: graduation | B59: graduation (Tốt nghiệp)
A60: personal | B60: personal (Cá nhân)
A62: learning_mode - Hình thức học
A63: Giá trị | B63: Combined (cho dropdown)
A64: online | B64: online (Trực tuyến)
A65: offline | B65: offline (Tại trung tâm)
A66: hybrid | B66: hybrid (Kết hợp)
A68: booking_status - TT đặt lịch test
A69: Giá trị | B69: Combined (cho dropdown)
A70: pending | B70: pending (Chưa đặt lịch)
A71: booked | B71: booked (Đã đặt lịch)
A72: rejected | B72: rejected (Khách từ chối test)
A73: cancelled | B73: cancelled (Đã đặt nhưng hủy)
A75: test_format - Hình thức test
A76: Giá trị | B76: Combined (cho dropdown)
A77: online | B77: online (Online (Zoom/LMS))
A78: offline | B78: offline (Offline tại trung tâm)
A80: test_attendance_status - KQ điểm danh test
A81: Giá trị | B81: Combined (cho dropdown)
A82: on_time | B82: on_time (Đúng giờ)
A83: late | B83: late (Đến trễ)
A84: no_show | B84: no_show (Vắng mặt)
A86: test_status - TT chấm bài test
A87: Giá trị | B87: Combined (cho dropdown)
A88: pending | B88: pending (Chưa có kết quả)
A89: graded | B89: graded (Đã chấm xong)
A91: post_test_status - TT sau test
A92: Giá trị | B92: Combined (cho dropdown)
A93: awaiting_consultation | B93: awaiting_consultation (Có KQ, chờ tư vấn)
A94: consulted | B94: consulted (Đã tư vấn xong)
A95: no_response | B95: no_response (Khách không phản hồi)
A97: consultation_status - TT tư vấn
A98: Giá trị | B98: Combined (cho dropdown)
A99: not_consulted | B99: not_consulted (Chưa tư vấn)
A100: consulted | B100: consulted (Đã tư vấn xong)
A101: no_response | B101: no_response (Không phản hồi)
A103: conversion_status - Kết quả tư vấn
A104: Giá trị | B104: Combined (cho dropdown)
A105: undecided | B105: undecided (Chưa quyết định)
A106: interested | B106: interested (Quan tâm, chưa chốt)
A107: confirmed_with_deposit | B107: confirmed_with_deposit (Đồng ý + có cọc)
A108: dropped | B108: dropped (Từ chối đăng ký)
A110: enrollment_status - TT đăng ký
A111: Giá trị | B111: Combined (cho dropdown)
A112: pending | B112: pending (Đang chờ xác nhận)
A113: confirmed | B113: confirmed (Đã xác nhận)
A114: cancelled | B114: cancelled (Đã hủy)
A116: payment_method - Phương thức thanh toán
...

Sheet CH2. Tham số & Quy tắc
A1: THAM SỐ & QUY TẮC - CẤU HÌNH TẬP TRUNG (CONFIG-DRIVEN)
A2: Đây là nơi đặt các CON SỐ QUY TẮC của trung tâm (thời hạn xử lý/SLA, ngưỡng cảnh báo, định mức). Mỗi dòng là 1 tham số: cột "Value" là con số đang áp dụng (ô vàng = được phép sửa), cột "Mô tả" giải thích con số đó dùng làm gì. Ví dụ slaLRT_minutes=15 nghĩa là nhân viên tư vấn phải gọi lead mới trong vòng 15 phút. Khi bạn đổi con số ở đây, toàn bộ công thức/KPI/cảnh báo trong file tự tính lại theo - không cần sửa ở đâu khác.
A4: PHẦN 1 - PARAMETERS (sửa cột "Value" ô vàng để cấu hình)
A5: Param Name (named range) | B5: Value | C5: Unit | D5: Ý nghĩa (là gì) | E5: Mục đích (vì sao có) | F5: Giá trị đề xuất | G5: Ví dụ thực tế | H5: Tác động khi đổi & dùng ở đâu
A6: SLA THEO GIAI ĐOẠN (P1 - Lead ... P10 - Kết thúc khóa)
A7: slaLRT_minutes | B7: 15 | C7: phút | D7: Thời gian phản hồi lead mới (LRT): tối đa bao lâu phải gọi/nhắn 1 lead MỚI kể từ khi lead vào hệ thống. | E7: Không để lead nguội. Gọi càng sớm tỷ lệ chốt càng cao. | F7: 15 phút trong giờ làm việc. Nới 30 phút nếu ít người trực. | G7: Lead vào 9:00, đến 9:15 chưa gọi thì ô Việc cần làm ở DL02 hiện "Quá SLA LRT - GỌI NGAY". | H7: Đặt nhỏ hơn thì nhắc gắt hơn. Dùng ở DL02 (Khách tiềm năng), cột Việc cần làm.
A8: slaLeadReassign_hours | B8: 4 | C8: giờ | D8: Hạn giao lại lead cho NV khác nếu người được giao không gọi. | E8: Lead luôn có người chăm, không bị "ôm" rồi bỏ. | F8: 4 giờ. | G8: ="Lead đã giao cho NV nhưng quá "&$B$49&"h chưa gọi thì DL02 đề xuất giao NV khác." -> Lead đã giao cho NV nhưng quá 1000000h chưa gọi thì DL02 đề xuất giao NV khác. | H8: Đặt nhỏ hơn thì giao lại nhanh hơn. Dùng ở DL02 (Khách tiềm năng), cột Việc cần làm.
A9: slaGLA_hours | B9: 24 | C9: giờ | D9: Thời hạn chấm bài test đầu vào (GLA): tối đa bao lâu phải chấm xong bài test của khách. | E9: Trả kết quả test nhanh để kịp tư vấn, tránh khách chờ lâu rồi bỏ. | F9: 24 giờ. | G9: ="Khách làm test sáng nay, quá "&$B$8&"h chưa có điểm thì DL03 nhắc chấm." -> Khách làm test sáng nay, quá 4h chưa có điểm thì DL03 nhắc chấm. | H9: Nới ra thì khách chờ lâu hơn. Dùng ở DL03 (Đặt lịch test), cột Việc cần làm.
A10: slaCVT_hours | B10: 24 | C10: giờ | D10: Thời hạn tư vấn sau khi có kết quả test (CVT): có điểm rồi thì tối đa bao lâu phải tư vấn cho khách. | E10: Chốt khách khi còn quan tâm, ngay sau khi có kết quả. | F10: 24 giờ. | G10: ="Có điểm test lúc 10:00, quá "&$B$9&"h chưa tư vấn thì hệ thống nhắc tư vấn ngay." -> Có điểm test lúc 10:00, quá 24h chưa tư vấn thì hệ thống nhắc tư vấn ngay. | H10: Nới ra thì dễ mất khách. Dùng ở DL03/DL04, cột Việc cần làm.
A11: slaFollowup_grace_days | B11: 3 | C11: ngày | D11: Hạn theo dõi lại lead đang cân nhắc: quá số ngày này chưa liên hệ lại thì nhắc. | E11: Không bỏ quên lead còn quan tâm. | F11: 3 ngày. | G11: ="Lead ""đang cân nhắc"", quá "&$B$12&" ngày chưa gọi lại thì DL02 nhắc liên hệ." -> Lead "đang cân nhắc", quá 1 ngày chưa gọi lại thì DL02 nhắc liên hệ. | H11: Nới ra thì lead dễ nguội. Dùng ở DL02/DL04, cột Việc cần làm.
A12: slaApproval_days | B12: 1 | C12: ngày | D12: Hạn để cấp trên phê duyệt một yêu cầu (giảm giá, hoàn tiền...). | E12: Yêu cầu được duyệt nhanh, không tắc nghẽn. | F12: 1 ngày. | G12: ="Yêu cầu cần duyệt quá "&$B$59&" ngày chưa xử lý thì coi là trễ (tính vào KPI duyệt)." -> Yêu cầu cần duyệt quá ngày chưa xử lý thì coi là trễ (tính vào KPI duyệt). | H12: Nới ra thì duyệt chậm hơn. Dùng cho chỉ số tỷ lệ duyệt đúng hạn ở báo cáo.
A13: slaENR_pending_hours | B13: 24 | C13: giờ | D13: Hạn xử lý đăng ký đang chờ (pending): để chờ quá lâu thì nhắc xác nhận hoặc hủy. | E13: Không để đăng ký treo, chốt rõ xác nhận hay hủy. | F13: 24 giờ. | G13: ="Đăng ký để ""chờ"" quá "&$B$13&"h thì DL06 nhắc xác nhận/hủy." -> Đăng ký để "chờ" quá 24h thì DL06 nhắc xác nhận/hủy. | H13: Nới ra thì đăng ký treo lâu. Dùng ở DL06 (Đăng ký), cột Việc cần làm.
A14: slaENR_cancel_hours | B14: 72 | C14: giờ | D14: Hạn coi như hủy đăng ký: đăng ký "chờ" quá lâu thì đề xuất hủy hẳn. | E14: Dọn các đăng ký ảo, giải phóng chỗ. | F14: 72 giờ. | G14: ="Đăng ký ""chờ"" quá "&$B$14&"h thì DL06 báo ""cân nhắc HỦY đăng ký""." -> Đăng ký "chờ" quá 72h thì DL06 báo "cân nhắc HỦY đăng ký". | H14: Nới ra thì đăng ký ảo tồn lâu. Dùng ở DL06 (Đăng ký), cột Việc cần làm.
A15: slaPayment_grace_days | B15: 14 | C15: ngày | D15: Hạn trễ đóng đợt tiền tiếp theo: quá số ngày này chưa đóng thì nhắc/cảnh báo. | E15: Thu đủ học phí đúng hạn. | F15: 14 ngày. | G15: ="Còn nợ học phí, quá "&$B$15&" ngày kể từ hạn thì DL06 báo số tiền còn thiếu." -> Còn nợ học phí, quá 14 ngày kể từ hạn thì DL06 báo số tiền còn thiếu. | H15: Nới ra thì dòng tiền chậm. Dùng ở DL06/DL07, cột Việc cần làm.
A16: slaClassInfoZalo_hours | B16: 24 | C16: giờ | D16: Hạn gửi thông tin lớp qua Zalo cho HV sau khi xếp lớp. | E16: HV nhận thông tin lớp kịp thời để đi học đúng buổi đầu. | F16: 24 giờ. | G16: ="Đã xếp lớp nhưng quá "&$B$50&"h chưa gửi thông tin Zalo thì DL08 nhắc gửi." -> Đã xếp lớp nhưng quá 5000000h chưa gửi thông tin Zalo thì DL08 nhắc gửi. | H16: Nới ra thì HV nhận tin trễ. Dùng ở DL08 (Xếp lớp), cột Việc cần làm.
A17: slaPLR48_hours | B17: 48 | C17: giờ | D17: Thời hạn xếp lớp (PLR48): đăng ký đã xác nhận thì tối đa bao lâu phải xếp được lớp cho HV. | E17: Cho HV vào học sớm, không để chờ sau khi đã đóng tiền. | F17: 48 giờ. | G17: Đăng ký xác nhận thứ Hai, quá thứ Tư chưa xếp lớp thì DL08 báo "Quá PLR48 - XẾP LỚP NGAY". | H17: Nới ra thì HV chờ lâu hơn. Dùng ở DL08 (Xếp lớp), cột Việc cần làm.
A18: slaOBT_hours | B18: 72 | C18: giờ | D18: Thời hạn nhập học (OBT): tối đa bao lâu phải hoàn tất thủ tục nhập học cho HV. | E18: Hoàn tất onboarding để HV bắt đầu học đúng hẹn. | F18: 72 giờ. | G18: ="Đã xếp lớp nhưng quá "&$B$11&"h chưa hoàn tất nhập học thì hệ thống nhắc." -> Đã xếp lớp nhưng quá 3h chưa hoàn tất nhập học thì hệ thống nhắc. | H18: Nới ra thì onboarding chậm. Dùng ở DL08 (Xếp lớp), cột Việc cần làm.
A19: slaTeacherAttendance_minutes | B19: 30 | C19: phút | D19: Hạn để GV bắt đầu lớp/điểm danh sau giờ vào học. | E19: Đảm bảo lớp bắt đầu đúng giờ, có điểm danh. | F19: 30 phút. | G19: ="Quá "&$B$51&" phút sau giờ vào lớp mà buổi vẫn ""chưa bắt đầu"" thì DL11 nhắc kiểm tra GV." -> Quá 2 phút sau giờ vào lớp mà buổi vẫn "chưa bắt đầu" thì DL11 nhắc kiểm tra GV. | H19: Đặt nhỏ hơn thì siết giờ giấc GV chặt hơn. Dùng ở DL11 (Buổi học), cột Việc cần làm.
A20: slaTeacherNote_hours | B20: 48 | C20: giờ | D20: Thời hạn giáo viên ghi nhận xét buổi học (teacher_note) sau khi buổi kết thúc. | E20: Bảo đảm có nhận xét từng buổi để theo dõi tiến bộ HV. | F20: 48 giờ. | G20: ="Buổi xong quá "&$B$60&"h chưa ghi nhận xét thì DL11 nhắc ghi ngay." -> Buổi xong quá 4h chưa ghi nhận xét thì DL11 nhắc ghi ngay. | H20: Nới ra thì nhận xét buổi bị chậm. Dùng ở DL11 (Buổi học), cột Việc cần làm.
A21: slaAbsenceCall_hours | B21: 24 | C21: giờ | D21: Hạn gọi HV/phụ huynh sau buổi HV vắng không phép. | E21: Liên hệ ngay khi HV vắng để giữ HV không bỏ học. | F21: 24 giờ. | G21: ="HV vắng không phép, quá "&$B$52&"h chưa gọi thì DL12 báo ""GỌI HV/phụ huynh NGAY""." -> HV vắng không phép, quá 14h chưa gọi thì DL12 báo "GỌI HV/phụ huynh NGAY". | H21: Nới ra thì phản ứng chậm khi HV vắng. Dùng ở DL12 (Điểm danh), cột Việc cần làm.
A22: slaHomeworkGrading_hours | B22: 48 | C22: giờ | D22: Hạn GV chấm bài tập sau khi HV nộp. | E22: Trả bài nhanh để HV biết kết quả và sửa. | F22: 48 giờ. | G22: ="HV nộp bài, quá "&$B$53&"h chưa chấm thì DL13 báo ""Quá SLA chấm bài - CHẤM NGAY""." -> HV nộp bài, quá 30h chưa chấm thì DL13 báo "Quá SLA chấm bài - CHẤM NGAY". | H22: Đặt nhỏ hơn thì siết tốc độ chấm. Dùng ở DL13 (Bài tập), cột Việc cần làm.
A23: slaWowQuotaCheck_hours | B23: 24 | C23: giờ | D23: Hạn kiểm tra và trừ quota buổi WOW sau khi buổi kết thúc. | E23: Đảm bảo số buổi WOW được tính đúng, không lệch quota. | F23: 24 giờ. | G23: ="Buổi WOW xong quá "&$B$54&"h chưa trừ quota thì DL14 nhắc kiểm tra quota." -> Buổi WOW xong quá 90h chưa trừ quota thì DL14 nhắc kiểm tra quota. | H23: Nới ra thì quota dễ sai. Dùng ở DL14 (Buổi WOW 1-1), cột Việc cần làm.
A24: slaWowOutcomeRead_hours | B24: 24 | C24: giờ | D24: Hạn Học vụ đọc và ghi kết quả (content_note) buổi WOW. | E24: Nắm kết quả buổi kèm để theo dõi tiến bộ HV. | F24: 24 giờ. | G24: ="Buổi WOW xong quá "&$B$55&"h chưa ghi kết quả thì DL14 báo viết content_note ngay." -> Buổi WOW xong quá h chưa ghi kết quả thì DL14 báo viết content_note ngay. | H24: Nới ra thì theo dõi tiến bộ trễ. Dùng ở DL14 (Buổi WOW 1-1), cột Việc cần làm.
A25: slaSurveyReport_hours | B25: 48 | C25: giờ | D25: Hạn xử lý và báo cáo khảo sát sau khi HV nộp. | E25: Đọc phản hồi khảo sát kịp thời để cải thiện. | F25: 48 giờ. | G25: ="HV nộp khảo sát, quá "&$B$56&"h chưa xử lý thì DL15 nhắc phân công đọc và báo cáo." -> HV nộp khảo sát, quá 7h chưa xử lý thì DL15 nhắc phân công đọc và báo cáo. | H25: Nới ra thì phản hồi bị chậm xử lý. Dùng ở DL15 (Khảo sát), cột Việc cần làm.
A26: slaFB_classify_hours | B26: 24 | C26: giờ | D26: Hạn phân loại phản hồi mới (tích cực/tiêu cực/góp ý). | E26: Đọc và phân loại phản hồi kịp thời để hành động. | F26: 24 giờ. | G26: ="Phản hồi mới quá "&$B$21&"h chưa phân loại thì DL16 nhắc phân loại." -> Phản hồi mới quá 24h chưa phân loại thì DL16 nhắc phân loại. | H26: Nới ra thì phản hồi bị bỏ. Dùng ở DL16 (Phản hồi), quy trình xử lý.
A27: slaKN_assignment_hours | B27: 2 | C27: giờ | D27: Hạn phân công người xử lý cho khiếu nại MỚI. | E27: Khiếu nại có người phụ trách ngay, không bị bỏ. | F27: 2 giờ. | G27: ="Khiếu nại mới quá "&$B$17&"h chưa phân công thì DL17 báo ""Quá SLA phân công - GẤP""." -> Khiếu nại mới quá 48h chưa phân công thì DL17 báo "Quá SLA phân công - GẤP". | H27: Nới ra thì khiếu nại bị treo. Dùng ở DL17 (Khiếu nại), cột Việc cần làm.
A28: slaKN_high_hours | B28: 4 | C28: giờ | D28: Hạn xử lý khiếu nại mức độ cao. | E28: Việc nghiêm trọng được giải quyết nhanh. | F28: 4 giờ. | G28: ="Khiếu nại mức cao quá "&$B$18&"h chưa xử lý thì DL17 nhắc xử lý." -> Khiếu nại mức cao quá 72h chưa xử lý thì DL17 nhắc xử lý. | H28: Nới ra thì việc gấp bị chậm. Dùng ở DL17 (Khiếu nại), cột Việc cần làm.
A29: slaKN_medium_hours | B29: 48 | C29: giờ | D29: Hạn xử lý khiếu nại mức độ trung bình. | E29: Cân đối nguồn lực cho việc mức trung bình. | F29: 48 giờ. | G29: ="Khiếu nại mức trung bình quá "&$B$19&"h chưa xử lý thì DL17 nhắc." -> Khiếu nại mức trung bình quá 30h chưa xử lý thì DL17 nhắc. | H29: Nới ra thì tồn đọng nhiều. Dùng ở DL17 (Khiếu nại), cột Việc cần làm.
A30: slaKN_low_hours | B30: 168 | C30: giờ | D30: Hạn xử lý khiếu nại mức độ thấp. | E30: Việc nhỏ vẫn phải được phản hồi, không bỏ quên. | F30: 168 giờ (7 ngày). | G30: Khiếu nại mức thấp quá 7 ngày chưa xử lý thì DL17 báo cần phản hồi. | H30: Nới ra thì việc nhỏ tồn lâu. Dùng ở DL17 (Khiếu nại), cột Việc cần làm.
A31: slaActivity_inactive_days | B31: 7 | C31: ngày | D31: Số ngày HV không có hoạt động học thì coi là có nguy cơ. | E31: Phát hiện sớm HV bỏ học để can thiệp. | F31: 7 ngày. | G31: ="HV không có hoạt động học quá "&$B$16&" ngày thì DL09 báo ""Không activity quá SLA""." -> HV không có hoạt động học quá 24 ngày thì DL09 báo "Không activity quá SLA". | H31: Nới ra thì phát hiện trễ. Dùng ở DL09 (Học viên), cột Việc cần làm.
A32: slaFinalTest_days | B32: 3 | C32: ngày | D32: Hạn nhập điểm test cuối khóa sau khi HV hoàn thành. | E32: Có điểm cuối để đánh giá kết quả và tư vấn khóa tiếp. | F32: 3 ngày. | G32: ="HV hoàn thành khóa, quá "&$B$57&" ngày chưa có điểm test cuối thì DL18 nhắc nhập điểm." -> HV hoàn thành khóa, quá 14 ngày chưa có điểm test cuối thì DL18 nhắc nhập điểm. | H32: Nới ra thì đánh giá kết quả trễ. Dùng ở DL18 (Kết thúc khóa), cột Việc cần làm.
A33: slaReenroll_contact_days | B33: 3 | C33: ngày | D33: Hạn liên hệ tái ghi danh sau khi HV hoàn thành khóa. | E33: Giữ chân HV, mời học khóa tiếp theo đúng thời điểm. | F33: 3 ngày. | G33: ="HV hoàn thành khóa, quá "&$B$22&" ngày chưa liên hệ thì DL18 nhắc liên hệ tái ghi danh." -> HV hoàn thành khóa, quá 48 ngày chưa liên hệ thì DL18 nhắc liên hệ tái ghi danh. | H33: Nới ra thì bỏ lỡ cơ hội tái ghi danh. Dùng ở DL18 (Kết thúc khóa), cột Việc cần làm.
A34: slaReenrollSchedule_days | B34: 14 | C34: ngày | D34: Hạn chốt lịch khóa mới cho HV đã quan tâm tái ghi danh. | E34: Chuyển HV quan tâm thành đăng ký khóa mới kịp thời. | F34: 14 ngày. | G34: ="HV quan tâm tái ghi danh, quá "&$B$58&" ngày chưa xếp khóa thì DL18 nhắc chốt lịch." -> HV quan tâm tái ghi danh, quá 30 ngày chưa xếp khóa thì DL18 nhắc chốt lịch. | H34: Nới ra thì dễ mất HV quay lại. Dùng ở DL18 (Kết thúc khóa), cột Việc cần làm.
A35: slaQuote_days | B35: 1 | C35: ngày | D35: Hạn gửi báo giá sau buổi tư vấn. | E35: Khách còn nóng thì chốt nhanh, để lâu nguội. | F35: 1 ngày. | G35: Tư vấn hôm nay thì mai phải có báo giá. | H35: Hiển thị ở HD2 P3.
A36: slaPaymentConfirm_days | B36: 1 | C36: ngày | D36: Hạn gửi xác nhận/phiếu thu sau khi thu đủ tiền. | E36: Khách yên tâm đã đóng thành công. | F36: 1 ngày. | G36: Thu đủ hôm nay, mai gửi xác nhận. | H36: Hiển thị ở HD2 P4.
A37: slaRefundProcess_days | B37: 5 | C37: ngày | D37: Hạn hoàn tất chuyển tiền hoàn sau khi duyệt. | E37: Giữ uy tín khi HV rời đi. | F37: 5 ngày. | G37: Duyệt hoàn thứ 2 thì thứ 6 tiền phải về. | H37: Hiển thị ở HD2 P4.
A38: slaNoteReview_hours | B38: 24 | C38: giờ | D38: Hạn học vụ duyệt nhận xét buổi học của GV. | E38: Phát hiện sớm vấn đề trong note. | F38: 24 giờ. | G38: GV nộp note tối nay, trưa mai học vụ phải duyệt. | H38: Hiển thị ở HD2 P6.
A39: slaRiskFlagUpdate_hours | B39: 48 | C39: giờ | D39: Hạn cập nhật cờ nguy cơ sau chuỗi tín hiệu yếu. | E39: Cờ đúng lúc thì can thiệp đúng lúc. | F39: 48 giờ. | G39: HV yếu 3 buổi liền thì trong 2 ngày phải xét cờ. | H39: Hiển thị ở HD2 P6.
A40: slaWowBooking_hours | B40: 24 | C40: giờ | D40: Hạn xử lý/xác nhận một booking WOW (mọi nguồn đặt). | E40: Buổi WOW là cam kết chăm sóc - không để trôi. | F40: 24 giờ. | G40: HV tự đặt sáng nay, trong hôm sau phải chốt lịch. | H40: Hiển thị ở HD2 P7.
A41: slaSurveyCollect_days | B41: 7 | C41: ngày | D41: Hạn thu khảo sát định kỳ sau khi gửi form. | E41: Thu đủ phản hồi khi trải nghiệm còn mới. | F41: 7 ngày. | G41: Gửi form tuần 4 thì trong 7 ngày phải chốt số. | H41: Hiển thị ở HD2 P8.
A42: slaTestimonialAsk_days | B42: 7 | C42: ngày | D42: Hạn xin review/testimonial khi HV đang hài lòng. | E42: Xin lúc cảm xúc tốt nhất. | F42: 7 ngày. | G42: NPS 9-10 thì trong tuần đó ngỏ lời xin review. | H42: Hiển thị ở HD2 P8-P9.
A43: slaComplaintClose_days | B43: 7 | C43: ngày | D43: Hạn đóng hồ sơ khiếu nại sau khi xử lý xong. | E43: Xác nhận HV thật sự hài lòng rồi mới đóng. | F43: 7 ngày. | G43: Xử lý xong thì trong 7 ngày gọi xác nhận + đóng case. | H43: Hiển thị ở HD2 P9.
A44: NGƯỠNG CẢNH BÁO (THRESHOLDS)
A45: thresholdContacted_attempts | B45: 5 | C45: lần | D45: Số lần liên hệ không được để chuyển lead sang "hết cách liên lạc". | E45: Dừng đeo bám lead không phản hồi, dồn sức cho lead khác. | F45: 5 lần. | G45: Đã gọi/nhắn 5 lần mà không phản hồi thì DL02 đề xuất chuyển unreachable. | H45: Đặt nhỏ hơn thì bỏ lead sớm hơn. Dùng ở DL02 (Khách tiềm năng), cột Việc cần làm.
A46: thresholdContacted_days | B46: 7 | C46: ngày | D46: Số ngày đã liên hệ mà chưa chốt thì cần đẩy mạnh tư vấn. | E46: Không để lead đã liên hệ trôi quá lâu. | F46: 7 ngày. | G46: ="Đã liên hệ nhưng quá "&$B$29&" ngày chưa chốt thì DL02 nhắc đẩy mạnh tư vấn." -> Đã liên hệ nhưng quá 48 ngày chưa chốt thì DL02 nhắc đẩy mạnh tư vấn. | H46: Đặt nhỏ hơn thì thúc chốt sớm hơn. Dùng ở DL02 (Khách tiềm năng), cột Việc cần làm.
A47: thresholdAtRisk_absences | B47: 2 | C47: buổi | D47: Số buổi vắng không phép để đánh dấu HV có nguy cơ về chuyên cần. | E47: Phát hiện HV hay vắng để can thiệp sớm. | F47: 2 buổi. | G47: HV vắng không phép 2 buổi thì DL09 báo nguy cơ chuyên cần, học vụ liên hệ. | H47: Đặt nhỏ hơn thì cảnh báo sớm hơn. Dùng ở DL09 (Học viên), cột Việc cần làm.
A48: thresholdAtRisk_hw_missing | B48: 3 | C48: lần | D48: Số lần thiếu bài tập để đánh dấu HV có nguy cơ về học thuật. | E48: Phát hiện HV lười làm bài để kèm thêm. | F48: 3 lần. | G48: HV thiếu bài tập 3 lần thì DL09 báo nguy cơ học thuật, cần can thiệp. | H48: Đặt nhỏ hơn thì cảnh báo sớm hơn. Dùng ở DL09 (Học viên), cột Việc cần làm.
A49: thresholdDiscount_approval | B49: 1000000 | C49: VND | D49: Mức giảm giá mà nếu vượt thì bắt buộc cấp trên duyệt. | E49: Kiểm soát giảm giá, tránh lạm dụng. | F49: 1.000.000đ. | G49: Giảm 1.500.000đ mà chưa có người duyệt thì DL06 báo "cần cấp trên duyệt". | H49: Đặt thấp hơn thì kiểm soát chặt hơn. Dùng ở DL06 (Đăng ký), cột Việc cần làm.
A50: thresholdDeposit_minimum | B50: 5000000 | C50: VND | D50: Mức cọc tối thiểu để đăng ký được chuyển sang "đã xác nhận". | E50: Đảm bảo HV cam kết bằng khoản cọc tối thiểu. | F50: 5.000.000đ. | G50: HV cọc đủ 5.000.000đ thì đăng ký mới chuyển xác nhận. | H50: Đặt cao hơn thì khó chốt hơn nhưng cam kết chắc hơn. Dùng ở DL06 (Đăng ký).
A51: thresholdPlacementChange_count | B51: 2 | C51: lần | D51: Số lần đổi lớp của một học viên mà từ đó quản lý cần chú ý. | E51: Đổi lớp nhiều lần là dấu hiệu xếp lớp chưa phù hợp - cần quản lý xem xét. | F51: 2 lần. | G51: HV đổi lớp lần 2 sẽ xuất hiện ở BC9 (Bảng Quản lý). | H51: Tăng lên thì ít cảnh báo hơn. Dùng ở BC9.
A52: thresholdClassStart_days | B52: 14 | C52: ngày | D52: Cửa sổ "lớp sắp khai giảng" trên bảng việc. | E52: Chuẩn bị lớp mới đủ sớm. | F52: 14 ngày. | G52: Lớp khai giảng trong 14 ngày sẽ hiện ở VH9. | H52: Dùng ở VH9, HD0.
A53: thresholdPreEnd_days | B53: 30 | C53: ngày | D53: Mốc bắt đầu quy trình kết thúc khóa trước ngày bế giảng. | E53: Chuẩn bị final test + tái ghi danh kịp lúc. | F53: 30 ngày. | G53: Lớp còn 30 ngày thì học vụ khởi động P10. | H53: Hiển thị ở HD2 P10.
A54: thresholdReenrollLost_days | B54: 90 | C54: ngày | D54: Quá số ngày này sau kết thúc mà chưa tái ghi danh thì coi như rời hệ thống. | E54: Chốt số liệu giữ chân chính xác. | F54: 90 ngày. | G54: Kết thúc 3 tháng chưa quay lại thì tính là churn. | H54: Hiển thị ở HD2 P10.
A55: CHÍNH SÁCH HOÀN TIỀN (REFUND)
A56: refundFull_days | B56: 7 | C56: ngày | D56: Hủy trong vòng số ngày này (từ khi xác nhận) thì hoàn 100% học phí. | E56: Chính sách hoàn tiền công bằng giai đoạn đầu. | F56: 7 ngày. | G56: HV hủy ở ngày thứ 5 thì DL06 hiện "hoàn 100%". | H56: Nới ra thì hoàn đủ trong thời gian dài hơn. Dùng ở DL06 (Đăng ký), cột Việc cần làm.
A57: refundPartial_days | B57: 14 | C57: ngày | D57: Hủy trong vòng số ngày này thì hoàn một phần. | E57: Mốc hoàn tiền trung gian. | F57: 14 ngày. | G57: HV hủy ở ngày thứ 10 thì DL06 hiện "hoàn một phần". | H57: Đổi thì thay mốc hoàn một phần. Dùng ở DL06 (Đăng ký), cột Việc cần làm.
A58: refundReduced_days | B58: 30 | C58: ngày | D58: Hủy trong vòng số ngày này thì hoàn mức thấp; quá thì không hoàn. | E58: Mốc hoàn tiền cuối trước khi hết quyền hoàn. | F58: 30 ngày. | G58: HV hủy ở ngày thứ 25 thì DL06 hiện "hoàn mức thấp"; ngày thứ 40 thì "quá hạn hoàn tiền". | H58: Đổi thì thay mốc hoàn cuối. Dùng ở DL06 (Đăng ký), cột Việc cần làm.
A59: WOW QUOTA
A60: wowQuota_default_sessions | B60: 4 | C60: buổi | D60: Số buổi WOW 1-1 mặc định mỗi HV được hưởng theo gói khóa. | E60: Định mức buổi kèm 1-1 chuẩn cho mỗi HV. | F60: 4 buổi (nếu khóa không ghi riêng). | G60: Khóa không khai báo số buổi WOW riêng thì HV được mặc định 4 buổi. | H60: Tăng lên thì mỗi HV được nhiều buổi kèm hơn. Dùng ở DL09 (Học viên), cột Lượt WOW mặc định.
A61: KPI THRESHOLDS (SOP standards) - quản lý & sửa tại CH6. Ngưỡng KPI
A62: kpiThreshold_VLR | B62: ='CH6. Ngưỡng KPI'!$C$5 -> 0.6 | C62: % | D62: Ngưỡng tỷ lệ lead đạt chuẩn (Valid Lead Rate). | E62: Đặt mục tiêu chất lượng lead đầu vào. | F62: 0,6 (tức 60%). | G62: ="Tỷ lệ lead đạt chuẩn dưới "&TEXT($B$31,"0%")&" thì báo cáo tô đỏ cảnh báo." -> Tỷ lệ lead đạt chuẩn dưới 700% thì báo cáo tô đỏ cảnh báo. | H62: Đặt cao hơn thì khắt khe hơn. Dùng ở các sheet Báo cáo (BC), so với số thực tế để tô cảnh báo.
A63: kpiThreshold_TAR | B63: ='CH6. Ngưỡng KPI'!$C$7 -> 0.85 | C63: % | D63: Ngưỡng tỷ lệ đi test đầy đủ (Test Attendance Rate). | E63: Mục tiêu khách đặt test thì đến làm test. | F63: 0,85 (85%). | G63: ="Dưới "&TEXT($B$32,"0%")&" khách đặt mà không đến thì cảnh báo." -> Dưới 300% khách đặt mà không đến thì cảnh báo. | H63: Đặt cao hơn thì khắt khe hơn. Dùng ở các sheet Báo cáo (BC), so với số thực tế để tô cảnh báo.
A64: kpiThreshold_CVR | B64: ='CH6. Ngưỡng KPI'!$C$13 -> 0.4 | C64: % | D64: Ngưỡng tỷ lệ chuyển đổi lead thành HV (Conversion Rate). | E64: Mục tiêu chốt lead thành học viên. | F64: 0,4 (40%). | G64: ="Tỷ lệ chốt dưới "&TEXT($B$33,"0%")&" thì cảnh báo." -> Tỷ lệ chốt dưới 300% thì cảnh báo. | H64: Đặt cao hơn thì khắt khe hơn. Dùng ở các sheet Báo cáo (BC), so với số thực tế để tô cảnh báo.
A65: kpiThreshold_PCR | B65: ='CH6. Ngưỡng KPI'!$C$16 -> 0.8 | C65: % | D65: Ngưỡng tỷ lệ thu đủ học phí (Payment Completion Rate). | E65: Mục tiêu thu đủ tiền các đăng ký. | F65: 0,8 (80%). | G65: ="Tỷ lệ thu đủ dưới "&TEXT($B$34,"0%")&" thì cảnh báo." -> Tỷ lệ thu đủ dưới 1400% thì cảnh báo. | H65: Đặt cao hơn thì khắt khe hơn. Dùng ở các sheet Báo cáo (BC), so với số thực tế để tô cảnh báo.
A66: kpiThreshold_ATR | B66: ='CH6. Ngưỡng KPI'!$C$22 -> 0.85 | C66: % | D66: Ngưỡng tỷ lệ chuyên cần (Attendance Rate). | E66: Mục tiêu HV đi học đều. | F66: 0,85 (85%). | G66: ="Chuyên cần dưới "&TEXT($B$35,"0%")&" thì cảnh báo." -> Chuyên cần dưới 100% thì cảnh báo. | H66: Đặt cao hơn thì khắt khe hơn. Dùng ở các sheet Báo cáo (BC), so với số thực tế để tô cảnh báo.
A67: kpiThreshold_UAR | B67: ='CH6. Ngưỡng KPI'!$C$23 -> 0.05 | C67: % | D67: Ngưỡng tỷ lệ vắng không phép tối đa (Unexcused Absence Rate). | E67: Giới hạn mức vắng không phép cho phép. | F67: 0,05 (5%, mức tối đa). | G67: ="Vắng không phép vượt "&TEXT($B$36,"0%")&" thì cảnh báo." -> Vắng không phép vượt 100% thì cảnh báo. | H67: Đặt cao hơn thì khắt khe hơn. Dùng ở các sheet Báo cáo (BC), so với số thực tế để tô cảnh báo.
A68: kpiThreshold_ARR | B68: ='CH6. Ngưỡng KPI'!$C$24 -> 0.1 | C68: % | D68: Ngưỡng tỷ lệ HV nguy cơ tối đa (At-Risk Rate). | E68: Giới hạn tỷ lệ HV có nguy cơ. | F68: 0,1 (10%, mức tối đa). | G68: ="HV nguy cơ vượt "&TEXT($B$37,"0%")&" thì cảnh báo." -> HV nguy cơ vượt 500% thì cảnh báo. | H68: Đặt cao hơn thì khắt khe hơn. Dùng ở các sheet Báo cáo (BC), so với số thực tế để tô cảnh báo.
A69: kpiThreshold_CIR | B69: ='CH6. Ngưỡng KPI'!$C$30 -> 0.03 | C69: % | D69: Ngưỡng tỷ lệ phát sinh khiếu nại tối đa mỗi tháng (Complaint Incidence Rate). | E69: Giới hạn số khiếu nại cho phép. | F69: 0,03 (3%, mức tối đa). | G69: ="Khiếu nại vượt "&TEXT($B$38,"0%")&" thì cảnh báo." -> Khiếu nại vượt 2400% thì cảnh báo. | H69: Đặt cao hơn thì khắt khe hơn. Dùng ở các sheet Báo cáo (BC), so với số thực tế để tô cảnh báo.
A70: kpiThreshold_RR | B70: ='CH6. Ngưỡng KPI'!$C$31 -> 0.9 | C70: % | D70: Ngưỡng tỷ lệ giải quyết khiếu nại thành công (Resolution Rate). | E70: Mục tiêu xử lý khiếu nại được HV chấp nhận. | F70: 0,9 (90%). | G70: ="Tỷ lệ giải quyết dưới "&TEXT($B$39,"0%")&" thì cảnh báo." -> Tỷ lệ giải quyết dưới 4800% thì cảnh báo. | H70: Đặt cao hơn thì khắt khe hơn. Dùng ở các sheet Báo cáo (BC), so với số thực tế để tô cảnh báo.
A71: kpiThreshold_RER | B71: ='CH6. Ngưỡng KPI'!$C$33 -> 0.4 | C71: % | D71: Ngưỡng tỷ lệ tái ghi danh (Re-enrollment Rate). | E71: Mục tiêu giữ chân HV học khóa tiếp. | F71: 0,4 (40%). | G71: ="Tỷ lệ tái ghi danh dưới "&TEXT($B$40,"0%")&" thì cảnh báo." -> Tỷ lệ tái ghi danh dưới 2400% thì cảnh báo. | H71: Đặt cao hơn thì khắt khe hơn. Dùng ở các sheet Báo cáo (BC), so với số thực tế để tô cảnh báo.

Sheet CH3. Phân quyền
A1: BẢNG PHÂN QUYỀN VẬN HÀNH (Ai được làm gì)
A2: Bảng này quy định MỖI VAI TRÒ được làm những việc gì. Khi không chắc ai có quyền duyệt/xử lý một việc, tra ở đây. Việc nằm ngoài quyền của mình thì phải chuyển cho người có thẩm quyền (vd: duyệt chiết khấu lớn cần Trưởng phòng/CEO).
A3: Hành động | B3: NV Tư vấn (sales_staff) | C3: NV WOW (wow_coach) | D3: NV Học vụ (academic_staff) | E3: Giảng viên (teacher) | F3: Quản lý (các *_manager) | G3: Điều kiện áp dụng
A4: QUẢN LÝ LEAD & TƯ VẤN
A5: Nhập và tạo lead mới | B5: X | C5: X | G5: NV Tư vấn và NV WOW được nhập lead mới
A6: Cập nhật thông tin lead | B6: X | G6: NV Tư vấn chỉ sửa được lead mình phụ trách
A7: Đặt lịch test đầu vào | B7: X
A8: Bàn giao lead khi NV nghỉ đột xuất | F8: [duyệt] | G8: Quản lý phê duyệt khi bàn giao lead lúc nhân viên nghỉ
A9: QUẢN LÝ BUỔI TEST
A10: Điểm danh và giám sát buổi test | C10: X
A11: Chấm bài test, viết academic_note | C11: X | G11: Chỉ NV WOW được chấm bài test
A12: Nhắc lịch test cho học viên | B12: X
A13: Đặt lại lịch test sau khi vắng | B13: X
A14: THANH TOÁN & ĐĂNG KÝ
A15: Ghi nhận thanh toán | B15: X | G15: NV Tư vấn (hoặc Kế toán) ghi nhận thanh toán
A16: Áp dụng chiết khấu dưới 1 triệu | B16: X | G16: Áp dụng khi chiết khấu dưới mức cần duyệt
A17: Áp dụng chiết khấu từ 1 triệu trở lên | F17: [duyệt] | G17: Khi chiết khấu từ mức cần duyệt trở lên, Quản lý phải phê duyệt
A18: Xác nhận hoàn tiền | F18: [duyệt] | G18: Quản lý phê duyệt việc hoàn tiền
A19: XẾP LỚP & ONBOARDING
A20: Xếp lớp học viên | D20: X | G20: NV Học vụ phụ trách xếp lớp
A21: Đổi lớp (lần 1 - miễn phí) | D21: X | G21: Đổi lớp lần đầu được miễn phí
A22: Đổi lớp (lần 2 trở đi) | F22: [duyệt] | G22: Đổi lớp lần 2 trở đi cần Quản lý phê duyệt
A23: GIẢNG DẠY & THEO DÕI HỌC
A24: Điểm danh buổi học | E24: X | G24: Giảng viên phụ trách điểm danh lớp mình dạy
A25: Giao và chấm bài tập về nhà | E25: X
A26: Viết teacher_note | E26: X | G26: Bắt buộc viết nhận xét khi học viên có mặt
A27: Book buổi WOW 1-1 cho học viên | D27: X | E27: X | G27: NV Học vụ và Giảng viên đều được đặt buổi WOW
A28: Cập nhật at_risk/off_track | D28: X | E28: X | G28: NV Học vụ và Giảng viên cập nhật tình trạng học viên
A29: BUỔI WOW 1-1
A30: Tạo buổi WOW từ cảnh báo at_risk | G30: Hệ thống tự tạo buổi WOW khi có cảnh báo nguy cơ
A31: Học viên tự book WOW qua LMS | D31: hỗ trợ | E31: hỗ trợ | G31: Học viên tự đặt qua hệ thống, tự trừ lượt
A32: Thực hiện buổi WOW 1-1 | C32: X | G32: NV WOW thực hiện buổi WOW
A33: Phê duyệt WOW bổ sung miễn phí | F33: [duyệt] | G33: Buổi WOW miễn phí thêm cần Quản lý duyệt
A34: Bán gói WOW bổ sung (có phí) | B34: X | G34: NV Tư vấn bán thêm gói WOW
A35: FEEDBACK & KHIẾU NẠI
A36: Ghi nhận và phân loại feedback | D36: X | G36: NV Học vụ ghi nhận và phân loại phản hồi
A37: Xử lý feedback tiêu cực (điểm 1-2) | D37: X
A38: Mở khiếu nại chính thức | D38: X
A39: Phê duyệt giải pháp khiếu nại | F39: [duyệt] | G39: Quản lý phê duyệt giải pháp khiếu nại
A40: VẬN HÀNH CHUNG
A41: Phê duyệt bảo lưu khóa học | F41: [duyệt] | G41: Quản lý phê duyệt việc bảo lưu khóa
A42: Cập nhật bảng giá khóa học | F42: [duyệt] | G42: Quản lý phê duyệt khi đổi bảng giá
A44: Ghi chú: Giảng viên KHÔNG có quyền truy cập thông tin thanh toán hoặc lead. Học viên tự book WOW qua LMS - hệ thống tự trừ quota không cần qua nhân viên.

Sheet CH4. Thông điệp nhắc việc
A1: THÔNG ĐIỆP NHẮC VIỆC (next_action)
A2: Đây là toàn bộ câu nhắc việc tự hiện ở cột "Việc cần làm" trong các sheet. Muốn đổi câu chữ: chỉ sửa ô VÀNG ở cột "Thông điệp nhắc", cả file tự đổi theo - không cần biết công thức. Cột "Khi nào câu này hiện ra" cho biết tình huống, cột "Người phụ trách" cho biết ai cần làm. VÍ DỤ dòng NA001: khi một khách đã có kết quả test nhưng quá 24 giờ chưa được tư vấn, nhân viên Tư vấn sẽ thấy câu "Quá hạn tư vấn sau test - tư vấn ngay" ở sheet DL03. Nếu trưởng phòng muốn câu khác, ví dụ "Gấp: khách chờ tư vấn đã lâu", thì sửa thẳng vào ô vàng dòng NA001.
A3: Mã | B3: Ở sheet nào | C3: MẪU CÂU (SỬA Ở ĐÂY - sửa chữ thoải mái, GIỮ NGUYÊN chỗ trống {1}) | D3: Khi nào câu này hiện ra | E3: Người phụ trách | F3: Tham số (bấm mở CH2) | G3: Câu hoàn chỉnh (tự ghép - KHÔNG SỬA)
A4: NA046 | B4: DL02 - Khách tiềm năng | C4: Lead đã giao cho NV nhưng quá {1} giờ (cấu hình slaLeadReassign_hours) chưa gọi. Việc cần làm: gọi gấp hoặc giao lại cho NV khác. | D4: Lead đã giao, quá hạn gọi | E4: NV Tư vấn | F4: =HYPERLINK("#'DL02. Khách tiềm năng'!A"&MATCH("slaLeadReassign_hours",'CH2. Tham số & Quy tắc'!$A:$A,0),"{1} = slaLeadReassign_hours") -> {1} = slaLeadReassign_hours | G4: =SUBSTITUTE(C4,"{1}",(slaLeadReassign_hours&"")) -> Lead đã giao cho NV nhưng quá 4 giờ (cấu hình slaLeadReassign_hours) chưa gọi. Việc cần làm: gọi gấp hoặc giao lại cho NV khác.
A5: NA047 | B5: DL02 - Khách tiềm năng | C5: Đã liên hệ đủ {1} lần (cấu hình thresholdContacted_attempts) mà khách không phản hồi. Việc cần làm: cân nhắc chuyển lead sang trạng thái không liên lạc được. | D5: Đã gọi đủ số lần ngưỡng | E5: NV Tư vấn | F5: =HYPERLINK("#'DL02. Khách tiềm năng'!A"&MATCH("thresholdContacted_attempts",'CH2. Tham số & Quy tắc'!$A:$A,0),"{1} = thresholdContacted_attempts") -> {1} = thresholdContacted_attempts | G5: =SUBSTITUTE(C5,"{1}",(thresholdContacted_attempts&"")) -> Đã liên hệ đủ 5 lần (cấu hình thresholdContacted_attempts) mà khách không phản hồi. Việc cần làm: cân nhắc chuyển lead sang trạng thái không liên lạc được.
A6: NA048 | B6: DL02 - Khách tiềm năng | C6: Đã liên hệ nhưng quá {1} ngày (cấu hình thresholdContacted_days) chưa chốt. Việc cần làm: đẩy mạnh tư vấn để chốt. | D6: Đã liên hệ, quá số ngày chưa chốt | E6: NV Tư vấn | F6: =HYPERLINK("#'DL02. Khách tiềm năng'!A"&MATCH("thresholdContacted_days",'CH2. Tham số & Quy tắc'!$A:$A,0),"{1} = thresholdContacted_days") -> {1} = thresholdContacted_days | G6: =SUBSTITUTE(C6,"{1}",(thresholdContacted_days&"")) -> Đã liên hệ nhưng quá 7 ngày (cấu hình thresholdContacted_days) chưa chốt. Việc cần làm: đẩy mạnh tư vấn để chốt.
A7: NA049 | B7: DL02 - Khách tiềm năng | C7: Lead mới đã quá {1} phút (cấu hình slaLRT_minutes) chưa được liên hệ. Việc cần làm: GỌI NGAY để không mất lead. | D7: Lead mới quá hạn phản hồi | E7: NV Tư vấn | F7: =HYPERLINK("#'DL02. Khách tiềm năng'!A"&MATCH("slaLRT_minutes",'CH2. Tham số & Quy tắc'!$A:$A,0),"{1} = slaLRT_minutes") -> {1} = slaLRT_minutes | G7: =SUBSTITUTE(C7,"{1}",(slaLRT_minutes&"")) -> Lead mới đã quá 15 phút (cấu hình slaLRT_minutes) chưa được liên hệ. Việc cần làm: GỌI NGAY để không mất lead.
A8: NA050 | B8: DL02 - Khách tiềm năng | C8: Lead mới, còn trong hạn phản hồi {1} phút (cấu hình slaLRT_minutes). Việc cần làm: liên hệ khách càng sớm càng tốt. | D8: Lead mới còn trong hạn phản hồi | E8: NV Tư vấn | F8: =HYPERLINK("#'DL02. Khách tiềm năng'!A"&MATCH("slaLRT_minutes",'CH2. Tham số & Quy tắc'!$A:$A,0),"{1} = slaLRT_minutes") -> {1} = slaLRT_minutes | G8: =SUBSTITUTE(C8,"{1}",(slaLRT_minutes&"")) -> Lead mới, còn trong hạn phản hồi 15 phút (cấu hình slaLRT_minutes). Việc cần làm: liên hệ khách càng sớm càng tốt.
A9: NA051 | B9: DL02 - Khách tiềm năng | C9: Đã tới hoặc quá hẹn theo dõi lead. Việc cần làm: liên hệ lại ngay. | D9: Tới/quá hẹn theo dõi | E9: NV Tư vấn | F9: - | G9: =C9 -> Đã tới hoặc quá hẹn theo dõi lead. Việc cần làm: liên hệ lại ngay.
A10: NA052 | B10: DL02 - Khách tiềm năng | C10: Sắp tới hẹn theo dõi lead (trong vòng 24 giờ). Việc cần làm: chuẩn bị liên hệ khách. | D10: Sắp tới hẹn theo dõi | E10: NV Tư vấn | F10: - | G10: =C10 -> Sắp tới hẹn theo dõi lead (trong vòng 24 giờ). Việc cần làm: chuẩn bị liên hệ khách.
A11: NA053 | B11: DL02 - Khách tiềm năng | C11: Lead đã đóng (từ chối hoặc không liên lạc được). Không cần làm gì thêm. | D11: Lead đã đóng | E11: - | F11: - | G11: =C11 -> Lead đã đóng (từ chối hoặc không liên lạc được). Không cần làm gì thêm.
A12: NA001 | B12: DL03 - Đặt lịch test | C12: Khách đã có kết quả test nhưng quá {1} giờ (cấu hình slaCVT_hours) chưa được tư vấn. Việc cần làm: tư vấn ngay để chốt khi khách còn quan tâm. | D12: ="Khách đã có kết quả test nhưng quá hạn tư vấn ("&slaCVT_hours&" giờ) vẫn chưa được tư vấn lộ trình." -> Khách đã có kết quả test nhưng quá hạn tư vấn (24 giờ) vẫn chưa được tư vấn lộ trình. | E12: NV Tư vấn | F12: =HYPERLINK("#'DL03. Đặt lịch test'!A"&MATCH("slaCVT_hours",'CH2. Tham số & Quy tắc'!$A:$A,0),"{1} = slaCVT_hours") -> {1} = slaCVT_hours | G12: =SUBSTITUTE(C12,"{1}",(slaCVT_hours&"")) -> Khách đã có kết quả test nhưng quá 24 giờ (cấu hình slaCVT_hours) chưa được tư vấn. Việc cần làm: tư vấn ngay để chốt khi khách còn quan tâm.
A13: NA002 | B13: DL03 - Đặt lịch test | C13: Đã tư vấn xong cho khách. Không cần làm gì thêm ở bước này. | D13: Đã tư vấn lộ trình cho khách - không cần làm gì thêm ở bước này. | E13: NV Tư vấn | F13: - | G13: =C13 -> Đã tư vấn xong cho khách. Không cần làm gì thêm ở bước này.
A14: NA054 | B14: DL03 - Đặt lịch test | C14: Khách đã làm test nhưng quá {1} giờ (cấu hình slaGLA_hours) chưa chấm bài. Việc cần làm: chấm bài test ngay. | D14: Có bài test, quá hạn chấm | E14: Người chấm test | F14: =HYPERLINK("#'DL03. Đặt lịch test'!A"&MATCH("slaGLA_hours",'CH2. Tham số & Quy tắc'!$A:$A,0),"{1} = slaGLA_hours") -> {1} = slaGLA_hours | G14: =SUBSTITUTE(C14,"{1}",(slaGLA_hours&"")) -> Khách đã làm test nhưng quá 24 giờ (cấu hình slaGLA_hours) chưa chấm bài. Việc cần làm: chấm bài test ngay.
A15: NA055 | B15: DL03 - Đặt lịch test | C15: Bài test chờ chấm, còn trong hạn {1} giờ (cấu hình slaGLA_hours). Việc cần làm: chấm bài sớm để kịp tư vấn. | D15: Có bài test, còn trong hạn chấm | E15: Người chấm test | F15: =HYPERLINK("#'DL03. Đặt lịch test'!A"&MATCH("slaGLA_hours",'CH2. Tham số & Quy tắc'!$A:$A,0),"{1} = slaGLA_hours") -> {1} = slaGLA_hours | G15: =SUBSTITUTE(C15,"{1}",(slaGLA_hours&"")) -> Bài test chờ chấm, còn trong hạn 24 giờ (cấu hình slaGLA_hours). Việc cần làm: chấm bài sớm để kịp tư vấn.
A16: NA056 | B16: DL03 - Đặt lịch test | C16: Đã chấm xong bài test. Việc cần làm: chuyển trạng thái sau test sang chờ tư vấn (awaiting). | D16: Đã chấm xong test | E16: NV Tư vấn | F16: - | G16: =C16 -> Đã chấm xong bài test. Việc cần làm: chuyển trạng thái sau test sang chờ tư vấn (awaiting).
A17: NA085 | B17: DL03 - Đặt lịch test | C17: Cập nhật post_test_status = awaiting_consultation (chờ tư vấn) | D17: Đã chấm xong, chưa chuyển trạng thái sau test | E17: Học vụ / hệ thống | F17: - | G17: =C17 -> Cập nhật post_test_status = awaiting_consultation (chờ tư vấn)
A18: NA086 | B18: DL03 - Đặt lịch test | C18: Tạo Tư vấn mới (CS-...) cho lead này ở sheet DL04 | D18: Đã chuyển chờ tư vấn, cần tạo bản ghi tư vấn | E18: NV Tư vấn | F18: - | G18: =C18 -> Tạo Tư vấn mới (CS-...) cho lead này ở sheet DL04
A19: NA003 | B19: DL04 - Tư vấn | C19: Khách quan tâm nhưng đã quá {1} ngày (cấu hình slaFollowup_grace_days) chưa chốt. Việc cần làm: liên hệ chốt ngay khi khách còn quan tâm. | D19: ="Khách đã quan tâm nhưng quá số ngày theo dõi ("&slaFollowup_grace_days&" ngày) vẫn chưa chốt đăng ký." -> Khách đã quan tâm nhưng quá số ngày theo dõi (3 ngày) vẫn chưa chốt đăng ký. | E19: NV Tư vấn | F19: =HYPERLINK("#'DL04. Tư vấn'!A"&MATCH("slaFollowup_grace_days",'CH2. Tham số & Quy tắc'!$A:$A,0),"{1} = slaFollowup_grace_days") -> {1} = slaFollowup_grace_days | G19: =SUBSTITUTE(C19,"{1}",(slaFollowup_grace_days&"")) -> Khách quan tâm nhưng đã quá 3 ngày (cấu hình slaFollowup_grace_days) chưa chốt. Việc cần làm: liên hệ chốt ngay khi khách còn quan tâm.
A20: NA004 | B20: DL04 - Tư vấn | C20: Khách chưa quyết định, vẫn trong thời gian theo dõi cho phép. Việc cần làm: tiếp tục theo dõi và chăm sóc. | D20: Khách đang trong thời gian theo dõi cho phép, chưa cần thúc. | E20: NV Tư vấn | F20: - | G20: =C20 -> Khách chưa quyết định, vẫn trong thời gian theo dõi cho phép. Việc cần làm: tiếp tục theo dõi và chăm sóc.
A21: NA057 | B21: DL04 - Tư vấn | C21: Khách đã đồng ý và đặt cọc. Việc cần làm: tạo đăng ký và thu cọc (chuyển sang sheet DL06 Đăng ký). | D21: Khách đồng ý + đặt cọc | E21: NV Tư vấn | F21: - | G21: =C21 -> Khách đã đồng ý và đặt cọc. Việc cần làm: tạo đăng ký và thu cọc (chuyển sang sheet DL06 Đăng ký).
A22: NA058 | B22: DL04 - Tư vấn | C22: Khách đã bỏ, không tiếp tục. Không cần làm gì thêm. | D22: Khách bỏ | E22: - | F22: - | G22: =C22 -> Khách đã bỏ, không tiếp tục. Không cần làm gì thêm.
A23: NA005 | B23: DL06 - Đăng ký | C23: Đăng ký ở trạng thái chờ đã quá {1} giờ (cấu hình slaENR_pending_hours). Việc cần làm: xác nhận hoặc hủy đăng ký ngay. | D23: ="Một đăng ký để ở trạng thái chờ quá hạn ("&slaENR_pending_hours&" giờ) mà chưa xử lý." -> Một đăng ký để ở trạng thái chờ quá hạn (24 giờ) mà chưa xử lý. | E23: NV Tư vấn / Học vụ | F23: =HYPERLINK("#'DL06. Đăng ký'!A"&MATCH("slaENR_pending_hours",'CH2. Tham số & Quy tắc'!$A:$A,0),"{1} = slaENR_pending_hours") -> {1} = slaENR_pending_hours | G23: =SUBSTITUTE(C23,"{1}",(slaENR_pending_hours&"")) -> Đăng ký ở trạng thái chờ đã quá 24 giờ (cấu hình slaENR_pending_hours). Việc cần làm: xác nhận hoặc hủy đăng ký ngay.
A24: NA006 | B24: DL06 - Đăng ký | C24: Đăng ký đã xác nhận nhưng chưa thu được tiền. Việc cần làm: thu học phí ngay. | D24: Đăng ký đã xác nhận nhưng chưa nhận được khoản tiền nào. | E24: NV Tư vấn | F24: - | G24: =C24 -> Đăng ký đã xác nhận nhưng chưa thu được tiền. Việc cần làm: thu học phí ngay.
A25: NA007 | B25: DL06 - Đăng ký | C25: Còn khoản học phí chưa đóng và đã quá hạn {1} ngày (cấu hình slaPayment_grace_days). Việc cần làm: nhắc HV đóng phần còn lại ngay. | D25: Còn một khoản học phí chưa đóng và đã tới hạn. Câu đầy đủ hiện ra: "Còn [số tiền]đ chưa đóng...". | E25: NV Tư vấn | F25: =HYPERLINK("#'DL06. Đăng ký'!A"&MATCH("slaPayment_grace_days",'CH2. Tham số & Quy tắc'!$A:$A,0),"{1} = slaPayment_grace_days") -> {1} = slaPayment_grace_days | G25: =SUBSTITUTE(C25,"{1}",(slaPayment_grace_days&"")) -> Còn khoản học phí chưa đóng và đã quá hạn 14 ngày (cấu hình slaPayment_grace_days). Việc cần làm: nhắc HV đóng phần còn lại ngay.
A26: NA008 | B26: DL06 - Đăng ký | C26: Đăng ký đã hủy. Việc cần làm: kiểm tra và xử lý hoàn tiền nếu có. | D26: Đăng ký đã hủy, cần kiểm tra việc hoàn tiền nếu có. | E26: Kế toán / Học vụ | F26: - | G26: =C26 -> Đăng ký đã hủy. Việc cần làm: kiểm tra và xử lý hoàn tiền nếu có.
A27: NA009 | B27: DL06 - Đăng ký | C27: Đăng ký đã xác nhận và HV đã đóng đủ tiền. Không cần làm gì thêm. | D27: Đăng ký đã xác nhận và học viên đã đóng đủ - xong. | E27: - | F27: - | G27: =C27 -> Đăng ký đã xác nhận và HV đã đóng đủ tiền. Không cần làm gì thêm.
A28: NA059 | B28: DL06 - Đăng ký | C28: Đăng ký đã hủy. Chính sách hoàn tiền (cấu hình): hoàn 100% nếu hủy trong {1} ngày, hoàn một phần nếu trong {2} ngày, hoàn mức thấp nếu trong {3} ngày, quá thì không hoàn. Việc cần làm: kiểm tra ngày hủy và xử lý hoàn tiền. | D28: Đăng ký đã hủy | E28: Kế toán / Học vụ | F28: =HYPERLINK("#'DL06. Đăng ký'!A"&MATCH("refundFull_days",'CH2. Tham số & Quy tắc'!$A:$A,0),"{1} = refundFull_days, {2} = refundPartial_days, {3} = refundReduced_days") -> {1} = refundFull_days, {2} = refundPartial_days, {3} = refundReduced_days | G28: =SUBSTITUTE(SUBSTITUTE(SUBSTITUTE(C28,"{1}",(refundFull_days&"")),"{2}",(refundPartial_days&"")),"{3}",(refundReduced_days&"")) -> Đăng ký đã hủy. Chính sách hoàn tiền (cấu hình): hoàn 100% nếu hủy trong 7 ngày, hoàn một phần nếu trong 14 ngày, hoàn mức thấp nếu trong 30 ngày, quá thì không hoàn. Việc cần làm: kiểm tra ngày hủy và xử lý hoàn tiền.
A29: NA060 | B29: DL06 - Đăng ký | C29: Đăng ký để ở trạng thái chờ quá {1} giờ (cấu hình slaENR_cancel_hours). Việc cần làm: cân nhắc hủy đăng ký ngay để dọn dữ liệu ảo. | D29: Đăng ký chờ quá hạn hủy | E29: NV Tư vấn / Học vụ | F29: =HYPERLINK("#'DL06. Đăng ký'!A"&MATCH("slaENR_cancel_hours",'CH2. Tham số & Quy tắc'!$A:$A,0),"{1} = slaENR_cancel_hours") -> {1} = slaENR_cancel_hours | G29: =SUBSTITUTE(C29,"{1}",(slaENR_cancel_hours&"")) -> Đăng ký để ở trạng thái chờ quá 72 giờ (cấu hình slaENR_cancel_hours). Việc cần làm: cân nhắc hủy đăng ký ngay để dọn dữ liệu ảo.
A30: NA061 | B30: DL06 - Đăng ký | C30: Khoản giảm giá vượt mức cho phép {1}đ (cấu hình thresholdDiscount_approval). Việc cần làm: trình cấp trên duyệt trước khi áp dụng. | D30: Giảm giá vượt mức | E30: Quản lý | F30: =HYPERLINK("#'DL06. Đăng ký'!A"&MATCH("thresholdDiscount_approval",'CH2. Tham số & Quy tắc'!$A:$A,0),"{1} = thresholdDiscount_approval") -> {1} = thresholdDiscount_approval | G30: =SUBSTITUTE(C30,"{1}",TEXT(thresholdDiscount_approval,"#,##0")) -> Khoản giảm giá vượt mức cho phép 1,000,000đ (cấu hình thresholdDiscount_approval). Việc cần làm: trình cấp trên duyệt trước khi áp dụng.
A31: NA087 | B31: DL06 - Đăng ký | C31: Đã đủ cọc tối thiểu {1}đ - chuyển enrollment_status = confirmed và tạo Onboarding (DL08) | D31: Đã đủ cọc tối thiểu, đăng ký còn ở trạng thái chờ | E31: Kế toán / Học vụ | F31: =HYPERLINK("#'DL06. Đăng ký'!A"&MATCH("thresholdDeposit_minimum",'CH2. Tham số & Quy tắc'!$A:$A,0),"{1} = thresholdDeposit_minimum") -> {1} = thresholdDeposit_minimum | G31: =SUBSTITUTE(C31,"{1}",TEXT(thresholdDeposit_minimum,"#,##0")) -> Đã đủ cọc tối thiểu 5,000,000đ - chuyển enrollment_status = confirmed và tạo Onboarding (DL08)
A32: NA088 | B32: DL06 - Đăng ký | C32: Đã thanh toán đủ - chuyển sang Onboarding (DL08) nếu chưa | D32: Đã thanh toán đủ học phí | E32: Kế toán / Học vụ | F32: - | G32: =C32 -> Đã thanh toán đủ - chuyển sang Onboarding (DL08) nếu chưa
A33: NA010 | B33: DL08 - Xếp lớp & Nhập học | C33: Đã xếp lớp nhưng quá {1} giờ (cấu hình slaOBT_hours) chưa hoàn tất nhập học. Việc cần làm: kiểm tra và đẩy nhanh nhập học ngay. | D33: ="Đăng ký đã xác nhận nhưng quá hạn hoàn tất nhập học ("&slaOBT_hours&" giờ)." -> Đăng ký đã xác nhận nhưng quá hạn hoàn tất nhập học (72 giờ). | E33: Học vụ | F33: =HYPERLINK("#'DL08. Xếp lớp & Nhập học'!A"&MATCH("slaOBT_hours",'CH2. Tham số & Quy tắc'!$A:$A,0),"{1} = slaOBT_hours") -> {1} = slaOBT_hours | G33: =SUBSTITUTE(C33,"{1}",(slaOBT_hours&"")) -> Đã xếp lớp nhưng quá 72 giờ (cấu hình slaOBT_hours) chưa hoàn tất nhập học. Việc cần làm: kiểm tra và đẩy nhanh nhập học ngay.
A34: NA011 | B34: DL08 - Xếp lớp & Nhập học | C34: Nhập học đang dở và đã quá {1} giờ (cấu hình slaOBT_hours). Việc cần làm: gửi tài liệu và hoàn tất thủ tục ngay. | D34: Thủ tục nhập học chưa hoàn tất, cần gửi tài liệu cho học viên. | E34: Học vụ | F34: =HYPERLINK("#'DL08. Xếp lớp & Nhập học'!A"&MATCH("slaOBT_hours",'CH2. Tham số & Quy tắc'!$A:$A,0),"{1} = slaOBT_hours") -> {1} = slaOBT_hours | G34: =SUBSTITUTE(C34,"{1}",(slaOBT_hours&"")) -> Nhập học đang dở và đã quá 72 giờ (cấu hình slaOBT_hours). Việc cần làm: gửi tài liệu và hoàn tất thủ tục ngay.
A35: NA012 | B35: DL08 - Xếp lớp & Nhập học | C35: HV đã hoàn tất nhập học. Không cần làm gì thêm. | D35: Học viên đã hoàn tất nhập học. | E35: Học vụ | F35: - | G35: =C35 -> HV đã hoàn tất nhập học. Không cần làm gì thêm.
A36: NA013 | B36: DL08 - Xếp lớp & Nhập học | C36: Đang trong thời hạn xử lý cho phép, chưa cần thúc. | D36: Còn trong thời hạn cho phép, chưa cần thúc. | E36: Học vụ | F36: - | G36: =C36 -> Đang trong thời hạn xử lý cho phép, chưa cần thúc.
A37: NA062 | B37: DL08 - Xếp lớp & Nhập học | C37: Đã xếp lớp nhưng quá {1} giờ (cấu hình slaClassInfoZalo_hours) chưa gửi thông tin lớp. Việc cần làm: gửi thông tin lớp qua Zalo cho HV ngay. | D37: Đã xếp lớp, quá hạn gửi Zalo | E37: Học vụ | F37: =HYPERLINK("#'DL08. Xếp lớp & Nhập học'!A"&MATCH("slaClassInfoZalo_hours",'CH2. Tham số & Quy tắc'!$A:$A,0),"{1} = slaClassInfoZalo_hours") -> {1} = slaClassInfoZalo_hours | G37: =SUBSTITUTE(C37,"{1}",(slaClassInfoZalo_hours&"")) -> Đã xếp lớp nhưng quá 24 giờ (cấu hình slaClassInfoZalo_hours) chưa gửi thông tin lớp. Việc cần làm: gửi thông tin lớp qua Zalo cho HV ngay.
A38: NA063 | B38: DL08 - Xếp lớp & Nhập học | C38: Đăng ký đã xác nhận nhưng quá {1} giờ (cấu hình slaPLR48_hours) chưa xếp lớp. Việc cần làm: xếp lớp ngay. | D38: Quá hạn xếp lớp | E38: Học vụ | F38: =HYPERLINK("#'DL08. Xếp lớp & Nhập học'!A"&MATCH("slaPLR48_hours",'CH2. Tham số & Quy tắc'!$A:$A,0),"{1} = slaPLR48_hours") -> {1} = slaPLR48_hours | G38: =SUBSTITUTE(C38,"{1}",(slaPLR48_hours&"")) -> Đăng ký đã xác nhận nhưng quá 48 giờ (cấu hình slaPLR48_hours) chưa xếp lớp. Việc cần làm: xếp lớp ngay.
A39: NA089 | B39: DL08 - Xếp lớp & Nhập học | C39: Hoàn tất - set student.status = active (DL09) | D39: Đã xác nhận lớp và hoàn tất onboarding | E39: Học vụ | F39: - | G39: =C39 -> Hoàn tất - set student.status = active (DL09)
A40: NA090 | B40: DL08 - Xếp lớp & Nhập học | C40: Gửi: lịch học + giáo trình + nội quy + LMS guide, rồi set onboarding_status = completed | D40: Đã xác nhận lớp, chưa hoàn tất onboarding | E40: Học vụ | F40: - | G40: =C40 -> Gửi: lịch học + giáo trình + nội quy + LMS guide, rồi set onboarding_status = completed
A41: NA014 | B41: DL09 - Học viên | C41: HV vừa yếu chuyên cần vừa yếu học thuật (mức nguy hiểm). Việc cần làm: họp 4 bên gấp và đặt buổi WOW kèm học thuật. | D41: Học viên vừa yếu chuyên cần vừa yếu học thuật ở mức nghiêm trọng - cần can thiệp khẩn. | E41: Học vụ + Quản lý | F41: - | G41: =C41 -> HV vừa yếu chuyên cần vừa yếu học thuật (mức nguy hiểm). Việc cần làm: họp 4 bên gấp và đặt buổi WOW kèm học thuật.
A42: NA015 | B42: DL09 - Học viên | C42: Tiến độ học thuật của HV rớt khỏi lộ trình. Việc cần làm: họp 3 bên gấp (trong 24 giờ) và đặt buổi WOW. | D42: Tiến độ học thuật của học viên rớt khỏi lộ trình. | E42: Học vụ | F42: - | G42: =C42 -> Tiến độ học thuật của HV rớt khỏi lộ trình. Việc cần làm: họp 3 bên gấp (trong 24 giờ) và đặt buổi WOW.
A43: NA016 | B43: DL09 - Học viên | C43: Chuyên cần của HV sa sút nặng. Việc cần làm: họp 3 bên gấp (trong 24 giờ). | D43: Học viên nghỉ học nhiều, chuyên cần rớt khỏi mức cho phép. | E43: Học vụ | F43: - | G43: =C43 -> Chuyên cần của HV sa sút nặng. Việc cần làm: họp 3 bên gấp (trong 24 giờ).
A44: NA017 | B44: DL09 - Học viên | C44: Chuyên cần có dấu hiệu rủi ro. Việc cần làm: can thiệp, liên hệ HV trong 24-48 giờ. | D44: Học viên bắt đầu nghỉ nhiều, có nguy cơ - cần nhắc sớm. | E44: Học vụ | F44: - | G44: =C44 -> Chuyên cần có dấu hiệu rủi ro. Việc cần làm: can thiệp, liên hệ HV trong 24-48 giờ.
A45: NA018 | B45: DL09 - Học viên | C45: HV đang học đều và ổn định. Không cần làm gì thêm. | D45: Học viên đi học và làm bài đều - không cần can thiệp. | E45: - | F45: - | G45: =C45 -> HV đang học đều và ổn định. Không cần làm gì thêm.
A46: NA064 | B46: DL09 - Học viên | C46: HV vắng không phép từ {1} buổi trở lên (cấu hình thresholdAtRisk_absences). Việc cần làm: đánh dấu nguy cơ chuyên cần, học vụ liên hệ HV ngay. | D46: Vắng vượt ngưỡng | E46: Học vụ | F46: =HYPERLINK("#'DL09. Học viên'!A"&MATCH("thresholdAtRisk_absences",'CH2. Tham số & Quy tắc'!$A:$A,0),"{1} = thresholdAtRisk_absences") -> {1} = thresholdAtRisk_absences | G46: =SUBSTITUTE(C46,"{1}",(thresholdAtRisk_absences&"")) -> HV vắng không phép từ 2 buổi trở lên (cấu hình thresholdAtRisk_absences). Việc cần làm: đánh dấu nguy cơ chuyên cần, học vụ liên hệ HV ngay.
A47: NA065 | B47: DL09 - Học viên | C47: HV thiếu bài tập từ {1} lần trở lên (cấu hình thresholdAtRisk_hw_missing). Việc cần làm: đánh dấu nguy cơ học thuật, can thiệp ngay. | D47: Thiếu bài vượt ngưỡng | E47: Học vụ | F47: =HYPERLINK("#'DL09. Học viên'!A"&MATCH("thresholdAtRisk_hw_missing",'CH2. Tham số & Quy tắc'!$A:$A,0),"{1} = thresholdAtRisk_hw_missing") -> {1} = thresholdAtRisk_hw_missing | G47: =SUBSTITUTE(C47,"{1}",(thresholdAtRisk_hw_missing&"")) -> HV thiếu bài tập từ 3 lần trở lên (cấu hình thresholdAtRisk_hw_missing). Việc cần làm: đánh dấu nguy cơ học thuật, can thiệp ngay.
A48: NA066 | B48: DL09 - Học viên | C48: Học thuật của HV có dấu hiệu rủi ro (at-risk). Việc cần làm: học vụ đặt buổi WOW kèm học thuật (academic_support, theo SOP P7). | D48: Học thuật at-risk | E48: Học vụ | F48: - | G48: =C48 -> Học thuật của HV có dấu hiệu rủi ro (at-risk). Việc cần làm: học vụ đặt buổi WOW kèm học thuật (academic_support, theo SOP P7).
A49: NA067 | B49: DL09 - Học viên | C49: HV không có hoạt động học quá {1} ngày (cấu hình slaActivity_inactive_days). Việc cần làm: liên hệ kiểm tra tình hình HV ngay. | D49: Không hoạt động quá hạn | E49: Học vụ | F49: =HYPERLINK("#'DL09. Học viên'!A"&MATCH("slaActivity_inactive_days",'CH2. Tham số & Quy tắc'!$A:$A,0),"{1} = slaActivity_inactive_days") -> {1} = slaActivity_inactive_days | G49: =SUBSTITUTE(C49,"{1}",(slaActivity_inactive_days&"")) -> HV không có hoạt động học quá 7 ngày (cấu hình slaActivity_inactive_days). Việc cần làm: liên hệ kiểm tra tình hình HV ngay.
A50: NA019 | B50: DL11 - Buổi học | C50: Buổi học sắp tới. Việc cần làm: chuẩn bị giáo án trước buổi. | D50: Sắp tới một buổi dạy, giáo viên cần chuẩn bị giáo án. | E50: Giáo viên | F50: - | G50: =C50 -> Buổi học sắp tới. Việc cần làm: chuẩn bị giáo án trước buổi.
A51: NA020 | B51: DL11 - Buổi học | C51: Buổi đang diễn ra. Sau buổi nhớ điểm danh và ghi nhận xét (teacher_note). | D51: Buổi học đang diễn ra hôm nay. | E51: Giáo viên | F51: - | G51: =C51 -> Buổi đang diễn ra. Sau buổi nhớ điểm danh và ghi nhận xét (teacher_note).
A52: NA021 | B52: DL11 - Buổi học | C52: Buổi đã xong nhưng quá {1} giờ (cấu hình slaTeacherNote_hours) chưa ghi nhận xét. Việc cần làm: ghi teacher_note ngay. | D52: ="Buổi học đã xong hơn "&slaTeacherNote_hours&" giờ mà giáo viên chưa ghi nhận xét." -> Buổi học đã xong hơn 48 giờ mà giáo viên chưa ghi nhận xét. | E52: Giáo viên | F52: =HYPERLINK("#'DL11. Buổi học'!A"&MATCH("slaTeacherNote_hours",'CH2. Tham số & Quy tắc'!$A:$A,0),"{1} = slaTeacherNote_hours") -> {1} = slaTeacherNote_hours | G52: =SUBSTITUTE(C52,"{1}",(slaTeacherNote_hours&"")) -> Buổi đã xong nhưng quá 48 giờ (cấu hình slaTeacherNote_hours) chưa ghi nhận xét. Việc cần làm: ghi teacher_note ngay.
A53: NA022 | B53: DL11 - Buổi học | C53: Đã hoàn tất. Không cần làm gì thêm ở bước này. | D53: Buổi học đã hoàn tất và đã ghi nhận xét. | E53: Giáo viên | F53: - | G53: =C53 -> Đã hoàn tất. Không cần làm gì thêm ở bước này.
A54: NA023 | B54: DL11 - Buổi học | C54: Buổi học bị hủy. Việc cần làm: lên lịch học bù. | D54: Buổi học bị hủy, cần sắp lịch dạy bù. | E54: Học vụ | F54: - | G54: =C54 -> Buổi học bị hủy. Việc cần làm: lên lịch học bù.
A55: NA024 | B55: DL11 - Buổi học | C55: Buổi học đã dời. Việc cần làm: cập nhật lại lịch. | D55: Buổi học đã dời sang thời gian khác, cần cập nhật lịch. | E55: Học vụ | F55: - | G55: =C55 -> Buổi học đã dời. Việc cần làm: cập nhật lại lịch.
A56: NA068 | B56: DL11 - Buổi học | C56: Đã quá {1} phút sau giờ vào lớp (cấu hình slaTeacherAttendance_minutes) mà buổi chưa bắt đầu. Việc cần làm: kiểm tra giáo viên và điểm danh ngay. | D56: Quá giờ vào lớp chưa bắt đầu | E56: Học vụ / GV | F56: =HYPERLINK("#'DL11. Buổi học'!A"&MATCH("slaTeacherAttendance_minutes",'CH2. Tham số & Quy tắc'!$A:$A,0),"{1} = slaTeacherAttendance_minutes") -> {1} = slaTeacherAttendance_minutes | G56: =SUBSTITUTE(C56,"{1}",(slaTeacherAttendance_minutes&"")) -> Đã quá 30 phút sau giờ vào lớp (cấu hình slaTeacherAttendance_minutes) mà buổi chưa bắt đầu. Việc cần làm: kiểm tra giáo viên và điểm danh ngay.
A57: NA069 | B57: DL11 - Buổi học | C57: Buổi đã xong, cần ghi nhận xét (teacher_note) trong hạn {1} giờ (cấu hình slaTeacherNote_hours). Việc cần làm: ghi nhận xét buổi. | D57: Buổi xong, trong hạn ghi nhận xét | E57: Giáo viên | F57: =HYPERLINK("#'DL11. Buổi học'!A"&MATCH("slaTeacherNote_hours",'CH2. Tham số & Quy tắc'!$A:$A,0),"{1} = slaTeacherNote_hours") -> {1} = slaTeacherNote_hours | G57: =SUBSTITUTE(C57,"{1}",(slaTeacherNote_hours&"")) -> Buổi đã xong, cần ghi nhận xét (teacher_note) trong hạn 48 giờ (cấu hình slaTeacherNote_hours). Việc cần làm: ghi nhận xét buổi.
A58: NA025 | B58: DL12 - Điểm danh | C58: HV vắng không phép. Việc cần làm: kiểm tra chuỗi buổi vắng và nhắc HV. | D58: Học viên vắng mà không xin phép (nhiều buổi liên tiếp có thể thành rủi ro). | E58: Giáo viên / Học vụ | F58: - | G58: =C58 -> HV vắng không phép. Việc cần làm: kiểm tra chuỗi buổi vắng và nhắc HV.
A59: NA026 | B59: DL12 - Điểm danh | C59: HV vắng có phép. Việc cần làm: đề xuất buổi WOW để học bù. | D59: Học viên vắng có xin phép. | E59: Học vụ | F59: - | G59: =C59 -> HV vắng có phép. Việc cần làm: đề xuất buổi WOW để học bù.
A60: NA027 | B60: DL12 - Điểm danh | C60: HV đi học trễ. Việc cần làm: nhắc nhở HV đi đúng giờ. | D60: Học viên đi học trễ. | E60: Giáo viên | F60: - | G60: =C60 -> HV đi học trễ. Việc cần làm: nhắc nhở HV đi đúng giờ.
A61: NA028 | B61: DL12 - Điểm danh | C61: HV đã điểm danh, đi học đúng giờ. Không cần làm gì thêm. | D61: Học viên có mặt đúng giờ. | E61: - | F61: - | G61: =C61 -> HV đã điểm danh, đi học đúng giờ. Không cần làm gì thêm.
A62: NA070 | B62: DL12 - Điểm danh | C62: HV vắng không phép đã quá {1} giờ (cấu hình slaAbsenceCall_hours). Việc cần làm: GỌI HV/phụ huynh ngay. | D62: Vắng không phép quá hạn gọi | E62: Học vụ | F62: =HYPERLINK("#'DL12. Điểm danh'!A"&MATCH("slaAbsenceCall_hours",'CH2. Tham số & Quy tắc'!$A:$A,0),"{1} = slaAbsenceCall_hours") -> {1} = slaAbsenceCall_hours | G62: =SUBSTITUTE(C62,"{1}",(slaAbsenceCall_hours&"")) -> HV vắng không phép đã quá 24 giờ (cấu hình slaAbsenceCall_hours). Việc cần làm: GỌI HV/phụ huynh ngay.
A63: NA029 | B63: DL13 - Bài tập | C63: HV chưa nộp bài tập. Việc cần làm: kiểm tra chuỗi bài thiếu (có thể thành nguy cơ học thuật) và nhắc HV nộp. | D63: Học viên không nộp bài tập đúng hạn. | E63: Giáo viên | F63: - | G63: =C63 -> HV chưa nộp bài tập. Việc cần làm: kiểm tra chuỗi bài thiếu (có thể thành nguy cơ học thuật) và nhắc HV nộp.
A64: NA030 | B64: DL13 - Bài tập | C64: Đã chấm bài xong cho HV. Không cần làm gì thêm. | D64: Bài tập đã được chấm. | E64: Giáo viên | F64: - | G64: =C64 -> Đã chấm bài xong cho HV. Không cần làm gì thêm.
A65: NA071 | B65: DL13 - Bài tập | C65: HV đã nộp bài nhưng quá {1} giờ (cấu hình slaHomeworkGrading_hours) chưa chấm. Việc cần làm: chấm bài ngay. | D65: Đã nộp, quá hạn chấm | E65: Giáo viên | F65: =HYPERLINK("#'DL13. Bài tập'!A"&MATCH("slaHomeworkGrading_hours",'CH2. Tham số & Quy tắc'!$A:$A,0),"{1} = slaHomeworkGrading_hours") -> {1} = slaHomeworkGrading_hours | G65: =SUBSTITUTE(C65,"{1}",(slaHomeworkGrading_hours&"")) -> HV đã nộp bài nhưng quá 48 giờ (cấu hình slaHomeworkGrading_hours) chưa chấm. Việc cần làm: chấm bài ngay.
A66: NA072 | B66: DL13 - Bài tập | C66: HV đã nộp bài, còn trong hạn chấm {1} giờ (cấu hình slaHomeworkGrading_hours). Việc cần làm: chấm bài sớm. | D66: Đã nộp, còn trong hạn chấm | E66: Giáo viên | F66: =HYPERLINK("#'DL13. Bài tập'!A"&MATCH("slaHomeworkGrading_hours",'CH2. Tham số & Quy tắc'!$A:$A,0),"{1} = slaHomeworkGrading_hours") -> {1} = slaHomeworkGrading_hours | G66: =SUBSTITUTE(C66,"{1}",(slaHomeworkGrading_hours&"")) -> HV đã nộp bài, còn trong hạn chấm 48 giờ (cấu hình slaHomeworkGrading_hours). Việc cần làm: chấm bài sớm.
A67: NA073 | B67: DL13 - Bài tập | C67: Đã giao bài, HV chưa tới hạn nộp. Chờ HV nộp bài. | D67: Đã giao, chưa tới hạn nộp | E67: - | F67: - | G67: =C67 -> Đã giao bài, HV chưa tới hạn nộp. Chờ HV nộp bài.
A68: NA031 | B68: DL14 - Buổi WOW 1-1 | C68: Buổi WOW vừa được đặt. Việc cần làm: học vụ xác nhận lịch với HV sớm. | D68: Buổi WOW 1-1 mới đặt, cần xác nhận lịch với học viên. | E68: Học vụ | F68: - | G68: =C68 -> Buổi WOW vừa được đặt. Việc cần làm: học vụ xác nhận lịch với HV sớm.
A69: NA032 | B69: DL14 - Buổi WOW 1-1 | C69: Đã qua giờ hẹn buổi WOW. Việc cần làm: cập nhật trạng thái buổi (đã diễn ra hoặc HV vắng). | D69: Buổi WOW đã qua giờ hẹn mà chưa cập nhật kết quả. | E69: NV WOW | F69: - | G69: =C69 -> Đã qua giờ hẹn buổi WOW. Việc cần làm: cập nhật trạng thái buổi (đã diễn ra hoặc HV vắng).
A70: NA033 | B70: DL14 - Buổi WOW 1-1 | C70: Buổi WOW sắp tới. Việc cần làm: chuẩn bị nội dung buổi. | D70: Sắp tới một buổi WOW 1-1. | E70: NV WOW | F70: - | G70: =C70 -> Buổi WOW sắp tới. Việc cần làm: chuẩn bị nội dung buổi.
A71: NA034 | B71: DL14 - Buổi WOW 1-1 | C71: Buổi WOW đã xong. Việc cần làm: đánh giá kết quả buổi (tiến bộ / không đổi / cần thêm). | D71: Buổi WOW đã dạy xong, cần đánh giá kết quả. | E71: NV WOW | F71: - | G71: =C71 -> Buổi WOW đã xong. Việc cần làm: đánh giá kết quả buổi (tiến bộ / không đổi / cần thêm).
A72: NA035 | B72: DL14 - Buổi WOW 1-1 | C72: HV vắng buổi WOW. Việc cần làm: trừ lượt WOW và ghi lý do. | D72: Học viên không đến buổi WOW đã đặt. | E72: NV WOW | F72: - | G72: =C72 -> HV vắng buổi WOW. Việc cần làm: trừ lượt WOW và ghi lý do.
A73: NA074 | B73: DL14 - Buổi WOW 1-1 | C73: Buổi WOW đã xong nhưng quá {1} giờ (cấu hình slaWowQuotaCheck_hours) chưa trừ lượt. Việc cần làm: kiểm tra và trừ quota (quota_deducted) ngay. | D73: Buổi xong, quá hạn trừ quota | E73: NV WOW / Học vụ | F73: =HYPERLINK("#'DL14. Buổi WOW 1-1'!A"&MATCH("slaWowQuotaCheck_hours",'CH2. Tham số & Quy tắc'!$A:$A,0),"{1} = slaWowQuotaCheck_hours") -> {1} = slaWowQuotaCheck_hours | G73: =SUBSTITUTE(C73,"{1}",(slaWowQuotaCheck_hours&"")) -> Buổi WOW đã xong nhưng quá 24 giờ (cấu hình slaWowQuotaCheck_hours) chưa trừ lượt. Việc cần làm: kiểm tra và trừ quota (quota_deducted) ngay.
A74: NA075 | B74: DL14 - Buổi WOW 1-1 | C74: Buổi WOW đã xong nhưng quá {1} giờ (cấu hình slaWowOutcomeRead_hours) chưa ghi kết quả. Việc cần làm: viết content_note ngay. | D74: Buổi xong, quá hạn ghi kết quả | E74: Học vụ | F74: =HYPERLINK("#'DL14. Buổi WOW 1-1'!A"&MATCH("slaWowOutcomeRead_hours",'CH2. Tham số & Quy tắc'!$A:$A,0),"{1} = slaWowOutcomeRead_hours") -> {1} = slaWowOutcomeRead_hours | G74: =SUBSTITUTE(C74,"{1}",(slaWowOutcomeRead_hours&"")) -> Buổi WOW đã xong nhưng quá 24 giờ (cấu hình slaWowOutcomeRead_hours) chưa ghi kết quả. Việc cần làm: viết content_note ngay.
A75: NA076 | B75: DL14 - Buổi WOW 1-1 | C75: Buổi WOW đã xong, cần ghi kết quả (content_note) trong hạn {1} giờ (cấu hình slaWowOutcomeRead_hours). Việc cần làm: viết content_note. | D75: Buổi xong, trong hạn ghi kết quả | E75: Học vụ | F75: =HYPERLINK("#'DL14. Buổi WOW 1-1'!A"&MATCH("slaWowOutcomeRead_hours",'CH2. Tham số & Quy tắc'!$A:$A,0),"{1} = slaWowOutcomeRead_hours") -> {1} = slaWowOutcomeRead_hours | G75: =SUBSTITUTE(C75,"{1}",(slaWowOutcomeRead_hours&"")) -> Buổi WOW đã xong, cần ghi kết quả (content_note) trong hạn 24 giờ (cấu hình slaWowOutcomeRead_hours). Việc cần làm: viết content_note.
A76: NA077 | B76: DL14 - Buổi WOW 1-1 | C76: Buổi WOW đã hủy. Không cần làm gì thêm. | D76: Buổi WOW đã hủy | E76: - | F76: - | G76: =C76 -> Buổi WOW đã hủy. Không cần làm gì thêm.
A77: NA036 | B77: DL15 - Khảo sát | C77: Đã gửi khảo sát nhưng HV chưa làm. Việc cần làm: nhắc HV làm khảo sát. | D77: Đã gửi khảo sát nhưng học viên chưa làm. | E77: Học vụ | F77: - | G77: =C77 -> Đã gửi khảo sát nhưng HV chưa làm. Việc cần làm: nhắc HV làm khảo sát.
A78: NA037 | B78: DL15 - Khảo sát | C78: HV đã làm khảo sát. Không cần làm gì thêm. | D78: Đã nhận được phản hồi khảo sát. | E78: - | F78: - | G78: =C78 -> HV đã làm khảo sát. Không cần làm gì thêm.
A79: NA078 | B79: DL15 - Khảo sát | C79: HV đã nộp khảo sát nhưng quá {1} giờ (cấu hình slaSurveyReport_hours) chưa xử lý. Việc cần làm: phân công đọc và báo cáo khảo sát ngay. | D79: Đã nộp khảo sát, quá hạn xử lý | E79: Học vụ | F79: =HYPERLINK("#'DL15. Khảo sát'!A"&MATCH("slaSurveyReport_hours",'CH2. Tham số & Quy tắc'!$A:$A,0),"{1} = slaSurveyReport_hours") -> {1} = slaSurveyReport_hours | G79: =SUBSTITUTE(C79,"{1}",(slaSurveyReport_hours&"")) -> HV đã nộp khảo sát nhưng quá 48 giờ (cấu hình slaSurveyReport_hours) chưa xử lý. Việc cần làm: phân công đọc và báo cáo khảo sát ngay.
A80: NA079 | B80: DL15 - Khảo sát | C80: Khảo sát cho thấy cần theo dõi thêm HV. Việc cần làm: học vụ liên hệ HV. | D80: Khảo sát cần theo dõi | E80: Học vụ | F80: - | G80: =C80 -> Khảo sát cho thấy cần theo dõi thêm HV. Việc cần làm: học vụ liên hệ HV.
A81: NA091 | B81: DL16 - Phản hồi | C81: Phản hồi mới đã quá {1} giờ (cấu hình slaFB_classify_hours) chưa phân loại. Việc cần làm: phân loại ngay. | D81: Phản hồi mới quá hạn phân loại | E81: Học vụ | F81: =HYPERLINK("#'DL16. Phản hồi'!A"&MATCH("slaFB_classify_hours",'CH2. Tham số & Quy tắc'!$A:$A,0),"{1} = slaFB_classify_hours") -> {1} = slaFB_classify_hours | G81: =SUBSTITUTE(C81,"{1}",(slaFB_classify_hours&"")) -> Phản hồi mới đã quá 24 giờ (cấu hình slaFB_classify_hours) chưa phân loại. Việc cần làm: phân loại ngay.
A82: NA092 | B82: DL16 - Phản hồi | C82: Phản hồi mới, còn trong hạn phân loại {1} giờ (cấu hình slaFB_classify_hours). Việc cần làm: phân loại sớm. | D82: Phản hồi mới còn trong hạn | E82: Học vụ | F82: =HYPERLINK("#'DL16. Phản hồi'!A"&MATCH("slaFB_classify_hours",'CH2. Tham số & Quy tắc'!$A:$A,0),"{1} = slaFB_classify_hours") -> {1} = slaFB_classify_hours | G82: =SUBSTITUTE(C82,"{1}",(slaFB_classify_hours&"")) -> Phản hồi mới, còn trong hạn phân loại 24 giờ (cấu hình slaFB_classify_hours). Việc cần làm: phân loại sớm.
A83: NA093 | B83: DL16 - Phản hồi | C83: Phản hồi tiêu cực chưa xử lý xong. Việc cần làm: xử lý ngay và cân nhắc tạo khiếu nại (sheet DL17). | D83: Phản hồi tiêu cực chưa xử lý xong | E83: Học vụ | F83: - | G83: =C83 -> Phản hồi tiêu cực chưa xử lý xong. Việc cần làm: xử lý ngay và cân nhắc tạo khiếu nại (sheet DL17).
A84: NA094 | B84: DL16 - Phản hồi | C84: Đã xử lý xong phản hồi. Không cần làm gì thêm. | D84: Đã xử lý xong phản hồi | E84: - | F84: - | G84: =C84 -> Đã xử lý xong phản hồi. Không cần làm gì thêm.
A85: NA038 | B85: DL17 - Khiếu nại | C85: Khiếu nại mức cao đã quá {1} giờ (cấu hình slaKN_high_hours) chưa xử lý xong. Việc cần làm: quản lý tham gia xử lý gấp. | D85: Khiếu nại ưu tiên cao quá hạn xử lý mà chưa xong. | E85: Học vụ + Quản lý | F85: =HYPERLINK("#'DL17. Khiếu nại'!A"&MATCH("slaKN_high_hours",'CH2. Tham số & Quy tắc'!$A:$A,0),"{1} = slaKN_high_hours") -> {1} = slaKN_high_hours | G85: =SUBSTITUTE(C85,"{1}",(slaKN_high_hours&"")) -> Khiếu nại mức cao đã quá 4 giờ (cấu hình slaKN_high_hours) chưa xử lý xong. Việc cần làm: quản lý tham gia xử lý gấp.
A86: NA039 | B86: DL17 - Khiếu nại | C86: Khiếu nại mức trung bình đã quá {1} giờ (cấu hình slaKN_medium_hours) chưa xử lý. Việc cần làm: xử lý ngay. | D86: Khiếu nại ưu tiên vừa quá hạn xử lý. | E86: Học vụ | F86: =HYPERLINK("#'DL17. Khiếu nại'!A"&MATCH("slaKN_medium_hours",'CH2. Tham số & Quy tắc'!$A:$A,0),"{1} = slaKN_medium_hours") -> {1} = slaKN_medium_hours | G86: =SUBSTITUTE(C86,"{1}",(slaKN_medium_hours&"")) -> Khiếu nại mức trung bình đã quá 48 giờ (cấu hình slaKN_medium_hours) chưa xử lý. Việc cần làm: xử lý ngay.
A87: NA040 | B87: DL17 - Khiếu nại | C87: Khiếu nại đã đẩy lên cấp cao. Việc cần làm: chờ CEO/quản lý cấp cao xử lý. | D87: Khiếu nại được đẩy lên mức cao nhất. | E87: CEO | F87: - | G87: =C87 -> Khiếu nại đã đẩy lên cấp cao. Việc cần làm: chờ CEO/quản lý cấp cao xử lý.
A88: NA041 | B88: DL17 - Khiếu nại | C88: Đã giải quyết khiếu nại và HV chấp nhận. Không cần làm gì thêm. | D88: Khiếu nại đã xử lý xong. | E88: - | F88: - | G88: =C88 -> Đã giải quyết khiếu nại và HV chấp nhận. Không cần làm gì thêm.
A89: NA080 | B89: DL17 - Khiếu nại | C89: Khiếu nại ưu tiên thấp đã quá {1} ngày (cấu hình slaKN_low_hours) chưa xử lý. Việc cần làm: phản hồi và xử lý cho HV ngay. | D89: Khiếu nại thấp quá hạn | E89: Học vụ | F89: =HYPERLINK("#'DL17. Khiếu nại'!A"&MATCH("slaKN_low_hours",'CH2. Tham số & Quy tắc'!$A:$A,0),"{1} = slaKN_low_hours (đổi ra ngày)") -> {1} = slaKN_low_hours (đổi ra ngày) | G89: =SUBSTITUTE(C89,"{1}",(ROUND(slaKN_low_hours/24,0)&"")) -> Khiếu nại ưu tiên thấp đã quá 7 ngày (cấu hình slaKN_low_hours) chưa xử lý. Việc cần làm: phản hồi và xử lý cho HV ngay.
A90: NA081 | B90: DL17 - Khiếu nại | C90: Khiếu nại mới đã quá {1} giờ (cấu hình slaKN_assignment_hours) chưa phân công người xử lý. Việc cần làm: phân công gấp. | D90: Khiếu nại mới quá hạn phân công | E90: Học vụ | F90: =HYPERLINK("#'DL17. Khiếu nại'!A"&MATCH("slaKN_assignment_hours",'CH2. Tham số & Quy tắc'!$A:$A,0),"{1} = slaKN_assignment_hours") -> {1} = slaKN_assignment_hours | G90: =SUBSTITUTE(C90,"{1}",(slaKN_assignment_hours&"")) -> Khiếu nại mới đã quá 2 giờ (cấu hình slaKN_assignment_hours) chưa phân công người xử lý. Việc cần làm: phân công gấp.
A91: NA042 | B91: DL18 - Kết thúc khóa | C91: HV đã hoàn thành khóa nhưng quá {1} ngày (cấu hình slaReenroll_contact_days) chưa liên hệ mời học tiếp. Việc cần làm: liên hệ mời tái ghi danh gấp. | D91: Học viên sắp/đã kết thúc khóa, quá hạn mời học tiếp mà chưa liên hệ. | E91: NV Tư vấn | F91: =HYPERLINK("#'DL18. Kết thúc khóa'!A"&MATCH("slaReenroll_contact_days",'CH2. Tham số & Quy tắc'!$A:$A,0),"{1} = slaReenroll_contact_days") -> {1} = slaReenroll_contact_days | G91: =SUBSTITUTE(C91,"{1}",(slaReenroll_contact_days&"")) -> HV đã hoàn thành khóa nhưng quá 3 ngày (cấu hình slaReenroll_contact_days) chưa liên hệ mời học tiếp. Việc cần làm: liên hệ mời tái ghi danh gấp.
A92: NA043 | B92: DL18 - Kết thúc khóa | C92: HV đã nghỉ giữa khóa. Việc cần làm: phân tích lý do HV nghỉ để rút kinh nghiệm. | D92: Học viên đã nghỉ hẳn, chỉ ghi nhận lý do để rút kinh nghiệm. | E92: NV Tư vấn | F92: - | G92: =C92 -> HV đã nghỉ giữa khóa. Việc cần làm: phân tích lý do HV nghỉ để rút kinh nghiệm.
A93: NA044 | B93: DL18 - Kết thúc khóa | C93: HV đã đăng ký học khóa tiếp theo. Không cần làm gì thêm. | D93: Học viên đã đăng ký khóa mới. | E93: - | F93: - | G93: =C93 -> HV đã đăng ký học khóa tiếp theo. Không cần làm gì thêm.
A94: NA045 | B94: DL18 - Kết thúc khóa | C94: HV quan tâm học tiếp. Việc cần làm: liên hệ chốt đăng ký khóa mới. | D94: Học viên quan tâm học tiếp, cần liên hệ chốt. | E94: NV Tư vấn | F94: - | G94: =C94 -> HV quan tâm học tiếp. Việc cần làm: liên hệ chốt đăng ký khóa mới.
A95: NA082 | B95: DL18 - Kết thúc khóa | C95: HV hoàn thành khóa nhưng quá {1} ngày (cấu hình slaFinalTest_days) chưa có điểm test cuối. Việc cần làm: nhập điểm test cuối ngay. | D95: Hoàn thành, chưa có điểm cuối | E95: Học vụ | F95: =HYPERLINK("#'DL18. Kết thúc khóa'!A"&MATCH("slaFinalTest_days",'CH2. Tham số & Quy tắc'!$A:$A,0),"{1} = slaFinalTest_days") -> {1} = slaFinalTest_days | G95: =SUBSTITUTE(C95,"{1}",(slaFinalTest_days&"")) -> HV hoàn thành khóa nhưng quá 3 ngày (cấu hình slaFinalTest_days) chưa có điểm test cuối. Việc cần làm: nhập điểm test cuối ngay.
A96: NA083 | B96: DL18 - Kết thúc khóa | C96: HV quan tâm tái ghi danh nhưng quá {1} ngày (cấu hình slaReenrollSchedule_days) chưa xếp khóa mới. Việc cần làm: chốt lịch khóa mới cho HV gấp. | D96: Quan tâm tái ghi danh, chưa xếp khóa | E96: Học vụ / Tư vấn | F96: =HYPERLINK("#'DL18. Kết thúc khóa'!A"&MATCH("slaReenrollSchedule_days",'CH2. Tham số & Quy tắc'!$A:$A,0),"{1} = slaReenrollSchedule_days") -> {1} = slaReenrollSchedule_days | G96: =SUBSTITUTE(C96,"{1}",(slaReenrollSchedule_days&"")) -> HV quan tâm tái ghi danh nhưng quá 14 ngày (cấu hình slaReenrollSchedule_days) chưa xếp khóa mới. Việc cần làm: chốt lịch khóa mới cho HV gấp.
A97: NA084 | B97: DL18 - Kết thúc khóa | C97: HV từ chối học tiếp. Không cần làm gì thêm. | D97: HV từ chối học tiếp | E97: - | F97: - | G97: =C97 -> HV từ chối học tiếp. Không cần làm gì thêm.

Sheet CH5. Thuật ngữ
A1: THUẬT NGỮ VIẾT TẮT - TRA NGHĨA NHANH
A2: Bảng tra các chữ viết tắt dùng trong toàn bộ file. Người mới đọc sheet nào gặp từ lạ thì tra ở đây. Không cần thuộc, chỉ cần biết tra.
A4: Viết tắt | B4: Tên đầy đủ (gốc) | C4: Nghĩa tiếng Việt | D4: Ghi chú / Dùng ở đâu
A5: VAI TRÒ & ĐỐI TƯỢNG
A6: HV | C6: Học viên | D6: Người đang/đã học tại trung tâm.
A7: NV | C7: Nhân viên | D7: Nhân sự nội bộ (tư vấn, học vụ, GV...).
A8: GV | C8: Giáo viên | D8: Người dạy lớp.
A9: TV | C9: Tư vấn viên | D9: NV tư vấn, chăm sóc khách trước khi đăng ký.
A10: KHÁI NIỆM VẬN HÀNH
A11: Lead | C11: Khách tiềm năng | D11: Người mới quan tâm, chưa đăng ký. Sheet DL02.
A12: ENR | B12: Enrollment | C12: Đăng ký khóa học | D12: Một lượt HV đăng ký 1 khóa. Sheet DL06.
A13: OB / OBT | B13: Onboarding | C13: Nhập học / làm quen | D13: Thủ tục đưa HV vào lớp sau khi đăng ký. Sheet DL08.
A14: WOW | C14: Buổi học kèm 1-1 đặc biệt | D14: Buổi kèm riêng cho HV (tên gọi nội bộ ITTs). Sheet DL14.
A15: KN | C15: Khiếu nại | D15: Phàn nàn/khiếu nại của HV. Sheet DL17.
A16: FB | B16: Feedback | C16: Phản hồi | D16: Góp ý/đánh giá của HV. Sheet DL16.
A17: SLA | B17: Service Level Agreement | C17: Cam kết thời gian xử lý tối đa | D17: Mốc thời gian tối đa cho 1 việc. Cấu hình ở CH2.
A18: KPI | B18: Key Performance Indicator | C18: Chỉ số đo hiệu quả | D18: Các tỷ lệ đánh giá hoạt động. Báo cáo ở nhóm BC.
A19: MÃ SLA (CAM KẾT THỜI GIAN) - cấu hình tại CH2
A20: LRT | B20: Lead Response Time | C20: Thời gian phản hồi lead mới | D20: Tối đa bao lâu phải gọi lead mới. Tham số slaLRT_minutes.
A21: GLA | C21: Thời hạn chấm bài test đầu vào | D21: Tối đa bao lâu phải chấm xong test khách. Tham số slaGLA_hours.
A22: CVT | B22: Consultation Time | C22: Thời hạn tư vấn sau khi có kết quả test | D22: Tham số slaCVT_hours.
A23: PLR48 | B23: Placement 48h | C23: Thời hạn xếp lớp | D23: =HYPERLINK("#'CH2. Tham số & Quy tắc'!A"&MATCH("slaPLR48_hours",'CH2. Tham số & Quy tắc'!$A:$A,0),"Đăng ký xác nhận thì tối đa "&slaPLR48_hours&"h phải xếp lớp. Tham số slaPLR48_hours.") -> Đăng ký xác nhận thì tối đa 48h phải xếp lớp. Tham số slaPLR48_hours.
A24: OBT | B24: Onboarding Time | C24: Thời hạn hoàn tất nhập học | D24: Tham số slaOBT_hours.
A25: MÃ KPI (CHỈ SỐ) - ngưỡng tại CH2, kết quả tại nhóm BC
A26: VLR | B26: Valid Lead Rate | C26: Tỷ lệ lead đạt chuẩn | D26: Ngưỡng kpiThreshold_VLR.
A27: TAR | B27: Test Attendance Rate | C27: Tỷ lệ khách đặt test có đến làm | D27: Ngưỡng kpiThreshold_TAR.
A28: CVR | B28: Conversion Rate | C28: Tỷ lệ chuyển lead thành HV | D28: Ngưỡng kpiThreshold_CVR.
A29: PCR | B29: Payment Completion Rate | C29: Tỷ lệ thu đủ học phí | D29: Ngưỡng kpiThreshold_PCR.
A30: ATR | B30: Attendance Rate | C30: Tỷ lệ chuyên cần | D30: Ngưỡng kpiThreshold_ATR.
A31: UAR | B31: Unexcused Absence Rate | C31: Tỷ lệ vắng không phép | D31: Ngưỡng kpiThreshold_UAR (mức tối đa).
A32: ARR | B32: At-Risk Rate | C32: Tỷ lệ HV có nguy cơ | D32: Ngưỡng kpiThreshold_ARR (mức tối đa).
A33: CIR | B33: Complaint Incidence Rate | C33: Tỷ lệ phát sinh khiếu nại/tháng | D33: Ngưỡng kpiThreshold_CIR (mức tối đa).
A34: RR | B34: Resolution Rate | C34: Tỷ lệ giải quyết khiếu nại thành công | D34: Ngưỡng kpiThreshold_RR.
A35: RER | B35: Re-enrollment Rate | C35: Tỷ lệ tái ghi danh | D35: Ngưỡng kpiThreshold_RER.

Sheet CH6. Ngưỡng KPI
A1: CH6 - NGƯỠNG KPI (quản lý tập trung toàn bộ 48 chỉ số)
A2: Mỗi KPI một dòng. Sửa ngưỡng ở cột C (ô vàng) - mọi bảng BC tự cập nhật theo. Ba chỉ số LRT/CVT/OBT dùng chung ngưỡng SLA ở CH2 (ô cột C là công thức trỏ về CH2, sửa tại CH2).
A3: Mã | B3: Tên KPI | C3: Ngưỡng (SỬA Ở ĐÂY) | D3: Hướng đạt | E3: Phase | F3: Cách đọc / áp dụng | G3: Dùng ở đâu
A4: LRT | B4: Lead Response Time - TB phút từ lead vào gọi LH đầu | C4: =slaLRT_minutes -> 15 | D4: ≤ | E4: P1 | F4: Đọc theo từng nhân viên hoặc theo tổng thể. LRT cao ở nhiều nhân viên cùng lúc -> vấn đề về cách hệ thống phân bổ hoặc số lượng task đang quá tải. LRT cao ở một vài người -> xem lại kỷ luật cá nhân | G4: =HYPERLINK("#'BC2. Chỉ số KPI'!B"&MATCH("LRT",'BC2. Chỉ số KPI'!$B:$B,0),"Mở BC2") -> Mở BC2
A5: VLR | B5: Valid Lead Rate - Tỷ lệ lead qualified | C5: 0.6 | D5: ≥ | E5: P1 | F5: VLR thấp ở tất cả nguồn -> nhân viên chưa khai thác nhu cầu đúng cách. VLR thấp chỉ ở một vài nguồn -> nguồn đó ra lead kém chất lượng, cần điều chỉnh ngân sách marketing | G5: =HYPERLINK("#'BC2. Chỉ số KPI'!B"&MATCH("VLR",'BC2. Chỉ số KPI'!$B:$B,0),"Mở BC2") -> Mở BC2
A6: TBR | B6: Test Booking Rate - Tỷ lệ lead có book test | C6: 0.5 | D6: ≥ | E6: P2 | F6: Đọc theo từng nhân viên tư vấn. Thấp đồng loạt -> vấn đề cách đề xuất test. Thấp ở một vài người -> kỹ năng chốt lịch cá nhân chưa tốt | G6: =HYPERLINK("#'BC2. Chỉ số KPI'!B"&MATCH("TBR",'BC2. Chỉ số KPI'!$B:$B,0),"Mở BC2") -> Mở BC2
A7: TAR | B7: Test Attendance Rate - Tỷ lệ test đã đặt có đi | C7: 0.85 | D7: ≥ | E7: P2 | F7: Kết hợp với lý do vắng (test_no_show_reason) để tìm điểm chung. TAR thấp ở một khung giờ cụ thể -> xem xét điều chỉnh hoặc bỏ khung giờ đó | G7: =HYPERLINK("#'BC2. Chỉ số KPI'!B"&MATCH("TAR",'BC2. Chỉ số KPI'!$B:$B,0),"Mở BC2") -> Mở BC2
A8: NSR | B8: No-Show Rate - Tỷ lệ vắng test | C8: 0.15 | D8: ≤ | E8: P2 | F8: Phân tích kết hợp lý do vắng, khung giờ test, và khoảng cách từ ngày đặt đến ngày test | G8: =HYPERLINK("#'BC2. Chỉ số KPI'!B"&MATCH("NSR",'BC2. Chỉ số KPI'!$B:$B,0),"Mở BC2") -> Mở BC2
A9: PTD | B9: Post-Test Decline - Tỷ lệ vào tư vấn sau test | C9: 0.8 | D9: ≥ | E9: P2 | F9: Nguyên nhân thường là cách giải thích lợi ích bài test chưa thuyết phục trong cuộc gọi đầu tiên | G9: =HYPERLINK("#'BC2. Chỉ số KPI'!B"&MATCH("PTD",'BC2. Chỉ số KPI'!$B:$B,0),"Mở BC2") -> Mở BC2
A10: GLA | B10: Grading SLA - Tỷ lệ chấm bài test trong 24h | C10: 1 | D10: ≥ | E10: P2 | F10: Đọc kèm với CVT (tốc độ tư vấn sau kết quả test) giai đoạn 3: NV WOW chấm trễ -> NV tư vấn không có dữ liệu để gọi đúng hạn, dẫn đến trễ toàn bộ | G10: =HYPERLINK("#'BC2. Chỉ số KPI'!B"&MATCH("GLA",'BC2. Chỉ số KPI'!$B:$B,0),"Mở BC2") -> Mở BC2
A11: ANR | B11: Academic Note Rate - Tỷ lệ có academic_note đầy đủ | C11: 1 | D11: ≥ | E11: P2 | F11: Đọc cùng Tỷ lệ chuyển đổi đăng ký (CVR, giai đoạn 3): khi ANR thấp đồng thời CVR thấp -> nhiều khả năng nhân viên tư vấn đang thiếu dữ liệu học thuật từ academic_note để phân tích điểm mạnh yếu và thuyết phục học viên đăng ký đúng khóa đăng ký | G11: =HYPERLINK("#'BC2. Chỉ số KPI'!B"&MATCH("ANR",'BC2. Chỉ số KPI'!$B:$B,0),"Mở BC2") -> Mở BC2
A12: CR3 | B12: Consultation Rate - Lead tư vấn | C12: 0.5 | D12: ≥ | E12: P3 | F12: Thấp = lead có kết quả nhưng bị bỏ sót. Đọc kèm GLA (SLA chấm bài và trả kết quả): nếu WOW chấm trễ thì CR3 cũng sẽ trễ theo, lỗi không hoàn toàn từ NV tư vấn | G12: =HYPERLINK("#'BC2. Chỉ số KPI'!B"&MATCH("CR3",'BC2. Chỉ số KPI'!$B:$B,0),"Mở BC2") -> Mở BC2
A13: CVR | B13: Conversion Rate - Lead đăng ký + cọc | C13: 0.4 | D13: ≥ | E13: P3 | F13: Thấp đồng loạt nhiều người -> vấn đề kịch bản, giá, hoặc sản phẩm. Thấp ở một vài người -> kỹ năng xử lý rào cản / xử lý từ chối. Thấp ở một khóa cụ thể -> vấn đề giá hoặc sự phù hợp của khóa đó với nhu cầu học viên | G13: =HYPERLINK("#'BC2. Chỉ số KPI'!B"&MATCH("CVR",'BC2. Chỉ số KPI'!$B:$B,0),"Mở BC2") -> Mở BC2
A14: DR3 | B14: Drop Rate Phase 3 - Tỷ lệ dropped sau tư vấn | C14: 0.3 | D14: ≤ | E14: P3 | F14: DR3 cao đồng loạt nhiều nhân viên -> vấn đề kịch bản, giá, sản phẩm; cao ở một vài nhân viên -> vấn đề kỹ năng xử lý từ chối; cao ở một khóa cụ thể -> vấn đề giá hoặc mức độ phù hợp của khóa với nhu cầu học viên; cao theo một nhóm lý do (conversion_note) -> xử lý trực tiếp theo nguyên nhân đó | G14: =HYPERLINK("#'BC2. Chỉ số KPI'!B"&MATCH("DR3",'BC2. Chỉ số KPI'!$B:$B,0),"Mở BC2") -> Mở BC2
A15: CVT | B15: Consultation Velocity - TB giờ từ result consulted | C15: =slaCVT_hours -> 24 | D15: ≤ | E15: P3 | F15: Mỗi giờ trễ sau khi có kết quả = giảm khả năng chốt đăng ký, vì học viên nguội dần. Đọc cùng GLA (SLA chấm bài và trả kết quả): nếu WOW chậm chấm thì CVT dù cao vẫn có thể mang lại kết quả chuyển đổi kém | G15: =HYPERLINK("#'BC2. Chỉ số KPI'!B"&MATCH("CVT",'BC2. Chỉ số KPI'!$B:$B,0),"Mở BC2") -> Mở BC2
A16: PCR | B16: Payment Completion Rate - Tỷ lệ đăng ký đã paid full | C16: 0.8 | D16: ≥ | E16: P4 | F16: Thấp = còn nhiều công nợ chưa thu, ảnh hưởng trực tiếp đến dòng tiền. Đọc kèm với remaining_amount tổng hợp để biết quy mô công nợ thực tế | G16: =HYPERLINK("#'BC2. Chỉ số KPI'!B"&MATCH("PCR",'BC2. Chỉ số KPI'!$B:$B,0),"Mở BC2") -> Mở BC2
A17: CAR | B17: Cancellation Rate - Tỷ lệ ĐK bị hủy | C17: 0.05 | D17: ≤ | E17: P4 | F17: Cao liên tục -> cần xem lại chất lượng tư vấn giai đoạn 3: học viên hủy sớm thường do kỳ vọng không khớp thực tế. Đọc cùng DR3 để xem bức tranh toàn diện từ tư vấn đến sau đăng ký | G17: =HYPERLINK("#'BC2. Chỉ số KPI'!B"&MATCH("CAR",'BC2. Chỉ số KPI'!$B:$B,0),"Mở BC2") -> Mở BC2
A18: PLR48 | B18: Placement Rate 48h - Tỷ lệ xếp lớp trong 48h sau confirm | C18: 0.9 | D18: ≥ | E18: P5 | F18: Thấp = học viên chờ đợi và mất trải nghiệm tốt ngay từ đầu. Đọc cùng Trạng thái Onboarding (onboarding_status) để biết toàn bộ thời gian từ đăng ký đến vào lớp | G18: =HYPERLINK("#'BC2. Chỉ số KPI'!B"&MATCH("PLR48",'BC2. Chỉ số KPI'!$B:$B,0),"Mở BC2") -> Mở BC2
A19: CLR | B19: Class Confirmation Rate - Tỷ lệ HV confirm lớp | C19: 0.85 | D19: ≥ | E19: P5 | F19: Cao -> xếp lớp ban đầu không chính xác. Nguyên nhân thường là đọc sai Lịch rảnh (availability_schedule) hoặc Hình thức học (learning_mode) từ giai đoạn 1. Xem thêm Ghi chú xếp lớp (placement_note) để tìm hiểu lý do | G19: =HYPERLINK("#'BC2. Chỉ số KPI'!B"&MATCH("CLR",'BC2. Chỉ số KPI'!$B:$B,0),"Mở BC2") -> Mở BC2
A20: CUR | B20: Class Utilization Rate - Tỷ lệ sĩ số / capacity TB | C20: 0.7 | D20: ≥ | E20: P5 | F20: Dưới 60% = lãng phí nguồn lực giảng viên và cơ sở vật chất. Trên 95% = quá chật, ảnh hưởng chất lượng giảng dạy. Đọc cùng PLR48: nếu xếp lớp nhanh nhưng CUR thấp -> cần gộp lớp hoặc điều chỉnh lịch mở lớp | G20: =HYPERLINK("#'BC2. Chỉ số KPI'!B"&MATCH("CUR",'BC2. Chỉ số KPI'!$B:$B,0),"Mở BC2") -> Mở BC2
A21: OBT | B21: Onboarding Time - TB giờ từ confirm onboarding done | C21: =slaOBT_hours -> 72 | D21: ≤ | E21: P5 | F21: Học viên chưa hoàn thành onboarding khi bắt đầu học = không biết cách dùng LMS, không biết lịch, không biết nội quy - tạo ra rào cản ngay từ buổi đầu | G21: =HYPERLINK("#'BC2. Chỉ số KPI'!B"&MATCH("OBT",'BC2. Chỉ số KPI'!$B:$B,0),"Mở BC2") -> Mở BC2
A22: ATR | B22: Attendance Rate - Tỷ lệ chuyên cần (đúng giờ + trễ) | C22: 0.85 | D22: ≥ | E22: P6 | F22: Kết hợp với loại vắng (absence_type) để phân biệt vắng có phép và không phép. Tỷ lệ tham gia học (ATR) thấp nhưng chủ yếu là vắng có phép ("excused") -> vấn đề lịch học không phù hợp, xem xét điều chỉnh giờ học. ATR thấp với nhiều vắng không phép ("unexcused") -> học viên thiếu cam kết, nguy cơ bỏ học cao | G22: =HYPERLINK("#'BC2. Chỉ số KPI'!B"&MATCH("ATR",'BC2. Chỉ số KPI'!$B:$B,0),"Mở BC2") -> Mở BC2
A23: UAR | B23: Unexcused Absence Rate - Tỷ lệ vắng không phép | C23: 0.05 | D23: ≤ | E23: P6 | F23: Quan trọng hơn tỷ lệ tham gia học (ATR) vì đo cam kết thực sự của học viên - vắng có phép vẫn là ổn, vắng không phép mới là cảnh báo thực sự. Tỷ lệ vắng không phép (UAR) cao = nguy cơ bỏ học cao trong 2-3 tuần tới | G23: =HYPERLINK("#'BC2. Chỉ số KPI'!B"&MATCH("UAR",'BC2. Chỉ số KPI'!$B:$B,0),"Mở BC2") -> Mở BC2
A24: ARR | B24: At-Risk Rate (chuyên cần) - Tỷ lệ HV at_risk | C24: 0.1 | D24: ≤ | E24: P6 | F24: Cao liên tục qua nhiều tuần -> vấn đề hệ thống của lớp, không chỉ cá nhân học viên. Phân tích theo: lý do có nguy cơ về chuyên cần (attendance_risk_reason) để tìm điểm chung và tìm nguyên nhân gốc | G24: =HYPERLINK("#'BC2. Chỉ số KPI'!B"&MATCH("ARR",'BC2. Chỉ số KPI'!$B:$B,0),"Mở BC2") -> Mở BC2
A25: AIR | B25: At-Risk Academic Rate - Tỷ lệ HV at_risk học thuật | C25: 0.1 | D25: ≤ | E25: P6 | F25: Chỉ số này đo kỷ luật vận hành của học vụ, không đo kết quả can thiệp. Liên hệ kịp thời chưa đủ - cần đọc cùng tỷ lệ phục hồi sau can thiệp (RCR) để biết can thiệp có hiệu quả không | G25: =HYPERLINK("#'BC2. Chỉ số KPI'!B"&MATCH("AIR",'BC2. Chỉ số KPI'!$B:$B,0),"Mở BC2") -> Mở BC2
A26: RCR | B26: Recovery Rate - Tỷ lệ HV at_risk quay lại on_track | C26: 0.5 | D26: ≥ | E26: P6 | F26: Thấp -> can thiệp chưa đúng cách (chỉ nhắn tin thay vì gọi điện) hoặc nguyên nhân at_risk sâu hơn (tài chính, cá nhân) mà học vụ không giải quyết được một mình | G26: =HYPERLINK("#'BC2. Chỉ số KPI'!B"&MATCH("RCR",'BC2. Chỉ số KPI'!$B:$B,0),"Mở BC2") -> Mở BC2
A27: GCR7 | B27: Grading Completion Rate 7d - BT chấm trong 5 ngày | C27: 1 | D27: ≥ | E27: P7 | F27: Giảng viên chậm chấm -> học viên không biết mình sai ở đâu -> lỗi cũ tiếp tục lặp lại trong bài sau. Đọc cùng tỷ lệ teacher_note đầy đủ (TNR): giảng viên chậm cả chấm bài lẫn ghi nhận xét là dấu hiệu quá tải hoặc thiếu nghiêm túc trong nghiệp vụ | G27: =HYPERLINK("#'BC2. Chỉ số KPI'!B"&MATCH("GCR7",'BC2. Chỉ số KPI'!$B:$B,0),"Mở BC2") -> Mở BC2
A28: WOR | B28: WOW Outcome Rate - Tỷ lệ buổi WOW improved | C28: 0.6 | D28: ≥ | E28: P7 | F28: Thấp -> NV WOW chưa chuẩn bị đúng điểm yếu cần can thiệp, hoặc học viên cần nhiều buổi hơn, hoặc vấn đề học thuật nghiêm trọng hơn mức WOW có thể xử lý một mình | G28: =HYPERLINK("#'BC2. Chỉ số KPI'!B"&MATCH("WOR",'BC2. Chỉ số KPI'!$B:$B,0),"Mở BC2") -> Mở BC2
A29: NER | B29: Negative Feedback Rate - Tỷ lệ FB tiêu cực | C29: 0.15 | D29: ≤ | E29: P8 | F29: NER tăng qua các đợt khảo sát liên tiếp -> vấn đề chưa được giải quyết tận gốc, chỉ đang đối phó bề mặt | G29: =HYPERLINK("#'BC2. Chỉ số KPI'!B"&MATCH("NER",'BC2. Chỉ số KPI'!$B:$B,0),"Mở BC2") -> Mở BC2
A30: CIR | B30: Complaint Incidence Rate - Tỷ lệ HV có KN / tháng | C30: 0.03 | D30: ≤ | E30: P9 | F30: Đọc cùng NER giai đoạn 8: nếu NER cao nhưng CIR thấp -> phần lớn tiêu cực đang được xử lý ổn ở giai đoạn 8. Nếu cả hai cao -> có vấn đề nghiêm trọng chưa được giải quyết | G30: =HYPERLINK("#'BC2. Chỉ số KPI'!B"&MATCH("CIR",'BC2. Chỉ số KPI'!$B:$B,0),"Mở BC2") -> Mở BC2
A31: RR | B31: Resolution Rate - Tỷ lệ KN được resolved + accepted | C31: 0.9 | D31: ≥ | E31: P9 | F31: Thấp -> giải pháp đưa ra chưa thuyết phục hoặc quy trình xử lý chưa phù hợp. Phân tích theo complaint_type để biết nhóm nào khó xử lý nhất và thiếu thẩm quyền gì | G31: =HYPERLINK("#'BC2. Chỉ số KPI'!B"&MATCH("RR",'BC2. Chỉ số KPI'!$B:$B,0),"Mở BC2") -> Mở BC2
A32: CR10 | B32: Course Completion Rate - Tỷ lệ HV hoàn thành khóa | C32: 0.85 | D32: ≥ | E32: P10 | F32: Kết hợp với dropout_reason để tìm nhóm nguyên nhân phổ biến nhất. Tỷ lệ thấp kéo dài liên tục -> cần xem lại toàn bộ quy trình can thiệp sớm ở giai đoạn 6 và 7 | G32: =HYPERLINK("#'BC2. Chỉ số KPI'!B"&MATCH("CR10",'BC2. Chỉ số KPI'!$B:$B,0),"Mở BC2") -> Mở BC2
A33: RER | B33: Re-Enrollment Rate - Tỷ lệ tái ĐK | C33: 0.4 | D33: ≥ | E33: P10 | F33: Chỉ số phản ánh mức độ hài lòng và giá trị cảm nhận của học viên sau khi trải nghiệm toàn bộ khóa học. Thấp không nhất thiết là do dịch vụ kém - có thể học viên đã đạt mục tiêu và không cần học tiếp (đọc cùng AR) | G33: =HYPERLINK("#'BC2. Chỉ số KPI'!B"&MATCH("RER",'BC2. Chỉ số KPI'!$B:$B,0),"Mở BC2") -> Mở BC2
A34: FUR | B34: Follow-up Rate - Tuân thủ lịch follow-up | C34: 0.9 | D34: ≥ | E34: P3 | F34: Thấp -> lead đang bị bỏ lơ dù đã có lịch hẹn. Đây là chỉ số kỷ luật cá nhân của NV tư vấn - quản lý nên xem hàng ngày | G34: =HYPERLINK("#'BC2. Chỉ số KPI'!B"&MATCH("FUR",'BC2. Chỉ số KPI'!$B:$B,0),"Mở BC2") -> Mở BC2
A35: HCR | B35: Homework Completion Rate - Tỷ lệ hoàn thành bài tập | C35: 0.8 | D35: ≥ | E35: P7 | F35: Thấp = học viên không thực hành đủ, một trong những lý cho chính có liên quan chặt chẽ với không đạt mục tiêu và nguy cơ bỏ học. Phân tích kết hợp với Tỷ lệ vắng không phép (UAR) giai đoạn 6: vắng học nhiều + không nộp bài = nguy cơ bỏ học rất cao | G35: =HYPERLINK("#'BC2. Chỉ số KPI'!B"&MATCH("HCR",'BC2. Chỉ số KPI'!$B:$B,0),"Mở BC2") -> Mở BC2
A36: OTR7 | B36: On-Time Rate - Tỷ lệ nộp bài đúng hạn | C36: 0.7 | D36: ≥ | E36: P7 | F36: Tỷ lệ nộp đúng hạn (OTR7) thấp nhưng tỷ lệ hoàn thành bài tập (HCR) cao -> học viên vẫn nộp bài nhưng hay trễ, cần thêm nhắc nhở trước deadline. Cả OTR7 lẫn HCR đều thấp -> học viên không làm bài, xem lại khối lượng, độ khó, không loại trừ thái độ học tập của học viên | G36: =HYPERLINK("#'BC2. Chỉ số KPI'!B"&MATCH("OTR7",'BC2. Chỉ số KPI'!$B:$B,0),"Mở BC2") -> Mở BC2
A37: TNR | B37: Teacher Note Rate - Tỷ lệ teacher_note đầy đủ | C37: 0.9 | D37: ≥ | E37: P7 | F37: Tỷ lệ teacher_note đầy đủ (TNR) thấp -> học vụ không có đủ dữ liệu học thuật để phát hiện học viên yếu và can thiệp đúng lúc. Đây là chỉ số trực tiếp đo chất lượng ghi chép của giảng viên | G37: =HYPERLINK("#'BC2. Chỉ số KPI'!B"&MATCH("TNR",'BC2. Chỉ số KPI'!$B:$B,0),"Mở BC2") -> Mở BC2
A38: ADC | B38: Attendance Discipline - Tuân thủ điểm danh của GV | C38: 0.95 | D38: ≥ | E38: P6 | F38: Thấp -> học vụ không có dữ liệu để phát hiện at_risk kịp thời. Giảng viên quên điểm danh là vi phạm SLA và phải được đưa vào đánh giá hiệu suất hàng tháng | G38: =HYPERLINK("#'BC2. Chỉ số KPI'!B"&MATCH("ADC",'BC2. Chỉ số KPI'!$B:$B,0),"Mở BC2") -> Mở BC2
A39: SPR | B39: Skill Progress Rate - Tiến bộ điểm kỹ năng (mốc 8 tuần) | C39: 0.5 | D39: ≥ | E39: P7 | F39: Chỉ số quan trọng nhất đo chất lượng giảng dạy thực tế. Đọc theo từng kỹ năng: nếu Listening tăng nhưng Writing không tăng -> giảng viên đang tập trung không đều. Đọc cùng Tỷ lệ đạt mục tiêu (AR) giai đoạn 10 | G39: =HYPERLINK("#'BC2. Chỉ số KPI'!B"&MATCH("SPR",'BC2. Chỉ số KPI'!$B:$B,0),"Mở BC2") -> Mở BC2
A40: SS | B40: Satisfaction Score - Điểm hài lòng trung bình | C40: 4.5 | D40: ≥ | E40: P8 | F40: Khi dưới ngưỡng: đừng xem SS tổng - hãy phân tích theo danh mục để biết vấn đề ở đâu (giảng viên? lịch học? dịch vụ?). Một danh mục thấp cần giải pháp khác với nhiều danh mục cùng thấp | G40: =HYPERLINK("#'BC2. Chỉ số KPI'!B"&MATCH("SS",'BC2. Chỉ số KPI'!$B:$B,0),"Mở BC2") -> Mở BC2
A41: SRR | B41: Survey Response Rate - Tỷ lệ phản hồi khảo sát | C41: 0.6 | D41: ≥ | E41: P8 | F41: Thấp = không có đủ dữ liệu để đánh giá trải nghiệm - đang bỏ sót vấn đề tiềm ẩn. Cải thiện bằng cách đơn giản hoá form, gửi đúng thời điểm (ngay sau buổi học), và học vụ nhắc nhở trực tiếp | G41: =HYPERLINK("#'BC2. Chỉ số KPI'!B"&MATCH("SRR",'BC2. Chỉ số KPI'!$B:$B,0),"Mở BC2") -> Mở BC2
A42: FTR | B42: Feedback Time Rate - Xử lý feedback đúng SLA 24h | C42: 1 | D42: ≥ | E42: P8 | F42: Đây là chỉ số kỷ luật vận hành của học vụ. Quản lý nên xem FTR mỗi ngày đầu tuần để đảm bảo không có feedback nào bị bỏ quên | G42: =HYPERLINK("#'BC2. Chỉ số KPI'!B"&MATCH("FTR",'BC2. Chỉ số KPI'!$B:$B,0),"Mở BC2") -> Mở BC2
A43: NPS | B43: Net Promoter Score - Chỉ số giới thiệu | C43: 0.5 | D43: ≥ | E43: P8 | F43: Chỉ số dài hạn phản ánh giá trị thực mà học viên cảm nhận. NPS cao = nguồn referral tự nhiên. Đọc cùng RER giai đoạn 10: NPS cao + RER thấp -> học viên hài lòng nhưng không có nhu cầu tiếp tục (đã đạt mục tiêu) | G43: =HYPERLINK("#'BC2. Chỉ số KPI'!B"&MATCH("NPS",'BC2. Chỉ số KPI'!$B:$B,0),"Mở BC2") -> Mở BC2
A44: SLA_R | B44: SLA Response - Tuân thủ SLA phản hồi khiếu nại đầu | C44: 0.9 | D44: ≥ | E44: P9 | F44: SLA phản hồi đầu tiên quan trọng hơn SLA giải quyết về mặt cảm nhận của học viên - học viên cần biết họ được lắng nghe ngay, dù chưa có giải pháp | G44: =HYPERLINK("#'BC2. Chỉ số KPI'!B"&MATCH("SLA_R",'BC2. Chỉ số KPI'!$B:$B,0),"Mở BC2") -> Mở BC2
A45: CTR | B45: Complaint Time Resolution - TG giải quyết khiếu nại TB | C45: 24 | D45: ≤ | E45: P9 | F45: Đọc theo mức độ: high severity > 24 giờ là vi phạm nghiêm trọng cần báo ban lãnh đạo ngay. medium/low > 72 giờ cũng là vi phạm SLA | G45: =HYPERLINK("#'BC2. Chỉ số KPI'!B"&MATCH("CTR",'BC2. Chỉ số KPI'!$B:$B,0),"Mở BC2") -> Mở BC2
A46: AR | B46: Achievement Rate - Tỷ lệ đạt mục tiêu | C46: 0.7 | D46: ≥ | E46: P10 | F46: Chỉ số quan trọng nhất phản ánh chất lượng đào tạo thực sự. Thấp ở một giảng viên cụ thể -> vấn đề giảng dạy cá nhân. Thấp ở một khóa học -> vấn đề chương trình. Thấp đồng loạt toàn trung tâm -> vấn đề hệ thống | G46: =HYPERLINK("#'BC2. Chỉ số KPI'!B"&MATCH("AR",'BC2. Chỉ số KPI'!$B:$B,0),"Mở BC2") -> Mở BC2
A47: DOR | B47: Dropout Rate - Tỷ lệ bỏ học | C47: 0.1 | D47: ≤ | E47: P10 | F47: Bỏ vì học thuật -> xếp lớp sai trình độ hoặc can thiệp chậm ở giai đoạn 6-7. Bỏ vì tài chính -> vấn đề chính sách học phí hoặc tình huống cá nhân. Bỏ vì dịch vụ -> cần xem lại toàn bộ trải nghiệm vận hành | G47: =HYPERLINK("#'BC2. Chỉ số KPI'!B"&MATCH("DOR",'BC2. Chỉ số KPI'!$B:$B,0),"Mở BC2") -> Mở BC2
A48: RTR | B48: Re-enroll Timely - Tư vấn tái ĐK kịp thời (3 ngày) | C48: 0.9 | D48: ≥ | E48: P10 | F48: Mỗi ngày trễ sau khi kết thúc khóa = học viên nguội dần và bắt đầu tìm kiếm lựa chọn khác. Đọc cùng RER: RTR cao + RER thấp -> có thể vấn đề ở nội dung tư vấn, không phải tốc độ | G48: =HYPERLINK("#'BC2. Chỉ số KPI'!B"&MATCH("RTR",'BC2. Chỉ số KPI'!$B:$B,0),"Mở BC2") -> Mở BC2
A49: TCR | B49: Transfer Comeback Rate - Bảo lưu quay lại học | C49: 0.5 | D49: ≥ | E49: P10 | F49: Thấp -> học vụ không nhắc học viên trước khi hết hạn (SLA: nhắc trước 2 tuần) hoặc nguyên nhân bảo lưu chưa được giải quyết. Đây là cơ hội khôi phục doanh thu đã có sẵn | G49: =HYPERLINK("#'BC2. Chỉ số KPI'!B"&MATCH("TCR",'BC2. Chỉ số KPI'!$B:$B,0),"Mở BC2") -> Mở BC2
A50: WSR | B50: WOW Session Rate - Tỷ lệ buổi WOW hoàn thành | C50: 0.9 | D50: ≥ | E50: P10 | F50: Tỷ lệ buổi WOW hoàn thành (WSR) thấp thường do học viên hủy hoặc không đến - cần xem tỷ lệ vắng mặt ("no_show") và hủy bởi học viên ("cancelled_by_student") để tìm nguyên nhân để phân biệt | G50: =HYPERLINK("#'BC2. Chỉ số KPI'!B"&MATCH("WSR",'BC2. Chỉ số KPI'!$B:$B,0),"Mở BC2") -> Mở BC2
A51: WRR | B51: WOW Recommend Rate - Đề xuất WOW phù hợp | C51: 0.7 | D51: ≥ | E51: P10 | F51: Giảng viên đề xuất WOW đúng học viên, đúng kỹ năng, đúng thời điểm -> WOR cao. Đề xuất tràn lan hoặc không có căn cứ -> WOR thấp và lãng phí quota | G51: =HYPERLINK("#'BC2. Chỉ số KPI'!B"&MATCH("WRR",'BC2. Chỉ số KPI'!$B:$B,0),"Mở BC2") -> Mở BC2

Sheet DL01. Nhân viên
A1: staff_id | B1: full_name | C1: role | D1: department | E1: reports_to | F1: branch | G1: phone | H1: email | I1: start_date | J1: status | K1: notes | L1: reports_to_name
A2: Mã NV | B2: Họ tên đầy đủ | C2: Vai trò (enum) | D2: Phòng ban | E2: Quản lý trực tiếp (link) | F2: Cơ sở | G2: SĐT | H2: Email | I2: Ngày vào làm | J2: Trạng thái | K2: Ghi chú | L2: Tên quản lý (tự hiện)
A3: NV001, NV002... (tự đặt theo thứ tự) | B3: Họ tên đầy đủ, có dấu | C3: Chọn dropdown từ enum_staff_role | D3: Tên phòng ban tiếng Việt | E3: Bấm chọn từ DS NV trên | F3: Chọn dropdown nếu thuộc cơ sở | G3: 10 chữ số, không khoảng trắng | H3: tên.viết_tắt@ieltsthetutors.edu.vn | I3: dd/mm/yyyy | J3: Mặc định = active | K3: Ghi chú thêm | L3: Tự lấy từ DL01
A4: NV001 | B4: Nguyễn Hoàng Anh Kiệt | C4: sales_staff (NV Tư vấn (EC)) | D4: Tư vấn | F4: branch_1 (Cơ sở 1) | G4: 0908000001 | H4: kiet.tv@ieltsthetutors.edu.vn | I4: 45306 | J4: active (Đang làm việc) | K4: Mã HR: SALE.4
A5: NV002 | B5: Nguyễn Văn Thanh Thuyên | C5: sales_staff (NV Tư vấn (EC)) | D5: Tư vấn | F5: branch_2 (Cơ sở 2) | G5: 0908000002 | H5: thuyen.tv@ieltsthetutors.edu.vn | I5: 45323 | J5: active (Đang làm việc) | K5: Mã HR: SALE.6
A6: NV003 | B6: Nguyễn Thanh Kiu | C6: wow_coach (Giáo viên WOW) | D6: ACA | G6: 0908000003 | H6: kiu.wow@ieltsthetutors.edu.vn | I6: 45017 | J6: active (Đang làm việc) | K6: Mã HR: WOW.2
A7: NV004 | B7: Nguyễn Tuấn Phong | C7: wow_coach (Giáo viên WOW) | D7: ACA | G7: 0908000004 | H7: phong.wow@ieltsthetutors.edu.vn | I7: 45108 | J7: active (Đang làm việc) | K7: Mã HR: WOW.3
A8: NV005 | B8: Phan Trung Chính | C8: teacher (Giáo viên ACA) | D8: ACA | G8: 0908000005 | H8: chinh.gv@ieltsthetutors.edu.vn | I8: 44774 | J8: active (Đang làm việc) | K8: Mã HR: ACA.06
A9: NV006 | B9: Phạm Tấn Phát | C9: teacher (Giáo viên ACA) | D9: ACA | G9: 0908000006 | H9: phat.gv@ieltsthetutors.edu.vn | I9: 44941 | J9: active (Đang làm việc) | K9: Mã HR: ACA.07
A10: NV007 | B10: Lê Thị Đức | C10: academic_staff (NV Học vụ / CSKH) | D10: Học vụ | G10: 0908000007 | H10: duc.hv@ieltsthetutors.edu.vn | I10: 45139 | J10: active (Đang làm việc) | K10: Mã HR: HV.2
A11: NV008 | B11: Nguyễn Thị Hồng Thu | C11: academic_staff (NV Học vụ / CSKH) | D11: Học vụ | G11: 0908000008 | H11: thu.hv@ieltsthetutors.edu.vn | I11: 45323 | J11: active (Đang làm việc) | K11: Mã HR: HV.3
A12: NV009 | B12: Nguyễn Lê Minh Chí | C12: ceo (Giám đốc (CEO)) | D12: Ban Giám đốc | G12: 0901000009 | H12: chi.ceo@ieltsthetutors.edu.vn | I12: 43831 | J12: active (Đang làm việc) | K12: Mã HR: CEO.1
A13: NV010 | B13: Phan Thị Hồng Đào | C13: accountant (NV Kế toán) | D13: Kế toán | G13: 0908000010 | H13: dao.kt@ieltsthetutors.edu.vn | I13: 44317 | J13: active (Đang làm việc) | K13: Mã HR: ACC.1
A14: NV011 | B14: Nguyễn Huỳnh Phương Lộc | C14: it_staff (NV IT) | D14: IT | G14: 0908000011 | H14: loc.it@ieltsthetutors.edu.vn | I14: 44866 | J14: active (Đang làm việc) | K14: Mã HR: IT.1
A15: NV012 | B15: Phạm Thị Kim Ngân | C15: sales_manager (Trưởng phòng Tư vấn) | D15: Tư vấn | E15: =IFERROR(HYPERLINK("#'DL01. Nhân viên'!A"&MATCH("NV009",'DL01. Nhân viên'!A:A,0),"NV009"),"NV009") -> NV009 | G15: 0901000012 | H15: ngan.tv@ieltsthetutors.edu.vn | I15: 43891 | J15: active (Đang làm việc) | K15: Mã HR: SALE.1 | L15: =IFERROR(VLOOKUP(E15,'DL01. Nhân viên'!$A:$B,2,FALSE()),"") -> Nguyễn Lê Minh Chí
A16: NV013 | B16: Phạm Thị Mỹ Tiên | C16: academic_manager (Trưởng phòng Học vụ) | D16: Học vụ | E16: =IFERROR(HYPERLINK("#'DL01. Nhân viên'!A"&MATCH("NV009",'DL01. Nhân viên'!A:A,0),"NV009"),"NV009") -> NV009 | G16: 0901000013 | H16: tien.hv@ieltsthetutors.edu.vn | I16: 43952 | J16: active (Đang làm việc) | K16: Mã HR: HV.1 | L16: =IFERROR(VLOOKUP(E16,'DL01. Nhân viên'!$A:$B,2,FALSE()),"") -> Nguyễn Lê Minh Chí
A17: NV014 | B17: Lê Trọng Tín | C17: aca_manager (Trưởng phòng ACA) | D17: ACA | E17: =IFERROR(HYPERLINK("#'DL01. Nhân viên'!A"&MATCH("NV009",'DL01. Nhân viên'!A:A,0),"NV009"),"NV009") -> NV009 | G17: 0901000014 | H17: tin.aca@ieltsthetutors.edu.vn | I17: 43952 | J17: active (Đang làm việc) | K17: Mã HR: ACA.01 | L17: =IFERROR(VLOOKUP(E17,'DL01. Nhân viên'!$A:$B,2,FALSE()),"") -> Nguyễn Lê Minh Chí
A18: NV015 | B18: Đỗ Thành Luân | C18: marketing_manager (Trưởng phòng Marketing) | D18: Marketing | E18: =IFERROR(HYPERLINK("#'DL01. Nhân viên'!A"&MATCH("NV009",'DL01. Nhân viên'!A:A,0),"NV009"),"NV009") -> NV009 | G18: 0901000015 | H18: luan.mkt@ieltsthetutors.edu.vn | I18: 44197 | J18: active (Đang làm việc) | K18: Mã HR: MKT.1 | L18: =IFERROR(VLOOKUP(E18,'DL01. Nhân viên'!$A:$B,2,FALSE()),"") -> Nguyễn Lê Minh Chí
A19: NV016 | B19: Trần Nhật Hào | C19: hr_manager (Trưởng phòng Nhân sự) | D19: Nhân sự | E19: =IFERROR(HYPERLINK("#'DL01. Nhân viên'!A"&MATCH("NV009",'DL01. Nhân viên'!A:A,0),"NV009"),"NV009") -> NV009 | G19: 0901000016 | H19: hao.hr@ieltsthetutors.edu.vn | I19: 44256 | J19: active (Đang làm việc) | K19: Mã HR: HR.1 | L19: =IFERROR(VLOOKUP(E19,'DL01. Nhân viên'!$A:$B,2,FALSE()),"") -> Nguyễn Lê Minh Chí
A20: NV017 | B20: Phan Thị Hồng Đào | C20: accounting_manager (Trưởng phòng Kế toán) | D20: Kế toán | E20: =IFERROR(HYPERLINK("#'DL01. Nhân viên'!A"&MATCH("NV009",'DL01. Nhân viên'!A:A,0),"NV009"),"NV009") -> NV009 | G20: 0901000017 | H20: dao2.kt@ieltsthetutors.edu.vn | I20: 44044 | J20: active (Đang làm việc) | K20: Mã HR: ACC.1 - kiêm nhiệm | L20: =IFERROR(VLOOKUP(E20,'DL01. Nhân viên'!$A:$B,2,FALSE()),"") -> Nguyễn Lê Minh Chí
A21: NV018 | B21: Nguyễn Huỳnh Phương Lộc | C21: it_manager (Trưởng phòng IT) | D21: IT | E21: =IFERROR(HYPERLINK("#'DL01. Nhân viên'!A"&MATCH("NV009",'DL01. Nhân viên'!A:A,0),"NV009"),"NV009") -> NV009 | G21: 0901000018 | H21: loc2.it@ieltsthetutors.edu.vn | I21: 44348 | J21: active (Đang làm việc) | K21: Mã HR: IT.1 - kiêm nhiệm | L21: =IFERROR(VLOOKUP(E21,'DL01. Nhân viên'!$A:$B,2,FALSE()),"") -> Nguyễn Lê Minh Chí
A22: NV020 | B22: Huỳnh Quang Khải | C22: sales_leader (Sale Leader Chi nhánh) | D22: Tư vấn | E22: =IFERROR(HYPERLINK("#'DL01. Nhân viên'!A"&MATCH("NV012",'DL01. Nhân viên'!A:A,0),"NV012"),"NV012") -> NV012 | F22: branch_1 (Cơ sở 1) | G22: 0901000020 | H22: khai.tv@ieltsthetutors.edu.vn | I22: 44287 | J22: active (Đang làm việc) | K22: Mã HR: SALE.2 | L22: =IFERROR(VLOOKUP(E22,'DL01. Nhân viên'!$A:$B,2,FALSE()),"") -> Phạm Thị Kim Ngân
A23: NV021 | B23: Trần Thị Thanh Hà | C23: sales_leader (Sale Leader Chi nhánh) | D23: Tư vấn | E23: =IFERROR(HYPERLINK("#'DL01. Nhân viên'!A"&MATCH("NV012",'DL01. Nhân viên'!A:A,0),"NV012"),"NV012") -> NV012 | F23: branch_2 (Cơ sở 2) | G23: 0901000021 | H23: ha.tv@ieltsthetutors.edu.vn | I23: 44378 | J23: active (Đang làm việc) | K23: Mã HR: SALE.5 | L23: =IFERROR(VLOOKUP(E23,'DL01. Nhân viên'!$A:$B,2,FALSE()),"") -> Phạm Thị Kim Ngân
A24: NV022 | B24: Nguyễn Huỳnh Thanh Phương | C24: sales_leader (Sale Leader Chi nhánh) | D24: Tư vấn | E24: =IFERROR(HYPERLINK("#'DL01. Nhân viên'!A"&MATCH("NV012",'DL01. Nhân viên'!A:A,0),"NV012"),"NV012") -> NV012 | F24: branch_3 (Cơ sở 3) | G24: 0901000022 | H24: phuong.tv@ieltsthetutors.edu.vn | I24: 44562 | J24: active (Đang làm việc) | K24: Mã HR: SALE.7 | L24: =IFERROR(VLOOKUP(E24,'DL01. Nhân viên'!$A:$B,2,FALSE()),"") -> Phạm Thị Kim Ngân
A25: NV023 | B25: Nguyễn Thị Phương Duyên | C25: sales_staff (NV Tư vấn (EC)) | D25: Tư vấn | E25: =IFERROR(HYPERLINK("#'DL01. Nhân viên'!A"&MATCH("NV021",'DL01. Nhân viên'!A:A,0),"NV021"),"NV021") -> NV021 | F25: branch_2 (Cơ sở 2) | G25: 0908000023 | H25: duyen.tv@ieltsthetutors.edu.vn | I25: 45352 | J25: active (Đang làm việc) | K25: Mã HR: SALE.9 | L25: =IFERROR(VLOOKUP(E25,'DL01. Nhân viên'!$A:$B,2,FALSE()),"") -> Trần Thị Thanh Hà
A26: NV024 | B26: Huỳnh Quốc Khánh | C26: sales_staff (NV Tư vấn (EC)) | D26: Tư vấn | E26: =IFERROR(HYPERLINK("#'DL01. Nhân viên'!A"&MATCH("NV022",'DL01. Nhân viên'!A:A,0),"NV022"),"NV022") -> NV022 | F26: branch_3 (Cơ sở 3) | G26: 0908000024 | H26: khanh.tv@ieltsthetutors.edu.vn | I26: 45383 | J26: active (Đang làm việc) | K26: Mã HR: SALE.10 | L26: =IFERROR(VLOOKUP(E26,'DL01. Nhân viên'!$A:$B,2,FALSE()),"") -> Nguyễn Huỳnh Thanh Phương
A27: NV025 | B27: Thái Phạm Tố Trinh | C27: sales_staff (NV Tư vấn (EC)) | D27: Tư vấn | E27: =IFERROR(HYPERLINK("#'DL01. Nhân viên'!A"&MATCH("NV012",'DL01. Nhân viên'!A:A,0),"NV012"),"NV012") -> NV012 | F27: branch_4 (Cơ sở 4) | G27: 0908000025 | H27: trinh.tv@ieltsthetutors.edu.vn | I27: 45413 | J27: inactive (Đã nghỉ việc) | K27: Mã HR: SALE.3 - đã nghỉ | L27: =IFERROR(VLOOKUP(E27,'DL01. Nhân viên'!$A:$B,2,FALSE()),"") -> Phạm Thị Kim Ngân
A28: NV026 | B28: Nguyễn Hoàng Phú | C28: sales_staff (NV Tư vấn (EC)) | D28: Tư vấn | E28: =IFERROR(HYPERLINK("#'DL01. Nhân viên'!A"&MATCH("NV012",'DL01. Nhân viên'!A:A,0),"NV012"),"NV012") -> NV012 | F28: branch_5 (Cơ sở 5) | G28: 0908000026 | H28: phu.tv@ieltsthetutors.edu.vn | I28: 45444 | J28: inactive (Đã nghỉ việc) | K28: Mã HR: SALE.8 - đã nghỉ | L28: =IFERROR(VLOOKUP(E28,'DL01. Nhân viên'!$A:$B,2,FALSE()),"") -> Phạm Thị Kim Ngân
